Workbook

Sheet DoubleClubble
A1: CharltonWestHam | E1: =vlookup(F2,AwayFixtures!$B$1:$C$47,2,FALSE) -> 22-08-2026 | J1: CharltonWatford | N1: =vlookup(O2,AwayFixtures!$B$1:$C$47,2,FALSE) -> 17-10-2026 | S1: CharltonWestBrom | W1: =vlookup(X2,AwayFixtures!$B$1:$C$47,2,FALSE) -> 02-09-2026 | AB1: CharltonStoke | AF1: =vlookup(AG2,AwayFixtures!$B$1:$C$47,2,FALSE) -> 05-09-2026 | AK1: CharltonSouthampton | AO1: =vlookup(AP2,AwayFixtures!$B$1:$C$47,2,FALSE) -> 20-03-2027 | AT1: CharltonSheffUtd | AX1: =vlookup(AY2,AwayFixtures!$B$1:$C$47,2,FALSE) -> 30-01-2027 | BC1: CharltonBirmingham | BG1: =vlookup(BH2,AwayFixtures!$B$1:$C$47,2,FALSE) -> 17-03-2027 | BL1: CharltonBlackburn | BP1: =vlookup(BQ2,AwayFixtures!$B$1:$C$47,2,FALSE) -> 28-11-2026 | BU1: CharltonBolton | BY1: =vlookup(BZ2,AwayFixtures!$B$1:$C$47,2,FALSE) -> 26-01-2027 | CD1: CharltonBristolCity | CH1: =vlookup(CI2,AwayFixtures!$B$1:$C$47,2,FALSE) -> 27-02-2027 | CM1: CharltonBurnley | CQ1: =vlookup(CR2,AwayFixtures!$B$1:$C$47,2,FALSE) -> 13-10-2026 | CV1: CharltonCardiff | CZ1: =vlookup(DA2,AwayFixtures!$B$1:$C$47,2,FALSE) -> 19-09-2026 | DE1: CharltonDerby | DI1: =vlookup(DJ2,AwayFixtures!$B$1:$C$47,2,FALSE) -> 06-02-2027 | DN1: CharltonMillwall | DR1: =vlookup(DS2,AwayFixtures!$B$1:$C$47,2,FALSE) -> 19-12-2026 | DW1: CharltonLincoln | EA1: =vlookup(EB2,AwayFixtures!$B$1:$C$47,2,FALSE) -> 01-05-2027 | EF1: CharltonMiddlesbrough | EJ1: =vlookup(EK2,AwayFixtures!$B$1:$C$47,2,FALSE) -> 31-10-2026 | EO1: CharltonNorwich | ES1: =vlookup(ET2,AwayFixtures!$B$1:$C$47,2,FALSE) -> 29-12-2026 | EX1: CharltonPortsmouth | FB1: =vlookup(FC2,AwayFixtures!$B$1:$C$47,2,FALSE) -> 13-02-2027 | FG1: CharltonPreston | FK1: =vlookup(FL2,AwayFixtures!$B$1:$C$47,2,FALSE) -> 17-04-2027 | FP1: CharltonQPR | FT1: =vlookup(FU2,AwayFixtures!$B$1:$C$47,2,FALSE) -> 06-04-2027 | FY1: CharltonSwansea | GC1: =vlookup(GD2,AwayFixtures!$B$1:$C$47,2,FALSE) -> 01-01-2027 | GH1: CharltonWolves | GL1: =vlookup(GM2,AwayFixtures!$B$1:$C$47,2,FALSE) -> 21-11-2026 | GQ1: CharltonWrexham | GU1: =vlookup(GV2,AwayFixtures!$B$1:$C$47,2,FALSE) -> 08-12-2026 | GZ1: CharltonTottenham | HD1: 25-08-2026
C2: Charlton | F2: West Ham United | L2: Charlton Athletic | O2: Watford | U2: Charlton Athletic | X2: West Bromwich Albion | AD2: Charlton Athletic | AG2: Stoke City | AM2: Charlton Athletic | AP2: Southampton | AV2: Charlton Athletic | AY2: Sheffield United | BE2: Charlton Athletic | BH2: Birmingham City | BN2: Charlton Athletic | BQ2: Blackburn Rovers | BW2: Charlton Athletic | BZ2: Bolton Wanderers | CF2: Charlton Athletic | CI2: Bristol City | CO2: Charlton Athletic | CR2: Burnley | CX2: Charlton Athletic | DA2: Cardiff City | DG2: Charlton Athletic | DJ2: Derby County | DP2: Charlton Athletic | DS2: Millwall | DY2: Charlton Athletic | EB2: Lincoln City | EH2: Charlton Athletic | EK2: Middlesbrough | EQ2: Charlton Athletic | ET2: Norwich City | EZ2: Charlton Athletic | FC2: Portsmouth | FI2: Charlton Athletic | FL2: Preston North End | FR2: Charlton Athletic | FU2: Queens Park Rangers | GA2: Charlton Athletic | GD2: Swansea City | GJ2: Charlton Athletic | GM2: Wolverhampton Wanderers | GS2: Charlton Athletic | GV2: Wrexham | HB2: Charlton Athletic | HE2: Tottenham Hotspur
A3: Players | B3: Position | C3: Years | D3: Played | E3: Scored | F3: Years | G3: Played | H3: Scored | J3: Player | K3: Position | L3: Years | M3: Apps | N3: Goals | O3: Years | P3: Apps | Q3: Goals | S3: Player | T3: Position | U3: Years | V3: Apps | W3: Goals | X3: Years | Y3: Apps | Z3: Goals | AB3: Player | AC3: Position | AD3: Years | AE3: Apps | AF3: Goals | AG3: Years | AH3: Apps | AI3: Goals | AK3: Player | AL3: Position | AM3: Years | AN3: Apps | AO3: Goals | AP3: Years | AQ3: Apps | AR3: Goals | AT3: Player | AU3: Position | AV3: Years | AW3: Apps | AX3: Goals | AY3: Years | AZ3: Apps | BA3: Goals | BC3: Player | BD3: Position | BE3: Years | BF3: Apps | BG3: Goals | BH3: Years | BI3: Apps | BJ3: Goals | BL3: Player | BM3: Position | BN3: Years | BO3: Apps | BP3: Goals | BQ3: Years | BR3: Apps | BS3: Goals | BU3: Player | BV3: Position | BW3: Years | BX3: Apps | BY3: Goals | BZ3: Years | CA3: Apps | CB3: Goals | CD3: Player | CE3: Position | CF3: Years | CG3: Apps | CH3: Goals | CI3: Years | CJ3: Apps | CK3: Goals | CM3: Player | CO3: Years | CP3: Apps | CQ3: Goals | CR3: Years | CS3: Apps | CT3: Goals | CV3: Player | CW3: Position | CX3: Years | CY3: Apps | CZ3: Goals | DA3: Years | DB3: Apps | DC3: Goals | DE3: Player | DF3: Position | DG3: Years | DH3: Apps | DI3: Goals | DJ3: Years | DK3: Apps | DL3: Goals | DN3: Player | DO3: Position | DP3: Years | DQ3: Apps | DR3: Goals | DS3: Years | DT3: Apps | DU3: Goals | DW3: Player | DX3: Position | DY3: Years | DZ3: Apps | EA3: Goals | EB3: Years | EC3: Apps | ED3: Goals | EF3: Player | EG3: Position | EH3: Years | EI3: Apps | EJ3: Goals | EK3: Years | EL3: Apps | EM3: Goals | EO3: Player | EP3: Position | EQ3: Years | ER3: Apps | ES3: Goals | ET3: Years | EU3: Apps | EV3: Goals | EX3: Player | EY3: Position | EZ3: Years | FA3: Apps | FB3: Goals | FC3: Years | FD3: Apps | FE3: Goals | FG3: Player | FH3: Position | FI3: Years | FJ3: Apps | FK3: Goals | FL3: Years | FM3: Apps | FN3: Goals | FP3: Player | FQ3: Position | FR3: Years | FS3: Apps | FT3: Goals | FU3: Years | FV3: Apps | FW3: Goals | FY3: Player | FZ3: Position | GA3: Years | GB3: Apps | GC3: Goals | GD3: Years | GE3: Apps | GF3: Goals | GH3: Player | GI3: Position | GJ3: Years | GK3: Apps | GL3: Goals | GM3: Years | GN3: Apps | GO3: Goals | GQ3: Player | GR3: Position | GS3: Years | GT3: Apps | GU3: Goals | GV3: Years | GW3: Apps | GX3: Goals | GZ3: Player | HA3: Position | HB3: Years | HC3: Apps | HD3: Goals | HE3: Years | HF3: Apps | HG3: Goals
A4: Tal Ben Haim | B4: CB | C4: 2014-2015 | D4: 38 | E4: 0 | F4: 2010 | G4: 8 | H4: 0 | J4: James Abankwah | K4: CB, RB | L4: 2023 | M4: 3 | N4: 0 | O4: 2024-2025 | P4: 51 | Q4: 1 | S4: Krystian Bielik | T4: CDM, CB | U4: 2018 | V4: 31 | W4: 3 | X4: 2025 | Y4: 19 | Z4: 0 | AB4: Jay Bothroyd | AC4: ST | AD4: 2005 | AE4: 18 | AF4: 2 | AG4: 2007 | AH4: 4 | AI4: 0 | AK4: Joe Aribo | AL4: CM | AM4: 2016-2018 | AN4: 85 | AO4: 14 | AP4: 2022-2025 | AQ4: 109 | AR4: 9 | AT4: Marcus Bent | AU4: ST | AV4: 2005-2007 | AW4: 46 | AX4: 4 | AY4: 1999-2010 | AZ4: 59 | BA4: 20 | BC4: Darren Ambrose | BD4: CAM, RM, LM | BE4: 2005-2008 | BF4: 112 | BG4: 13 | BH4: 2012-2013 | BI4: 7 | BJ4: 0 | BL4: Amari'i Bell | BM4: CB, LB | BN4: 2025 | BO4: 35 | BP4: 0 | BQ4: 2017-2020 | BR4: 99 | BS4: 3 | BU4: Ben Alnwick | BV4: GK | BW4: 2013 | BX4: 10 | BY4: 0 | BZ4: 2016-2019 | CA4: 93 | CB4: 0 | CD4: Joe Anyinsah | CE4: ST | CF4: 2010 | CG4: 19 | CH4: 3 | CI4: 2004 | CJ4: 7 | CK4: 0 | CM4: Jóhann Berg Guðmundsson | CN4: LM, RM | CO4: 2014-2015 | CP4: 86 | CQ4: 17 | CR4: 2016-2024 | CS4: 223 | CT4: 15 | CV4: Ben Amos | CW4: GK | CX4: 2017-2020 | CY4: 97 | CZ4: 0 | DA4: 2016 | DB4: 16 | DC4: 0 | DE4: Darren Bent | DF4: ST | DG4: 2005-2006 | DH4: 68 | DI4: 31 | DJ4: 2014-2017 | DK4: 84 | DL4: 28 | DN4: Ben Amos | DO4: GK | DP4: 2017-2020 | DQ4: 97 | DR4: 0 | DS4: 2018 | DT4: 15 | DU4: 0 | DW4: Macauley Bonne | DX4: ST | DY4: 2019-2022 | DZ4: 55 | EA4: 14 | EB4: 2016 | EC4: 8 | ED4: 1 | EF4: Nicky Bailey | EG4: CM | EH4: 2008-2009 | EI4: 87 | EJ4: 25 | EK4: 2010-2012 | EL4: 99 | EM4: 4 | EO4: Ben Alnwick | EP4: GK | EQ4: 2013 | ER4: 10 | ES4: 0 | ET4: 2009 | EU4: 3 | EV4: 0 | EX4: Gassan Ahadme | EY4: ST | EZ4: 2024 | FA4: 22 | FB4: 4 | FC4: 2021 | FD4: 7 | FE4: 0 | FG4: Pawel Abbott | FH4: ST | FI4: 2010 | FJ4: 17 | FK4: 1 | FL4: 2002-2003 | FM4: 25 | FN4: 5 | FP4: Bradley Allen | FQ4: ST | FR4: 1995-1999 | FS4: 40 | FT4: 9 | FU4: 1992-1995 | FV4: 59 | FW4: 20 | FY4: Pawel Abbott | FZ4: ST | GA4: 2010 | GB4: 17 | GC4: 1 | GD4: 2006 | GE4: 18 | GF4: 1 | GH4: Marcus Bent | GI4: ST | GJ4: 2005-2007 | GK4: 46 | GL4: 4 | GM4: 2010 | GN4: 3 | GO4: 0 | GQ4: Joe Anyinsah | GR4: ST | GS4: 2010 | GT4: 19 | GU4: 3 | GV4: 2013 | GW4: 34 | GX4: 4 | GZ4: Ben Alnwick | HA4: GK | HB4: 2013 | HC4: 10 | HD4: 0 | HE4: 2009 | HF4: 1 | HG4: 0
A5: Mark Bowen | B5: LB | C5: 1997-1998 | D5: 42 | E5: 0 | F5: 1996 | G5: 17 | H5: 1 | J5: Dennis Bailey | K5: ST | L5: 1993 | M5: 4 | N5: 0 | O5: 1993 | P5: 8 | Q5: 4 | S5: David Button | T5: GK | U5: 2012 | V5: 5 | W5: 0 | X5: 2020-2022 | Y5: 34 | Z5: 0 | AB5: Deon Burton | AC5: ST | AD5: 2008-2009 | AE5: 59 | AF5: 18 | AG5: 2001 | AH5: 12 | AI5: 2 | AK5: Leon Best | AL5: ST | AM5: 2017 | AN5: 6 | AO5: 0 | AP5: 2004-2006 | AQ5: 11 | AR5: 4 | AT5: Tyler Bindon | AU5: CB | AV5: 2026- | AW5: 2* | AX5: 0* | AY5: 2026 | AZ5: 26 | BA5: 1 | BC5: Chuks Aneke | BD5: ST | BE5: 2019-2024 | BF5: 134 | BG5: 27 | BH5: 2021 | BI5: 21 | BJ5: 2 | BL5: Marcus Bent | BM5: ST | BN5: 2005-2007 | BO5: 46 | BP5: 4 | BQ5: 2000-2001 | BR5: 37 | BS5: 8 | BU5: Ben Amos | BV5: GK | BW5: 2017-2020 | BX5: 97 | BY5: 0 | BZ5: 2014-2016 | CA5: 53 | CB5: 0 | CD5: Tyreeq Bakinson | CE5: CM | CF5: 2023 | CG5: 15 | CH5: 1 | CI5: 2017-2021 | CJ5: 54 | CK5: 5 | CM5: André Bikey | CN5: CB | CO5: 2014 | CP5: 34 | CQ5: 1 | CR5: 2009-2011 | CS5: 70 | CT5: 3 | CV5: Harry Arter | CW5: CM | CX5: 2021 | CY5: 5 | CZ5: 0 | DA5: 2018 | DB5: 25 | DC5: 0 | DE5: Leon Best | DF5: ST | DG5: 2017 | DH5: 6 | DI5: 0 | DJ5: 2014 | DK5: 20 | DL5: 1 | DN5: Nicky Bailey | DO5: CM | DP5: 2008-2009 | DQ5: 87 | DR5: 25 | DS5: 2013-2014 | DT5: 36 | DU5: 1 | DW5: Conor Coventry | DX5: CM | DY5: 2023-2025 | DZ5: 106 | EA5: 1 | EB5: 2019 | EC5: 7 | ED5: 0 | EF5: Marcus Bent | EG5: ST | EH5: 2005-2007 | EI5: 46 | EJ5: 4 | EK5: 2009 | EL5: 7 | EM5: 0 | EO5: Mark Bowen | EP5: LB | EQ5: 1997-1998 | ER5: 42 | ES5: 0 | ET5: 1992-1995 | EU5: 156 | EV5: 11 | EX5: Millenic Alli | EY5: LW, RW | EZ5: 2026- | FA5: 4* | FB5: 0* | FC5: 2026 | FD5: 21 | FE5: 1 | FG5: Chuks Aneke | FH5: ST | FI5: 2019-2024 | FJ5: 134 | FK5: 27 | FL5: 2011 | FM5: 7 | FN5: 1 | FP5: Dennis Bailey | FQ5: ST | FR5: 1993 | FS5: 4 | FT5: 0 | FU5: 1992 | FV5: 15 | FW5: 1 | FY5: Federico Bessone | FZ5: LB | GA5: 2010 | GB5: 13 | GC5: 0 | GD5: 2008-2011 | GE5: 37 | GF5: 1 | GH5: Jay Bothroyd | GI5: ST | GJ5: 2005 | GK5: 18 | GL5: 2 | GM5: 2006-2007 | GN5: 55 | GO5: 12 | GQ5: Andrew Crofts | GR5: CM | GS5: 2016-2017 | GT5: 50 | GU5: 1 | GV5: 2008 | GW5: 16 | GX5: 1 | GZ5: Darren Bent | HA5: ST | HB5: 2005-2006 | HC5: 68 | HD5: 31 | HE5: 2007-2008 | HF5: 74 | HG5: 24
A6: Lee Bowyer | B6: CM | C6: 1993-1996 | D6: 46 | E6: 8 | F6: 2002-2008 | G6: 53 | H6: 4 | J6: Hameur Bouazza | K6: LM, RM | L6: 2008 | M6: 25 | N6: 4 | O6: 2003-2006 | P6: 83 | Q6: 8 | S6: Scott Carson | T6: GK | U6: 2006 | V6: 36 | W6: 0 | X6: 2008-2010 | Y6: 110 | Z6: 0 | AB6: Harry Clarke | AC6: CB, RB | AD6: 2025 | AE6: 19 | AF6: 0 | AG6: 2022 | AH6: 20 | AI6: 2 | AK6: James Bree | AL6: RB | AM6: 2025 | AN6: 22 | AO6: 2 | AP6: 2022-2025 | AQ6: 76 | AR6: 7 | AT6: Jamal Campbell-Ryce | AU6: RM | AV6: 2002-2003 | AW6: 3 | AX6: 0 | AY6: 2014-2015 | AZ6: 49 | BA6: 6 | BC6: Amari'i Bell | BD6: CB, LB | BE6: 2025 | BF6: 35 | BG6: 0 | BH6: 2013 | BI6: 1 | BJ6: 0 | BL6: Leon Best | BM6: ST | BN6: 2017 | BO6: 6 | BP6: 0 | BQ6: 2012-2013 | BR6: 14 | BS6: 2 | BU6: Rob Apter | BV6: RW, RWB | BW6: 2025 | BX6: 13 | BY6: 1 | BZ6: 2025 | CA6: 13 | CB6: 0 | CD6: André Bikey | CE6: CB | CF6: 2014 | CG6: 34 | CH6: 1 | CI6: 2011 | CJ6: 7 | CK6: 0 | CM6: Nathaniel Chalobah | CN6: CM | CO6: 2026- | CP6: 3* | CQ6: 0* | CR6: 2014-2015 | CS6: 4 | CT6: 0 | CV6: Mickey Bennett | CW6: MF | CX6: 1993-1995 | CY6: 24 | CZ6: 1 | DA6: 1996 | DB6: 14 | DC6: 1 | DE6: Krystian Bielik | DF6: CDM, CB | DG6: 2018 | DH6: 31 | DI6: 3 | DJ6: 2019-2021 | DK6: 53 | DL6: 3 | DN6: Federico Bessone | DO6: LB | DP6: 2010 | DQ6: 13 | DR6: 0 | DS6: 2013 | DT6: 2 | DU6: 0 | DW6: Tayo Edun | DX6: LB | DY6: 2023-2024 | DZ6: 31 | EA6: 0 | EB6: 2019-2021 | EC6: 55 | ED6: 3 | EF6: André Bikey | EG6: CB | EH6: 2014 | EI6: 34 | EJ6: 1 | EK6: 2012 | EL6: 33 | EM6: 1 | EO6: Andrew Crofts | EP6: CM | EQ6: 2016-2017 | ER6: 50 | ES6: 1 | ET6: 2010-2011 | EU6: 68 | EV6: 8 | EX6: Tal Ben Haim | EY6: CB | EZ6: 2014 | FA6: 38 | FB6: 0 | FC6: 2009-2011 | FD6: 55 | FE6: 0 | FG6: Joe Anyinsah | FH6: ST | FI6: 2010 | FJ6: 19 | FK6: 3 | FL6: 2006 | FM6: 3 | FN6: 0 | FP6: Tal Ben Haim | FQ6: CB | FR6: 2014 | FS6: 38 | FT6: 0 | FU6: 2012 | FV6: 3 | FW6: 0 | FY6: Conor Gallagher | FZ6: CM | GA6: 2019 | GB6: 26 | GC6: 6 | GD6: 2019 | GE6: 19 | GF6: 0 | GH6: Nathan Byrne | GI6: RB, RW | GJ6: 2016 | GK6: 17 | GL6: 1 | GM6: 2015 | GN6: 24 | GO6: 2 | GQ6: George Dobson | GR6: CM | GS6: 2021-2023 | GT6: 139 | GU6: 5 | GV6: 2024-2025 | GW6: 90 | GX6: 3 | GZ6: Gary Doherty | HA6: CB | HB6: 2010-2011 | HC6: 41 | HD6: 0 | HE6: 1999-2004 | HF6: 64 | HG6: 4
A7: Reece Burke | B7: CB | C7: 2025 | D7: 17 | E7: 1 | F7: 2014-2017 | G7: 9 | H7: 1 | J7: Nathaniel Chalobah | K7: CM | L7: 2026- | M7: 3* | N7: 0 | O7: 2012-2013, 2017-2021 | P7: 127 | Q7: 9 | S7: Nathaniel Chalobah | T7: CM | U7: 2026- | V7: 3* | W7: 0* | X7: 2022-2024 | Y7: 49 | Z7: 1 | AB7: Leon Cort | AC7: CB | AD7: 2011-2013 | AE7: 48 | AF7: 2 | AG7: 2007-2008 | AH7: 44 | AI7: 8 | AK7: Danny Butterfield | AL7: RB | AM7: 2008 | AN7: 12 | AO7: 0 | AP7: 2010-2011 | AQ7: 44 | AR7: 0 | AT7: Billy Clarke | AU7: ST, CAM | AV7: 2017-2018 | AW7: 23 | AX7: 2 | AY7: 2011 | AZ7: 5 | BA7: 1 | BC7: Marcus Bent | BD7: ST | BE7: 2005-2007 | BF7: 46 | BG7: 4 | BH7: 2008 | BI7: 33 | BJ7: 3 | BL7: Jay Bothroyd | BM7: ST | BN7: 2005 | BO7: 18 | BP7: 2 | BQ7: 2004 | BR7: 11 | BS7: 1 | BU7: Anthony Barness | BV7: LB | BW7: 1992-1999 | BX7: 101 | BY7: 3 | BZ7: 2000-2004 | CA7: 93 | CB7: 0 | CD7: Jamal Campbell-Ryce | CE7: RM | CF7: 2002-2003 | CG7: 3 | CH7: 0 | CI7: 2009-2011 | CJ7: 62 | CK7: 2 | CM7: Leon Cort | CN7: CB | CO7: 2011-2013 | CP7: 48 | CQ7: 2 | CR7: 2009-2010 | CS7: 19 | CT7: 0 | CV7: Omar Bogle | CW7: ST | CX7: 2020 | CY7: 17 | CZ7: 2 | DA7: 2017-2019 | DB7: 24 | DC7: 4 | DE7: Corey Blackett-Taylor | DF7: LW | DG7: 2021-2023 | DH7: 90 | DI7: 18 | DJ7: 2023-2025 | DK7: 35 | DL7: 1 | DN7: Hameur Bouazza | DO7: LM, RM | DP7: 2008 | DQ7: 25 | DR7: 4 | DS7: 2010-2011 | DT7: 38 | DU7: 3 | DW7: Lewis Fiorini | DX7: CAM | DY7: 2023 | DZ7: 5 | EA7: 0 | EB7: 2021 | EC7: 41 | ED7: 6 | EF7: Nathaniel Chalobah | EG7: CM | EH7: 2026- | EI7: 3* | EJ7: 0* | EK7: 2013-2014 | EL7: 19 | EM7: 1 | EO7: Gary Doherty | EP7: CB | EQ7: 2010-2011 | ER7: 41 | ES7: 0 | ET7: 2004-2009 | EU7: 202 | EV7: 11 | EX7: Paul Benson | EY7: ST | EZ7: 2010-2011 | FA7: 33 | FB7: 10 | FC7: 2012 | FD7: 7 | FE7: 2 | FG7: Patrick Bauer | FH7: CB | FI7: 2015-2018 | FJ7: 129 | FK7: 8 | FL7: 2019-2024 | FM7: 105 | FN7: 8 | FP7: Marcus Bent | FQ7: ST | FR7: 2005-2007 | FS7: 46 | FT7: 4 | FU7: 2009 | FV7: 3 | FW7: 0 | FY7: Mark Gower | FZ7: CM | GA7: 2012-2013 | GB7: 13 | GC7: 0 | GD7: 2008-2012 | GE7: 128 | GF7: 3 | GH7: Chem Campbell | GI7: RW, LW | GJ7: 2023 | GK7: 14 | GL7: 2 | GM7: 2019-2023 | GN7: 57 | GO7: 13 | GQ7: Elliot Lee | GR7: CAM | GS7: 2021 | GT7: 37 | GU7: 3 | GV7: 2022-2025 | GW7: 145 | GX7: 39 | GZ7: Conor Gallagher | HA7: CM | HB7: 2019 | HC7: 26 | HD7: 6 | HE7: 2025 | HF7: 18 | HG7: 1
A8: Carlton Cole | B8: ST | C8: 2003 | D8: 21 | E8: 4 | F8: 2006-2014 | G8: 261 | H8: 56 | J8: Lee Cook | K8: LM | L8: 2007-2011 | M8: 13 | N8: 0 | O8: 2000-2003 | P8: 59 | Q8: 7 | S8: Sam Field | T8: CM | U8: 2019 | V8: 18 | W8: 0 | X8: 2015-2020 | Y8: 56 | Z8: 2 | AB8: Jordan Cousins | AC8: CM, RB | AD8: 2013-2015 | AE8: 131 | AF8: 7 | AG8: 2019-2020 | AH8: 47 | AI8: 0 | AK8: Martin Cranie | AL8: RB | AM8: 2008 | AN8: 19 | AO8: 0 | AP8: 2004-2005 | AQ8: 14 | AR8: 0 | AT8: Harry Clarke | AU8: CB, RB | AV8: 2025 | AW8: 19 | AX8: 0 | AY8: 2024 | AZ8: 6 | BA8: 0 | BC8: Krystian Bielik | BD8: CDM, CB | BE8: 2018 | BF8: 31 | BG8: 3 | BH8: 2016-2025 | BI8: 122 | BJ8: 2 | BL8: Christian Dailly | BM8: CB | BN8: 2009-2010 | BO8: 76 | BP8: 1 | BQ8: 1998-2000 | BR8: 72 | BS8: 4 | BU8: Tal Ben Haim | BV8: CB | BW8: 2014 | BX8: 38 | BY8: 0 | BZ8: 2004-2006 | CA8: 95 | CB8: 1 | CD8: Jay Dasilva | CE8: LB | CF8: 2016-2017 | CG8: 51 | CH8: 0 | CI8: 2018-2022 | CJ8: 144 | CK8: 2 | CM8: Josh Cullen | CN8: CM | CO8: 2018-2019 | CP8: 63 | CQ8: 2 | CR8: 2022-2025 | CS8: 140 | CT8: 7 | CV8: Jay Bothroyd | CW8: ST | CX8: 2005 | CY8: 18 | CZ8: 2 | DA8: 2008-2010 | DB8: 116 | DC8: 41 | DE8: Deon Burton | DF8: ST | DG8: 2008-2009 | DH8: 59 | DI8: 18 | DJ8: 1997-2002 | DK8: 125 | DL8: 25 | DN8: Allan Campbell | DO8: CM | DP8: 2024 | DQ8: 14 | DR8: 0 | DS8: 2023 | DT8: 12 | DU8: 0 | DW8: Reeco Hackett-Fairchild | DX8: LW, ST | DY8: 2017-2018 | DZ8: 12 | EA8: 0 | EB8: 2023-2025 | EC8: 111 | ED8: 22 | EF8: Martin Cranie | EG8: CB, RB | EH8: 2008 | EI8: 19 | EJ8: 0 | EK8: 2017 | EL8: 9 | EM8: 0 | EO8: Akin Famewo | EP8: CB | EQ8: 2020-2021 | ER8: 61 | ES8: 1 | ET8: 2018-2020 | EU8: 12 | EV8: 1 | EX8: Omar Bogle | EY8: ST | EZ8: 2020 | FA8: 17 | FB8: 2 | FC8: 2018 | FD8: 12 | FE8: 5 | FG8: Leon Clarke | FH8: ST | FI8: 2011 | FJ8: 7 | FK8: 0 | FL8: 2010 | FM8: 6 | FN8: 1 | FP8: Leon Best | FQ8: ST | FR8: 2017 | FS8: 6 | FT8: 0 | FU8: 2004 | FV8: 5 | FW8: 0 | FY8: Ben Hamer | FZ8: GK | GA8: 2011-2013 | GB8: 114 | GC8: 0 | GD8: 2020-2021 | GE8: 23 | GF8: 0 | GH8: Leon Clarke | GI8: ST | GJ8: 2011 | GK8: 7 | GL8: 0 | GM8: 2004-2014 | GN8: 90 | GO8: 11 | GQ8: Harry Lennon | GR8: CB | GS8: 2013-2017 | GT8: 35 | GU8: 2 | GV8: 2021-2022 | GW8: 19 | GX8: 2 | GZ8: Chris Gunter | HA8: RB | HB8: 2020-2021 | HC8: 56 | HD8: 1 | HE8: 2007-2008 | HF8: 12 | HG8: 0
A9: Conor Coventry | B9: CM | C9: 2023-2025 | D9: 106 | E9: 1 | F9: 2017-2023 | G9: 75 | H9: 8 | J9: Chris Eagles | K9: RW, LW | L9: 2014 | M9: 15 | N9: 2 | O9: 2004-2005 | P9: 30 | Q9: 4 | S9: Conor Gallagher | T9: CM | U9: 2019 | V9: 26 | W9: 6 | X9: 2020 | Y9: 32 | Z9: 2 | AB9: Alfie Doughty | AC9: LB, LW | AD9: 2018-2020 | AE9: 40 | AF9: 3 | AG9: 2021 | AH9: 17 | AI9: 0 | AK9: Christian Dailly | AL9: CB | AM9: 2009-2010 | AN9: 76 | AO9: 1 | AP9: 2007 | AQ9: 11 | AR9: 0 | AT9: Leon Clarke | AU9: ST | AV9: 2011 | AW9: 7 | AX9: 0 | AY9: 2016-2019 | AZ9: 95 | BA9: 31 | BC9: Omar Bogle | BD9: ST | BE9: 2020 | BF9: 17 | BG9: 2 | BH9: 2018 | BI9: 16 | BJ9: 1 | BL9: Tayo Edun | BM9: LB | BN9: 2023-2024 | BO9: 31 | BP9: 0 | BQ9: 2021-2022 | BR9: 41 | BS9: 0 | BU9: Corey Blackett-Taylor | BV9: LW | BW9: 2021-2023 | BX9: 90 | BY9: 18 | BZ9: 2025 | CA9: 7 | CB9: 2 | CD9: Hogan Ephraim | CE9: LW | CF9: 2011 | CG9: 5 | CH9: 1 | CI9: 2011 | CJ9: 5 | CK9: 1 | CM9: Chris Eagles | CN9: RW, LW | CO9: 2014 | CP9: 15 | CQ9: 2 | CR9: 2008-2010 | CS9: 120 | CT9: 20 | CV9: Deon Burton | CW9: ST | CX9: 2008-2009 | CY9: 59 | CZ9: 18 | DA9: 1996 | DB9: 5 | DC9: 2 | DE9: Nathan Byrne | DF9: RB, RW | DG9: 2016 | DH9: 17 | DI9: 1 | DJ9: 2020-2021 | DK9: 82 | DL9: 0 | DN9: Alfie Doughty | DO9: LB, LW | DP9: 2018-2020 | DQ9: 40 | DR9: 3 | DS9: 2025 | DT9: 26 | DU9: 0 | DW9: Mark McCammon | DX9: ST | DY9: 1999 | DZ9: 4 | EA9: 0 | EB9: 2011-2012 | EC9: 8 | ED9: 2 | EF9: Anfernee Dijksteel | EG9: RB | EH9: 2016-2019 | EI9: 48 | EJ9: 1 | EK9: 2019-2024 | EL9: 170 | EM9: 3 | EO9: Sam Field | EP9: CM | EQ9: 2019 | ER9: 18 | ES9: 0 | ET9: 2025 | EU9: 15 | EV9: 0 | EX9: Deon Burton | EY9: ST | EZ9: 2008-2009 | FA9: 59 | FB9: 18 | FC9: 1993-2003 | FD9: 78 | FE9: 14 | FG9: Leon Cort | FH9: CB | FI9: 2011-2013 | FJ9: 48 | FK9: 2 | FL9: 2010 | FM9: 13 | FN9: 0 | FP9: Macauley Bonne | FQ9: ST | FR9: 2019-2022 | FS9: 55 | FT9: 14 | FU9: 2020-2022 | FV9: 44 | FW9: 3 | FY9: Leroy Lita | FZ9: ST | GA9: 2007 | GB9: 8 | GC9: 3 | GD9: 2011-2013 | GE9: 18 | GF9: 2 | GH9: Conor Coady | GI9: CB, CDM | GJ9: 2025 | GK9: 12 | GL9: 1 | GM9: 2015-2022 | GN9: 311 | GO9: 7 | GQ9: Izale McLeod | GR9: ST | GS9: 2007-2009 | GT9: 31 | GU9: 3 | GV9: 2016 | GW9: 15 | GX9: 1 | GZ9: Johnnie Jackson | HA9: LM/CM/LB | HB9: 2009-2017 | HC9: 256 | HD9: 52 | HE9: 2003-2005 | HF9: 20 | HG9: 1
A10: Josh Cullen | B10: CM | C10: 2018-2019 | D10: 63 | E10: 2 | F10: 2014-2020 | G10: 10 | H10: 1 | J10: Rob Elliot | K10: GK | L10: 2007-2011 | M10: 96 | N10: 0 | O10: 2020-2021 | P10: 1 | Q10: 0 | S10: Karlan Grant | T10: ST | U10: 2014-2018, 2026- | V10: 95* | W10: 20* | X10: 2020-2025 | Y10: 174 | Z10: 35 | AB10: Amdy Faye | AC10: CDM | AD10: 2006-2007 | AE10: 29 | AF10: 1 | AG10: 2008 | AH10: 21 | AI10: 0 | AK10: Jason Euell | AL10: ST | AM10: 2001-2011 | AN10: 150 | AO10: 34 | AP10: 2007-2008 | AQ10: 62 | AR10: 5 | AT10: Conor Coady | AU10: CB, CDM | AV10: 2025 | AW10: 12 | AX10: 1 | AY10: 2013 | AZ10: 39 | BA10: 5 | BC10: Hameur Bouazza | BD10: LM, RM | BE10: 2008 | BF10: 25 | BG10: 4 | BH10: 2008 | BI10: 16 | BJ10: 1 | BL10: Keith Gillespie | BM10: RM | BN10: 2008 | BO10: 6 | BP10: 0 | BQ10: 1998-2002 | BR10: 116 | BS10: 5 | BU10: Reece Burke | BV10: CB | BW10: 2025 | BX10: 17 | BY10: 1 | BZ10: 2017 | CA10: 26 | CB10: 1 | CD10: Ben Hamer | CE10: GK | CF10: 2011-2013 | CG10: 114 | CH10: 0 | CI10: 2015 | CJ10: 5 | CK10: 0 | CM10: Andy Gray | CN10: ST | CO10: 2007-2009 | CP10: 45 | CQ10: 9 | CR10: 2005-2007 | CS10: 70 | CT10: 29 | CV10: Alfie Doughty | CW10: LB, LW | CX10: 2018-2020 | CY10: 40 | CZ10: 3 | DA10: 2021 | DB10: 9 | DC10: 1 | DE10: Scott Carson | DF10: GK | DG10: 2006 | DH10: 36 | DI10: 0 | DJ10: 2015-2018 | DK10: 167 | DL10: 0 | DN10: Ricardo Fuller | DO10: ST | DP10: 2012 | DQ10: 31 | DR10: 5 | DS10: 2014 | DT10: 40 | DU10: 6 | DW10: Conor McGrandles | DX10: CM | DY10: 2022-2023 | DZ10: 16 | EA10: 1 | EB10: 2020-2025 | EC10: 184 | ED10: 9 | EF10: Jason Euell | EG10: ST | EH10: 2001-2011 | EI10: 150 | EJ10: 34 | EK10: 2006 | EL10: 17 | EM10: 0 | EO10: Onel Hernández | EP10: LW, RW | EQ10: 2025 | ER10: 6 | ES10: 0 | ET10: 2017-2024 | EU10: 210 | EV10: 15 | EX10: Martin Cranie | EY10: CB, RB | EZ10: 2008 | FA10: 19 | FB10: 0 | FC10: 2007 | FD10: 2 | FE10: 0 | FG10: Ricardo Fuller | FH10: ST | FI10: 2012 | FJ10: 31 | FK10: 5 | FL10: 2002-2004 | FM10: 58 | FN10: 27 | FP10: Gary Borrowdale | FQ10: LB | FR10: 2009 | FS10: 10 | FT10: 0 | FU10: 2009-2010 | FV10: 22 | FW10: 0 | FY10: Frank Nouble | FZ10: ST | GA10: 2010 | GB10: 9 | GC10: 1 | GD10: 2010 | GE10: 6 | GF10: 1 | GH10: Carlton Cole | GI10: ST | GJ10: 2003 | GK10: 21 | GL10: 4 | GM10: 2002 | GN10: 7 | GO10: 1 | GQ10: Eoghan O'Connell | GR10: CB | GS10: 2022 | GT10: 22 | GU10: 1 | GV10: 2022-2025 | GW10: 90 | GX10: 2 | GZ10: Paul Konchesky | HA10: LB/LM | HB10: 1997-2004 | HC10: 149 | HD10: 5 | HE10: 2003 | HF10: 12 | HG10: 0
A11: Christian Dailly | B11: CB | C11: 2009-2010 | D11: 76 | E11: 1 | F11: 2000-2006 | G11: 158 | H11: 2 | J11: Ben Hamer | K11: GK | L11: 2011-2013 | M11: 114 | N11: 0 | O11: 2022-2023 | P11: 22 | Q11: 0 | S11: Robert Hulse | T11: ST | U11: 2012 | V11: 15 | W11: 3 | X11: 2003-2004 | Y11: 38 | Z11: 10 | AB11: Jonathan Fortune | AC11: CB | AD11: 1999-2010 | AE11: 182 | AF11: 6 | AG11: 2006 | AH11: 14 | AI11: 1 | AK11: Ricardo Fuller | AL11: ST | AM11: 2012 | AN11: 31 | AO11: 5 | AP11: 2005 | AQ11: 30 | AR11: 9 | AT11: Martin Cranie | AU11: RB | AV11: 2008 | AW11: 19 | AX11: 0 | AY11: 2018 | AZ11: 16 | BA11: 0 | BC11: Lee Bowyer | BD11: CM, RM | BE11: 1993-1996 | BF11: 46 | BG11: 8 | BH11: 2008-2010 | BI11: 81 | BJ11: 10 | BL11: Matty Holmes | BM11: LM | BN11: 1997-1999 | BO11: 16 | BP11: 1 | BQ11: 1995 | BR11: 12 | BS11: 1 | BU11: Mason Burstow | BV11: ST | BW11: 2021 | BX11: 18 | BY11: 3 | BZ11: 2025 | CA11: 48 | CB11: 12 | CD11: Danny Haynes | CE11: ST | CF11: 2011-2012 | CG11: 34 | CH11: 9 | CI11: 2009-2010 | CJ11: 51 | CK11: 8 | CM11: Chris Iwelumo | CN11: ST | CO11: 2007 | CP11: 46 | CQ11: 10 | CR11: 2010 | CS11: 45 | CT11: 11 | CV11: Neil Etheridge | CW11: GK | CX11: 2014 | CY11: 5 | CZ11: 0 | DA11: 2017-2020 | DB11: 102 | DC11: 0 | DE11: Christian Dailly | DF11: CB | DG11: 2009-2010 | DH11: 76 | DI11: 1 | DJ11: 1996-1998 | DK11: 67 | DL11: 4 | DN11: Danny Haynes | DO11: ST | DP11: 2011-2012 | DQ11: 34 | DR11: 9 | DS11: 2006 | DT11: 5 | DU11: 2 | DW11: Alex Mitchell | DX11: CB | DY11: 2024-2025 | DZ11: 35 | EA11: 2 | EB11: 2023 | EC11: 38 | ED11: 1 | EF11: Jimmy Floyd Hasselbaink | EG11: ST | EH11: 2006 | EI11: 25 | EJ11: 2 | EK11: 2004-2005 | EL11: 78 | EM11: 29 | EO11: Andrew Hughes | EP11: CM, RB | EQ11: 2011-2013 | ER11: 28 | ES11: 0 | ET11: 2005-2006 | EU11: 72 | EV11: 2 | EX11: Christian Dailly | EY11: CB | EZ11: 2009-2010 | FA11: 76 | FB11: 1 | FC11: 2011 | FD11: 1 | FE11: 0 | FG11: André Green | FH11: LW, RW, ST | FI11: 2019 | FJ11: 14 | FK11: 2 | FL11: 2019 | FM11: 6 | FN11: 1 | FP11: Jay Bothroyd | FQ11: ST | FR11: 2005 | FS11: 18 | FT11: 2 | FU11: 2011-2012 | FV11: 25 | FW11: 3 | FY11: Darren Pratley | FZ11: CM | GA11: 2018-2020 | GB11: 107 | GC11: 5 | GD11: 2006-2010 | GE11: 177 | GF11: 26 | GH11: David Davis | GI11: CM | GJ11: 2019 | GK11: 5 | GL11: 0 | GM11: 2011-2013 | GN11: 53 | GO11: 0 | GQ11: Arthur Okonkwo | GR11: GK | GS11: 2026- | GT11: 3* | GU11: 0* | GV11: 2023-2026 | GW11: 121 | GX11: 0 | GZ11: Danny Murphy | HA11: CM | HB11: 2004-2005 | HC11: 56 | HD11: 7 | HE11: 2005-2006 | HF11: 25 | HG11: 1
A12: Paolo Di Canio | B12: ST | C12: 2003 | D12: 31 | E12: 4 | F12: 1998-2002 | G12: 122 | H12: 49 | J12: Chris Iwelumo | K12: ST | L12: 2007 | M12: 46 | N12: 10 | O12: 2011-2012 | P12: 46 | Q12: 4 | S12: Andy Hunt | T12: ST | U12: 1998-2000 | V12: 86 | W12: 34 | X12: 1992-1997 | Y12: 212 | Z12: 76 | AB12: Tariqe Fosu | AC12: LW, RW | AD12: 2017-2018 | AE12: 61 | AF12: 11 | AG12: 2022 | AH12: 20 | AI12: 0 | AK12: Neil Heaney | AL12: LW | AM12: 1997 | AN12: 6 | AO12: 0 | AP12: 1993-1996 | AQ12: 61 | AR12: 5 | AT12: Jonathan Fortune | AU12: CB | AV12: 1999-2010 | AW12: 182 | AX12: 6 | AY12: 2009 | AZ12: 5 | BA12: 1 | BC12: Juan Castillo | BD12: LB | BE12: 2021 | BF12: 2 | BG12: 0 | BH12: 2021 | BI12: 9 | BJ12: 1 | BL12: Francis Jeffers | BM12: ST | BN12: 2004 | BO12: 20 | BP12: 3 | BQ12: 2006 | BR12: 13 | BS12: 1 | BU12: Danny Butterfield | BV12: RB | BW12: 2008 | BX12: 12 | BY12: 0 | BZ12: 2012 | CA12: 6 | CB12: 0 | CD12: Stephen Henderson | CE12: GK | CF12: 2014-2021 | CG12: 59 | CH12: 0 | CI12: 2007-2009 | CJ12: 5 | CK12: 0 | CM12: Ian Maatsen | CN12: LB | CO12: 2020 | CP12: 35 | CQ12: 1 | CR12: 2022 | CS12: 42 | CT12: 4 | CV12: Jimmy Floyd Hasselbaink | CW12: ST | CX12: 2006 | CY12: 25 | CZ12: 2 | DA12: 2007 | DB12: 36 | DC12: 7 | DE12: Ben Hamer | DF12: GK | DG12: 2011-2013 | DH12: 114 | DI12: 0 | DJ12: 2019 | DK12: 27 | DL12: 0 | DN12: Robert Hulse | DO12: ST | DP12: 2012 | DQ12: 15 | DR12: 3 | DS12: 2012 | DT12: 11 | DU12: 0 | DW12: Dany N'Guessan | DX12: LM, RM | DY12: 2011 | DZ12: 7 | EA12: 4 | EB12: 2006-2008 | EC12: 91 | ED12: 16 | EF12: Alexander Gilbert | EG12: CM | EH12: 2024 | EI12: 12 | EJ12: 0 | EK12: 2023-2025 | EL12: 49 | EM12: 4 | EO12: Matt Jackson | EP12: CB | EQ12: 1995 | ER12: 8 | ES12: 0 | ET12: 1996-2000 | EU12: 161 | EV12: 6 | EX12: Amdy Faye | EY12: CDM | EZ12: 2006-2007 | FA12: 29 | FB12: 1 | FC12: 2003-2004 | FD12: 47 | FE12: 0 | FG12: Paul Hayes | FH12: ST | FI12: 2011 | FJ12: 19 | FK12: 3 | FL12: 2010 | FM12: 23 | FN12: 2 | FP12: Leon Clarke | FQ12: ST | FR12: 2011 | FS12: 7 | FT12: 0 | FU12: 2010 | FV12: 13 | FW12: 0 | FY12: Jonjo Shelvey | FZ12: CAM | GA12: 2007-2009 | GB12: 42 | GC12: 7 | GD12: 2013-2015 | GE12: 92 | GF12: 10 | GH12: Kevin Foley | GI12: CM | GJ12: 2016 | GK12: 18 | GL12: 0 | GM12: 2007-2013 | GN12: 193 | GO12: 5 | GZ12: Jonathan Obika | HA12: ST | HB12: 2012-2013 | HC12: 22 | HD12: 3 | HE12: 2008 | HF12: 2 | HG12: 0
A13: Alou Diarra | B13: CB, CM | C13: 2014-2015 | D13: 45 | E13: 1 | F13: 2012-2013 | G13: 6 | H13: 0 | J13: Johnnie Jackson | K13: LM, CM | L13: 2009-2017 | M13: 256 | N13: 52 | O13: 2004 | P13: 15 | Q13: 0 | S13: Dean Kiely | T13: GK | U13: 1999-2005 | V13: 222 | W13: 0 | X13: 2006-2009 | Y13: 80 | Z13: 0 | AB13: Morgan Fox | AC13: LB | AD13: 2013-2016 | AE13: 113 | AF13: 1 | AG13: 2020-2022 | AH13: 80 | AI13: 0 | AK13: Tahar El Khalej | AL13: CB | AM13: 2002 | AN13: 3 | AO13: 0 | AP13: 1999-2002 | AQ13: 58 | AR13: 3 | AT13: Simon Francis | AU13: RB | AV13: 2010 | AW13: 34 | AX13: 0 | AY13: 2003-2004 | AZ13: 11 | BA13: 0 | BC13: David Davis | BD13: CM | BE13: 2019 | BF13: 5 | BG13: 0 | BH13: 2014-2020 | BI13: 194 | BJ13: 11 | BL13: Thomas Kaminski | BM13: GK | BN13: 2025 | BO13: 37 | BP13: 0 | BQ13: 2020-2022 | BR13: 119 | BS13: 0 | BU13: Adam Chicksen | BV13: LB | BW13: 2016 | BX13: 22 | BY13: 2 | BZ13: 2019 | CA13: 17 | CB13: 0 | CD13: Chris Iwelumo | CE13: ST | CF13: 2007 | CG13: 46 | CH13: 10 | CI13: 2009 | CJ13: 7 | CK13: 2 | CM13: Jay McEveley | CN13: LB | CO13: 2008 | CP13: 6 | CQ13: 0 | CR13: 2003 | CS13: 4 | CT13: 0 | CV13: Karlan Grant | CW13: ST | CX13: 2014-2018, 2026- | CY13: 95* | CZ13: 20 | DA13: 2023 | DB13: 40 | DC13: 6 | DE13: Bryan Hughes | DF13: CM | DG13: 2004-2006 | DH13: 74 | DI13: 5 | DJ13: 2009 | DK13: 3 | DL13: 0 | DN13: Trésor Kandol | DO13: ST | DP13: 2008 | DQ13: 13 | DR13: 2 | DS13: 2008 | DT13: 18 | DU13: 8 | DW13: Jack Payne | DX13: CAM | DY13: 2022-2023 | DZ13: 50 | EA13: 6 | EB13: 2019 | EC13: 27 | ED13: 2 | EF13: Onel Hernández | EG13: LW, RW | EH13: 2025 | EI13: 6 | EJ13: 0 | EK13: 2021 | EL13: 18 | EM13: 1 | EO13: Jonatan Johansson | EP13: ST | EQ13: 2000-2005 | ER13: 148 | ES13: 27 | ET13: 2005 | EU13: 12 | EV13: 3 | EX13: Ricardo Fuller | EY13: ST | EZ13: 2012 | FA13: 31 | FB13: 5 | FC13: 2004 | FD13: 31 | FE13: 1 | FG13: Todd Kane | FH13: RB | FI13: 2022 | FJ13: 5 | FK13: 0 | FL13: 2012 | FM13: 3 | FN13: 0 | FP13: Lee Cook | FQ13: LW | FR13: 2007-2011 | FS13: 13 | FT13: 0 | FU13: 2002-2009 | FV13: 182 | FW13: 12 | FY13: Scott Sinclair | FZ13: LW, RW | GA13: 2007 | GB13: 3 | GC13: 0 | GD13: 2010-2012 | GE13: 82 | GF13: 28 | GH13: Emmanuel Frimpong | GI13: CDM | GJ13: 2012 | GK13: 6 | GL13: 0 | GM13: 2011 | GN13: 5 | GO13: 0 | GZ13: Scott Parker | HA13: CM | HB13: 1997-2003 | HC13: 128 | HD13: 9 | HE13: 2011-2012 | HF13: 56 | HG13: 0
A14: Matty Holmes | B14: LM | C14: 1997-1999 | D14: 16 | E14: 1 | F14: 1992-1994 | G14: 76 | H14: 4 | J14: Matt Jackson | K14: CB | L14: 1995 | M14: 8 | N14: 0 | O14: 2007 | P14: 6 | Q14: 0 | S14: Mark Kinsella | T14: CM | U14: 1996-2001 | V14: 208 | W14: 20 | X14: 2003 | Y14: 18 | Z14: 1 | AB14: Ricardo Fuller | AC14: ST | AD14: 2012 | AE14: 31 | AF14: 5 | AG14: 2006-2011 | AH14: 186 | AI14: 44 | AK14: Graeme Murty | AL14: RB | AM14: 2008 | AN14: 8 | AO14: 0 | AP14: 2009 | AQ14: 6 | AR14: 0 | AT14: Keith Gillespie | AU14: RM | AV14: 2008 | AW14: 6 | AX14: 0 | AY14: 2005-2008 | AZ14: 97 | BA14: 4 | BC14: Lyndon Dykes | BD14: ST | BE14: 2025 | BF14: 20 | BG14: 3 | BH14: 2024-2025 | BI14: 51 | BJ14: 5 | BL14: Todd Kane | BM14: RB | BN14: 2022 | BO14: 5 | BP14: 0 | BQ14: 2012-2013 | BR14: 41 | BS14: 2 | BU14: Josh Cullen | BV14: CM | BW14: 2018-2019 | BX14: 63 | BY14: 2 | BZ14: 2017 | CA14: 12 | CB14: 0 | CD14: Todd Kane | CE14: RB | CF14: 2022 | CG14: 5 | CH14: 0 | CI14: 2014 | CJ14: 7 | CK14: 0 | CM14: Nick Pope | CN14: GK | CO14: 2012-2015 | CP14: 38 | CQ14: 0 | CR14: 2016-2021 | CS14: 154 | CT14: 0 | CV14: Chris Gunter | CW14: RB | CX14: 2020-2021 | CY14: 56 | CZ14: 1 | DA14: 2006-2007 | DB14: 28 | DC14: 0 | DE14: Robert Hulse | DF14: ST | DG14: 2012 | DH14: 15 | DI14: 3 | DJ14: 2008-2010 | DK14: 82 | DL14: 28 | DN14: Kevin Lisbie | DO14: ST | DP14: 1996-2006 | DQ14: 155 | DR14: 16 | DS14: 2010 | DT14: 20 | DU14: 4 | DW14: Frazer Richardson | DX14: RB | DY14: 2009 | DZ14: 38 | EA14: 1 | EB14: 2003 | EC14: 2 | ED14: 0 | EF14: Carl Ikeme | EG14: GK | EH14: 2009 | EI14: 4 | EJ14: 0 | EK14: 2011 | EL14: 10 | EM14: 0 | EO14: Leroy Lita | EP14: ST | EQ14: 2007 | ER14: 8 | ES14: 3 | ET14: 2008 | EU14: 16 | EV14: 7 | EX14: André Green | EY14: RW, LW, ST | EZ14: 2019 | FA14: 14 | FB14: 2 | FC14: 2018 | FD14: 8 | FE14: 3 | FG14: Simon Makienok | FH14: ST | FI14: 2015 | FJ14: 37 | FK14: 5 | FL14: 2016 | FM14: 29 | FN14: 6 | FP14: Jordan Cousins | FQ14: CM | FR14: 2013-2015 | FS14: 131 | FT14: 7 | FU14: 2016-2018 | FV14: 70 | FW14: 1 | GH14: Greg Halford | GI14: RB | GJ14: 2007 | GK14: 16 | GL14: 2 | GM14: 2009-2010 | GN14: 17 | GO14: 0 | GZ14: Dean Parrett | HA14: CM | HB14: 2010 | HC14: 9 | HD14: 1 | HE14: 2008-2011 | HF14: 4 | HG14: 0
A15: Saša Ilić | B15: GK | C15: 1997-2000 | D15: 51 | E15: 0 | F15: 1999 | G15: 1 | H15: 0 | J15: Jason Lee | K15: ST | L15: 1996 | M15: 8 | N15: 3 | O15: 1997-1998 | P15: 37 | Q15: 11 | S15: Jonathan Leko | T15: ST | U15: 2019-2021 | V15: 48 | W15: 7 | X15: 2015-2019 | Y15: 41 | Z15: 3 | AB15: Chris Iwelumo | AC15: ST | AD15: 2007 | AE15: 46 | AF15: 10 | AG15: 1999-2003 | AH15: 84 | AI15: 15 | AK15: Dany N'Guessan | AL15: LW, ST | AM15: 2011 | AN15: 7 | AO15: 4 | AP15: 2010 | AQ15: 6 | AR15: 0 | AT15: Andy Gray | AU15: ST | AV15: 2007-2009 | AW15: 45 | AX15: 9 | AY15: 2003-2004 | AZ15: 57 | BA15: 24 | BC15: Neil Etheridge | BD15: GK | BE15: 2014 | BF15: 5 | BG15: 0 | BH15: 2020-2023 | BI15: 84 | BJ15: 0 | BL15: Jay McEveley | BM15: LB | BN15: 2008 | BO15: 6 | BP15: 0 | BQ15: 2002-2006 | BR15: 19 | BS15: 0 | BU15: Dorian Dervite | BV15: CB | BW15: 2012-2013 | BX15: 70 | BY15: 5 | BZ15: 2014-2017 | CA15: 99 | CB15: 2 | CD15: Jonathan Leko | CE15: ST, RW | CF15: 2019-2021 | CG15: 48 | CH15: 7 | CI15: 2017 | CJ15: 11 | CK15: 0 | CM15: Jonjo Shelvey | CN15: CAM | CO15: 2007-2009 | CP15: 42 | CQ15: 7 | CR15: 2024 | CS15: 4 | CT15: 0 | CV15: Greg Halford | CW15: RB | CX15: 2007 | CY15: 16 | CZ15: 2 | DA15: 2016-2017 | DB15: 33 | DC15: 1 | DE15: Johnnie Jackson | DF15: LM, CM | DG15: 2009-2017 | DH15: 256 | DI15: 52 | DJ15: 2005 | DK15: 6 | DL15: 0 | DN15: Lee Martin | DO15: LM, RM | DP15: 2010 | DQ15: 20 | DR15: 2 | DS15: 2013-2015 | DT15: 65 | DU15: 2 | DW15: Cameron Stewart | DX15: LW, RW | DY15: 2013 | DZ15: 18 | EA15: 3 | EB15: 2017 | EC15: 4 | ED15: 0 | EF15: Leroy Lita | EG15: ST | EH15: 2007 | EI15: 8 | EJ15: 3 | EK15: 2009-2010 | EL15: 78 | EM15: 20 | EO15: Conor McGrandles | EP15: CM | EQ15: 2022-2023 | ER15: 16 | ES15: 1 | ET15: 2014 | EU15: 1 | EV15: 0 | EX15: Reeco Hackett-Fairchild | EY15: LW, ST | EZ15: 2017-2018 | FA15: 12 | FB15: 0 | FC15: 2021-2022 | FD15: 68 | FE15: 10 | FG15: Stephy Mavididi | FH15: LW, ST | FI15: 2016-2017 | FJ15: 17 | FK15: 2 | FL15: 2017 | FM15: 11 | FN15: 0 | FP15: Martin Cranie | FQ15: CB, RB | FR15: 2008 | FS15: 19 | FT15: 0 | FU15: 2007 | FV15: 6 | FW15: 0 | GH15: Carl Ikeme | GI15: GK | GJ15: 2009 | GK15: 4 | GL15: 0 | GM15: 2008-2016 | GN15: 196 | GO15: 0 | GZ15: Chris Perry | HA15: CB | HB15: 2003-2005 | HC15: 76 | HD15: 3 | HE15: 1999-2002 | HF15: 124 | HG15: 4
A16: Carl Jenkinson | B16: RB | C16: 2010 | D16: 8 | E16: 0 | F16: 2014-2015 | G16: 58 | H16: 2 | J16: Marco Motta | K16: RB | L16: 2015 | M16: 12 | N16: 0 | O16: 2014 | P16: 9 | Q16: 0 | S16: Frank Nouble | T16: ST | U16: 2010 | V16: 9 | W16: 1 | X16: 2009 | Y16: 3 | Z16: 0 | AB16: Gavin Kilkenny | AC16: CM | AD16: 2022 | AE16: 8 | AF16: 0 | AG16: 2022 | AH16: 4 | AI16: 0 | AK16: Chris Perry | AL16: CB | AM16: 2003-2005 | AN16: 76 | AO16: 3 | AP16: 2007-2009 | AQ16: 58 | AR16: 2 | AT16: Greg Halford | AU16: RB | AV16: 2007 | AW16: 16 | AX16: 2 | AY16: 2008 | AZ16: 41 | BA16: 4 | BC16: Nicky Forster | BD16: ST | BE16: 2009 | BF16: 8 | BG16: 2 | BH16: 1996-1999 | BI16: 68 | BJ16: 11 | BL16: Danny Murphy | BM16: CM | BN16: 2004-2005 | BO16: 56 | BP16: 7 | BQ16: 2012 | BR16: 33 | BS16: 1 | BU16: Joe Dodoo | BV16: ST | BW16: 2017 | BX16: 6 | BY16: 1 | BZ16: 2019 | CA16: 25 | CB16: 4 | CD16: Leroy Lita | CE16: ST | CF16: 2007 | CG16: 8 | CH16: 3 | CI16: 2002-2004 | CJ16: 85 | CK16: 31 | CM16: Marvin Sordell | CN16: ST | CO16: 2013 | CP16: 31 | CQ16: 7 | CR16: 2014-2015 | CS16: 21 | CT16: 1 | CV16: Mark Hudson | CW16: CB | CX16: 2008 | CY16: 43 | CZ16: 3 | DA16: 2009-2014 | DB16: 144 | DC16: 11 | DE16: Paul Kitson | DF16: ST | DG16: 1999 | DH16: 6 | DI16: 1 | DJ16: 1992-1994 | DK16: 93 | DL16: 32 | DN16: Mark McCammon | DO16: ST | DP16: 1999 | DQ16: 4 | DR16: 0 | DS16: 2002-2004 | DT16: 14 | DU16: 2 | EF16: Danny Mills | EG16: RB | EH16: 1997-2007 | EI16: 64 | EJ16: 3 | EK16: 2003 | EL16: 28 | EM16: 0 | EO16: Leon McKenzie | EP16: ST | EQ16: 2009 | ER16: 12 | ES16: 0 | ET16: 2003-2005 | EU16: 75 | EV16: 20 | EX16: Greg Halford | EY16: RB | EZ16: 2007 | FA16: 16 | FB16: 2 | FC16: 2010-2011 | FD16: 75 | FE16: 12 | FG16: Paddy McCarthy | FH16: CB | FI16: 2007 | FJ16: 29 | FK16: 2 | FL16: 2015 | FM16: 1 | FN16: 0 | FP16: Lyndon Dykes | FQ16: ST | FR16: 2025 | FS16: 20 | FT16: 3 | FU16: 2020-2024 | FV16: 165 | FW16: 37 | GH16: Chris Iwelumo | GI16: ST | GJ16: 2007 | GK16: 46 | GL16: 10 | GM16: 2008-2009 | GN16: 46 | GO16: 14 | GZ16: Andy Reid | HA16: CM | HB16: 2006-2007 | HC16: 38 | HD16: 8 | HE16: 2004-2005 | HF16: 26 | HG16: 1
A17: Roger Johnson | B17: CB | C17: 2014-2016 | D17: 23 | E17: 0 | F17: 2013 | G17: 4 | H17: 0 | J17: Chris Powell | K17: LB | L17: 1998-2007 | M17: 244 | N17: 2 | O17: 2006 | P17: 15 | Q17: 0 | S17: Chris Perry | T17: CB | U17: 2003-2005 | V17: 76 | W17: 3 | X17: 2006 | Y17: 23 | Z17: 0 | AB17: Lee Martin | AC17: LM, RM | AD17: 2010 | AE17: 20 | AF17: 2 | AG17: 2006 | AH17: 13 | AI17: 1 | AK17: Kayne Ramsey | AL17: RB, CB | AM17: 2023-2025 | AN17: 77 | AO17: 1 | AP17: 2018-2022 | AQ17: 38 | AR17: 0 | AT17: Ricky Holmes | AU17: RM | AV17: 2016-2017 | AW17: 62 | AX17: 19 | AY17: 2017 | AZ17: 5 | BA17: 0 | BC17: Greg Halford | BD17: RB | BE17: 2007 | BF17: 16 | BG17: 2 | BH17: 2015 | BI17: 3 | BJ17: 0 | BL17: Jack Payne | BM17: CAM | BN17: 2022-2023 | BO17: 50 | BP17: 6 | BQ17: 2017 | BR17: 18 | BS17: 1 | BU17: Chris Eagles | BV17: LW, RW | BW17: 2014 | BX17: 15 | BY17: 2 | BZ17: 2011-2013 | CA17: 93 | CB17: 17 | CD17: Adam Matthews | CE17: RB | CF17: 2019-2021 | CG17: 85 | CH17: 0 | CI17: 2015-2016 | CJ17: 23 | CK17: 0 | CM17: Dale Stephens | CN17: CM | CO17: 2011-2013 | CP17: 84 | CQ17: 9 | CR17: 2020-2021 | CS17: 16 | CT17: 0 | CV17: Roger Johnson | CW17: CB | CX17: 2014-2016 | CY17: 23 | CZ17: 0 | DA17: 2006-2008 | DB17: 119 | DC17: 12 | DE17: Joe Ledley | DF17: CM | DG17: 2019 | DH17: 1 | DI17: 0 | DJ17: 2017-2018 | DK17: 30 | DL17: 2 | DN17: Izale McLeod | DO17: ST | DP17: 2007-2009 | DQ17: 31 | DR17: 3 | DS17: 2008 | DT17: 7 | DU17: 2 | EF17: Robbie Mustoe | EG17: CM | EH17: 2002 | EI17: 6 | EJ17: 0 | EK17: 1992-2001 | EL17: 294 | EM17: 19 | EO17: Danny Mills | EP17: RB | EQ17: 1997-2007 | ER17: 64 | ES17: 3 | ET17: 1995-1997 | EU17: 66 | EV17: 0 | EX17: Stephen Henderson | EY17: GK | EZ17: 2014-2021 | FA17: 59 | FB17: 0 | FC17: 2011-2017 | FD17: 26 | FE17: 0 | FG17: Alan McCormack | FH17: CM | FI17: 2010 | FJ17: 24 | FK17: 1 | FL17: 2003-2004 | FM17: 8 | FN17: 0 | FP17: Hogan Ephraim | FQ17: LW | FR17: 2011 | FS17: 5 | FT17: 1 | FU17: 2007-2011 | FV17: 108 | FW17: 7 | GH17: Roger Johnson | GI17: CB | GJ17: 2014-2016 | GK17: 23 | GL17: 0 | GM17: 2011-2012 | GN17: 69 | GO17: 2 | GZ17: Kevin Scott | HA17: CB | HB17: 1996 | HC17: 4 | HD17: 0 | HE17: 1993-1995 | HF17: 18 | HG17: 1
A18: Steve Jones | B18: RW | C18: 1996-1999 | D18: 53 | E18: 8 | F18: 1992-1996 | G18: 24 | H18: 4 | J18: Sam Sodje | K18: CB | L18: 2007-2009 | M18: 54 | N18: 7 | O18: 2008 | P18: 1 | Q18: 0 | S18: Scott Sinclair | T18: LW | U18: 2007 | V18: 3 | W18: 0 | X18: 2013 | Y18: 8 | Z18: 0 | AB18: Jesurun Rak Sakyi | AC18: RW | AD18: 2022 | AE18: 49 | AF18: 15 | AG18: 2025 | AH18: 16 | AI18: 3 | AK18: Ben Reeves | AL18: CM | AM18: 2017-2018 | AN18: 61 | AO18: 9 | AP18: 2011-2025 | AQ18: 11 | AR18: 0 | AT18: Robert Hulse | AU18: ST | AV18: 2012 | AW18: 15 | AX18: 3 | AY18: 2006-2007 | AZ18: 50 | BA18: 8 | BC18: Onel Hernández | BD18: LW, RW | BE18: 2025 | BF18: 6 | BG18: 0 | BH18: 2021 | BI18: 22 | BJ18: 3 | BL18: Joe Rankin-Costello | BM18: CM, RB | BN18: 2025 | BO18: 26 | BP18: 2 | BQ18: 2017-2024 | BR18: 168 | BS18: 15 | BU18: Mark Fish | BV18: CB | BW18: 2000-2004 | BX18: 102 | BY18: 3 | BZ18: 1997-2000 | CA18: 103 | CB18: 3 | CD18: Mark McCammon | CE18: ST | CF18: 1999 | CG18: 4 | CH18: 0 | CI18: 2005 | CJ18: 11 | CK18: 4 | CM18: Cameron Stewart | CN18: LW, RW | CO18: 2013 | CP18: 18 | CQ18: 3 | CR18: 2012 | CS18: 9 | CT18: 0 | CV18: Joe Ledley | CW18: CM | CX18: 2019 | CY18: 1 | CZ18: 0 | DA18: 2004-2009 | DB18: 226 | DC18: 26 | DE18: Rob Lee | DF18: CM | DG18: 1992 | DH18: 7 | DI18: 1 | DJ18: 2001-2002 | DK18: 48 | DL18: 2 | DN18: Danny McNamara | DO18: RB | DP18: 2026- | DQ18: 5 | DR18: 0 | DS18: 2018-2026 | DT18: 166 | DU18: 2 | EF18: Darren Randolph | EG18: GK | EH18: 2006-2009 | EI18: 14 | EJ18: 0 | EK18: 2017-2019 | EL18: 110 | EM18: 0 | EO18: Dave Mooney | EP18: ST | EQ18: 2009 | ER18: 28 | ES18: 5 | ET18: 2008 | EU18: 9 | EV18: 3 | EX18: Danny Hollands | EY18: CM | EZ18: 2011-2012 | FA18: 57 | FB18: 7 | FC18: 2013-2015 | FD18: 92 | FE18: 8 | FG18: Jay McEveley | FH18: LB | FI18: 2008 | FJ18: 6 | FK18: 0 | FL18: 2008 | FM18: 7 | FN18: 0 | FP18: Sam Field | FQ18: CM | FR18: 2019 | FS18: 18 | FT18: 0 | FU18: 2020-2025 | FV18: 198 | FW18: 12 | GH18: Eggert Jónsson | GI18: CDM | GJ18: 2012 | GK18: 2 | GL18: 0 | GM18: 2011-2012 | GN18: 4 | GO18: 0 | GZ18: Ben Thatcher | HA18: LB/LM | HB18: 2006-2007 | HC18: 22 | HD18: 0 | HE18: 2000-2002 | HF18: 36 | HG18: 0
A19: Paul Kitson | B19: ST | C19: 1999 | D19: 6 | E19: 1 | F19: 1996-2001 | G19: 66 | H19: 19 | J19: Marvin Sordell | K19: ST | L19: 2013 | M19: 31 | N19: 7 | O19: 2009-2011 | P19: 75 | Q19: 21 | S19: Sam Sodje | T19: CB | U19: 2007-2009 | V19: 54 | W19: 7 | X19: 2006 | Y19: 7 | Z19: 1 | AB19: Frazer Richardson | AC19: RB | AD19: 2009 | AE19: 38 | AF19: 1 | AG19: 2002-2003 | AH19: 13 | AI19: 1 | AK19: Frazer Richardson | AL19: RB | AM19: 2009 | AN19: 38 | AO19: 1 | AP19: 2010-2012 | AQ19: 60 | AR19: 0 | AT19: Carl Ikeme | AU19: GK | AV19: 2009 | AW19: 4 | AX19: 0 | AY19: 2009 | AZ19: 2 | BA19: 0 | BC19: Bryan Hughes | BD19: CM | BE19: 2004-2006 | BF19: 74 | BG19: 5 | BH19: 1996-2003 | BI19: 248 | BJ19: 34 | BL19: Cameron Stewart | BM19: LW, RW | BN19: 2013 | BO19: 18 | BP19: 3 | BQ19: 2012 | BR19: 7 | BS19: 0 | BU19: Claus Jensen | BV19: CM | BW19: 2000-2003 | BX19: 122 | BY19: 16 | BZ19: 1998-1999 | CA19: 86 | CB19: 8 | CD19: Osei Sankofa | CE19: CB | CF19: 2002-2007 | CG19: 15 | CH19: 0 | CI19: 2005 | CJ19: 8 | CK19: 0 | CM19: Andy Todd | CN19: CB | CO19: 1999-2001 | CP19: 40 | CQ19: 1 | CR19: 2003 | CS19: 7 | CT19: 0 | CV19: Josh Magennis | CW19: ST | CX19: 2016-2017 | CY19: 85 | CZ19: 20 | DA19: 2009 | DB19: 9 | DC19: 0 | DE19: Kevin Lisbie | DF19: ST | DG19: 1996-2006 | DH19: 155 | DI19: 16 | DJ19: 2005 | DK19: 13 | DL19: 2 | DN19: Alex Mitchell | DO19: CB | DP19: 2024-2025 | DQ19: 35 | DR19: 2 | DS19: 2021 | DT19: 1 | DU19: 0 | EF19: Frazer Richardson | EG19: RB | EH19: 2009 | EI19: 38 | EJ19: 1 | EK19: 2013 | EL19: 11 | EM19: 0 | EO19: Elliot Omozusi | EP19: RB | EQ19: 2009 | ER19: 9 | ES19: 0 | ET19: 2008 | EU19: 21 | EV19: 0 | EX19: Ricky Holmes | EY19: RM | EZ19: 2016-2017 | FA19: 62 | FB19: 19 | FC19: 2013-2014 | FD19: 56 | FE19: 2 | FG19: Aiden McGeady | FH19: LW, RW | FI19: 2019 | FJ19: 10 | FK19: 0 | FL19: 2016 | FM19: 35 | FN19: 8 | FP19: Morgan Fox | FQ19: LB | FR19: 2013-2016 | FS19: 113 | FT19: 1 | FU19: 2023-2024 | FV19: 48 | FW19: 2 | GH19: Shaun Newton | GI19: RM | GJ19: 1992-2000 | GK19: 240 | GL19: 20 | GM19: 2001-2003 | GN19: 106 | GO19: 11 | GZ19: Miloš Veljković | HA19: CB | HB19: 2014 | HC19: 3 | HD19: 0 | HE19: 2013 | HF19: 2 | HG19: 0
A20: Paul Konchesky | B20: LB | C20: 1997-2004 | D20: 149 | E20: 5 | F20: 2005-2006 | G20: 61 | H20: 1 | J20: Matthew Spring | K20: CM | L20: 2008-2009 | M20: 25 | N20: 2 | O20: 2005-2006 | P20: 45 | Q20: 8 | S20: Jerome Thomas | T20: LW | U20: 2003-2008 | V20: 103 | W20: 7 | X20: 2009-2012 | Y20: 99 | Z20: 11 | AB20: Darel Russell | AC20: CDM | AD20: 2011 | AE20: 11 | AF20: 2 | AG20: 2003-2006 | AH20: 171 | AI20: 16 | AK20: Danny Seaborne | AL20: CB | AM20: 2012 | AN20: 7 | AO20: 0 | AP20: 2009-2011 | AQ20: 44 | AR20: 0 | AT20: Lee Martin | AU20: RM, LM | AV20: 2010 | AW20: 20 | AX20: 2 | AY20: 2007 | AZ20: 6 | BA20: 0 | BC20: Matt Jackson | BD20: CB | BE20: 1995 | BF20: 8 | BG20: 0 | BH20: 1996 | BI20: 10 | BJ20: 0 | BL20: Andy Todd | BM20: CB, RB | BN20: 1999-2001 | BO20: 40 | BP20: 1 | BQ20: 2002-2006 | BR20: 92 | BS20: 4 | BU20: Marcus Maddison | BV20: RW, LW | BW20: 2020 | BX20: 9 | BY20: 1 | BZ20: 2020 | CA20: 10 | CB20: 0 | CD20: Steven Sessegnon | CE20: RB, LB | CF20: 2022 | CG20: 38 | CH20: 2 | CI20: 2020 | CJ20: 18 | CK20: 0 | CM20: Fredrik Ulvestad | CN20: CM | CO20: 2016 | CP20: 29 | CQ20: 1 | CR20: 2014-2017 | CS20: 10 | CT20: 0 | CV20: Adam Matthews | CW20: RB | CX20: 2019-2021 | CY20: 85 | CZ20: 0 | DA20: 2009-2010 | DB20: 40 | DC20: 1 | DE20: Jay McEveley | DF20: LB | DG20: 2008 | DH20: 6 | DI20: 0 | DJ20: 2006-2009 | DK20: 92 | DL20: 4 | DN20: Dany N'Guessan | DO20: LM, RM | DP20: 2011 | DQ20: 7 | DR20: 4 | DS20: 2011-2013 | DT20: 29 | DU20: 2 | EF20: Ben Roberts | EG20: GK | EH20: 2002 | EI20: 1 | EJ20: 0 | EK20: 1993-1997 | EL20: 16 | EM20: 0 | EO20: Scott Parker | EP20: CM | EQ20: 1997-2003 | ER20: 128 | ES20: 9 | ET20: 2000 | EU20: 6 | EV20: 1 | EX20: Tareiq Holmes-Dennis | EY20: LB | EZ20: 2015-2016 | FA20: 14 | FB20: 0 | FC20: 2017 | FD20: 1 | FE20: 0 | FG20: Liam Millar | FH20: LW | FI20: 2020 | FJ20: 27 | FK20: 3 | FL20: 2023 | FM20: 36 | FN20: 5 | FP20: Ben Hamer | FQ20: GK | FR20: 2011-2013 | FS20: 114 | FT20: 0 | FU20: 2025 | FV20: 7 | FW20: 0 | GH20: Frank Nouble | GI20: ST | GJ20: 2010 | GK20: 9 | GL20: 1 | GM20: 2012 | GN20: 2 | GO20: 0 | GZ20: Luke Young | HA20: RB | HB20: 2001-2006 | HC20: 187 | HD20: 4 | HE20: 1998-2000 | HF20: 61 | HG20: 0
A21: Elliot Lee | B21: CAM | C21: 2021 | D21: 37 | E21: 3 | F21: 2013-2015 | G21: 2 | H21: 0 | J21: Toby Stevenson | K21: LB | L21: 2018-2019 | M21: 7 | N21: 1 | O21: 2020 | P21: 2 | Q21: 0 | S21: Ben Watson | T21: CM | U21: 2020-2021 | V21: 40 | W21: 1 | X21: 2009 | Y21: 7 | Z21: 1 | AB21: Tom Soares | AC21: CM | AD21: 2008 | AE21: 11 | AF21: 1 | AG21: 2008 | AH21: 7 | AI21: 0 | AK21: Thierry Small | AL21: LWB, RWB | AM21: 2023-2024 | AN21: 57 | AO21: 3 | AP21: 2021-2022 | AQ21: 22 | AR21: 4 | AT21: Paddy McCarthy | AU21: CB | AV21: 2007 | AW21: 29 | AX21: 2 | AY21: 2014 | AZ21: 11 | BA21: 1 | BC21: Carl Jenkinson | BD21: RB | BE21: 2010 | BF21: 8 | BG21: 0 | BH21: 2017 | BI21: 9 | BJ21: 0 | BL21: Luke Varney | BM21: ST | BN21: 2007-2008 | BO21: 57 | BP21: 10 | BQ21: 2013-2014 | BR21: 26 | BS21: 0 | BU21: Josh Magennis | BV21: ST | BW21: 2016-2017 | BX21: 85 | BY21: 20 | BZ21: 2018 | CA21: 45 | CB21: 6 | CD21: Scott Wagstaff | CE21: RW | CF21: 2007-2012 | CG21: 118 | CH21: 18 | CI21: 2013-2015 | CJ21: 78 | CK21: 8 | CM21: Rhys Williams | CN21: CB | CO21: 2015 | CP21: 4 | CQ21: 0 | CR21: 2008 | CS21: 16 | CT21: 0 | CV21: Conor McAleny | CW21: LW | CX21: 2015 | CY21: 9 | CZ21: 0 | DA21: 2014 | DB21: 8 | DC21: 2 | DE21: Izale McLeod | DF21: ST | DG21: 2007-2009 | DH21: 31 | DI21: 3 | DJ21: 2002-2003 | DK21: 39 | DL21: 4 | DN21: Jonathan Obika | DO21: ST | DP21: 2012-2013 | DQ21: 22 | DR21: 3 | DS21: 2009 | DT21: 12 | DU21: 2 | EF21: Andy Todd | EG21: CB | EH21: 1999-2001 | EI21: 40 | EJ21: 1 | EK21: 1993-1994 | EL21: 8 | EM21: 0 | EO21: Lee Power | EP21: ST | EQ21: 1992 | ER21: 5 | ES21: 0 | ET21: 1992-1993 | EU21: 25 | EV21: 6 | EX21: Hermann Hreiðarsson | EY21: LB | EZ21: 2003-2006 | FA21: 132 | FB21: 3 | FC21: 2007-2011 | FD21: 105 | FE21: 8 | FG21: Kevin Nicholls | FH21: RM | FI21: 1995-1999 | FJ21: 12 | FK21: 1 | FL21: 2007 | FM21: 18 | FN21: 0 | FP21: Tomer Hemed | FQ21: ST | FR21: 2019 | FS21: 19 | FT21: 0 | FU21: 2018 | FV21: 29 | FW21: 7 | GH21: Kyel Reid | GI21: LW | GJ21: 2009-2010 | GK21: 49 | GL21: 5 | GM21: 2008 | GN21: 8 | GO21: 1
A22: Rob Lee | B22: CM | C22: 1992 | D22: 7 | E22: 1 | F22: 2003 | G22: 16 | H22: 0 | J22: Darren Ward | K22: CB | L22: 2008 | M22: 16 | N22: 0 | O22: 1995-2008 | P22: 68 | Q22: 3 | AK22: Dale Stephens | AL22: CM | AM22: 2011-2013 | AN22: 84 | AO22: 9 | AP22: 2010 | AQ22: 6 | AR22: 0 | AT22: Jay McEveley | AU22: LB | AV22: 2008 | AW22: 6 | AX22: 0 | AY22: 2014-2015 | AZ22: 83 | BA22: 1 | BC22: Roger Johnson | BD22: CB | BE22: 2014-2016 | BF22: 23 | BG22: 0 | BH22: 2009-2010 | BI22: 76 | BJ22: 2 | BL22: Tony Watt | BM22: ST | BN22: 2014-2017 | BO22: 56 | BP22: 10 | BQ22: 2015 | BR22: 11 | BS22: 2 | BU22: Jamie Mascoll | BV22: LB | BW22: 2018 | BX22: 1 | BY22: 0 | BZ22: 2020 | CA22: 7 | CB22: 0 | CD22: Kelly Youga | CE22: LB | CF22: 2007-2009 | CG22: 62 | CH22: 1 | CI22: 2005 | CJ22: 4 | CK22: 0 | CV22: Deji Oshilaja | CW22: CB | CX22: 2019-2020 | CY22: 46 | CZ22: 1 | DA22: 2014-2015 | DB22: 1 | DC22: 0 | DE22: Danny Mills | DF22: RB | DG22: 1997-2007 | DH22: 64 | DI22: 3 | DJ22: 2007 | DK22: 2 | DL22: 0 | DN22: Isaac Olaofe | DO22: ST | DP22: 2025 | DQ22: 25 | DR22: 1 | DS22: 2022 | DT22: 3 | DU22: 0 | EF22: Miloš Veljković | EG22: CB | EH22: 2014 | EI22: 3 | EJ22: 0 | EK22: 2014 | EL22: 4 | EM22: 0 | EO22: Declan Rudd | EP22: GK | EQ22: 2016 | ER22: 40 | ES22: 0 | ET22: 2009-2015 | EU22: 26 | EV22: 0 | EX22: Saša Ilić | EY22: GK | EZ22: 1997-2000 | FA22: 51 | FB22: 0 | FC22: 2001 | FD22: 7 | FE22: 0 | FG22: Kyel Reid | FH22: LW | FI22: 2009-2010 | FJ22: 49 | FK22: 5 | FL22: 2014-2015 | FM22: 23 | FN22: 0 | FP22: Robert Hulse | FQ22: ST | FR22: 2012 | FS22: 15 | FT22: 3 | FU22: 2010-2011 | FV22: 23 | FW22: 2 | GH22: Mike Small | GI22: ST | GJ22: 1993 | GK22: 2 | GL22: 0 | GM22: 1993 | GN22: 3 | GO22: 1
A23: Scott Minto | B23: LB | C23: 1992-1993 | D23: 78 | E23: 3 | F23: 1998-2002 | G23: 51 | H23: 0 | J23: Ben Watson | K23: CM | L23: 2020-2021 | M23: 40 | N23: 1 | O23: 2014-2017 | P23: 78 | Q23: 2 | AK23: Bradley Wright-Phillips | AL23: ST | AM23: 2010-2012 | AN23: 82 | AO23: 31 | AP23: 2006-2008 | AQ23: 111 | AR23: 22 | AT23: Alan McLeary | AU23: CB | AV23: 1992-1995 | AW23: 66 | AX23: 3 | AY23: 1992 | AZ23: 3 | BA23: 0 | BC23: Jonathan Leko | BD23: LW, RW, ST | BE23: 2019-2021 | BF23: 48 | BG23: 7 | BH23: 2020-2022 | BI23: 50 | BJ23: 1 | BU23: Paddy McCarthy | BV23: CB | BW23: 2007 | BX23: 29 | BY23: 2 | BZ23: 2014 | CA23: 5 | CB23: 0 | CV23: Dillon Phillips | CW23: GK | CX23: 2014-2019 | CY23: 90 | CZ23: 0 | DA23: 2020-2021 | DB23: 36 | DC23: 0 | DE23: Chris Powell | DF23: LB | DG23: 1998-2007 | DH23: 244 | DI23: 2 | DJ23: 1995-1997 | DK23: 91 | DL23: 1 | DN23: Therry Racon | DO23: CM | DP23: 2007-2010 | DQ23: 98 | DR23: 7 | DS23: 2012 | DT23: 1 | DU23: 0 | EF23: Rhys Williams | EG23: CB | EH23: 2015 | EI23: 4 | EJ23: 0 | EK23: 2009-2014 | EL23: 126 | EM23: 5 | EO23: Darel Russell | EP23: CDM | EQ23: 2011 | ER23: 11 | ES23: 2 | ET23: 1997-2009 | EU23: 244 | EV23: 18 | EX23: Dean Kiely | EY23: GK | EZ23: 1999-2005 | FA23: 222 | FB23: 0 | FC23: 2005 | FD23: 15 | FE23: 0 | FG23: Declan Rudd | FH23: GK | FI23: 2016 | FJ23: 40 | FK23: 0 | FL23: 2012-2021 | FM23: 187 | FN23: 0 | FP23: Carl Ikeme | FQ23: GK | FR23: 2009 | FS23: 4 | FT23: 0 | FU23: 2009 | FV23: 17 | FW23: 0 | GH23: Terry Taylor | GI23: CM | GJ23: 2023-2024 | GK23: 16 | GL23: 0 | GM23: 2019-2020 | GN23: 11 | GO23: 1
A24: Shaun Newton | B24: RM | C24: 1992-2000 | D24: 240 | E24: 20 | F24: 2004-2006 | G24: 64 | H24: 2 | AT24: Izale McLeod | AU24: ST | AV24: 2007-2009 | AW24: 31 | AX24: 3 | AY24: 2003 | AZ24: 7 | BA24: 0 | BC24: Leroy Lita | BD24: ST | BE24: 2007 | BF24: 8 | BG24: 3 | BH24: 2012 | BI24: 10 | BJ24: 3 | BU24: Erhun Oztumer | BV24: CAM | BW24: 2019-2020 | BX24: 18 | BY24: 0 | BZ24: 2018-2019 | CA24: 19 | CB24: 1 | CV24: John Robinson | CW24: RM | CX24: 1992-2002 | CY24: 332 | CZ24: 36 | DA24: 2003 | DB24: 34 | DC24: 2 | DE24: Gary Rowett | DF24: RB | DG24: 2002-2003 | DH24: 13 | DI24: 1 | DJ24: 1995-1997 | DK24: 105 | DL24: 2 | DN24: Martyn Waghorn | DO24: ST | DP24: 2008 | DQ24: 7 | DR24: 1 | DS24: 2013 | DT24: 14 | DU24: 3 | EF24: Luke Young | EG24: RB | EH24: 2001-2006 | EI24: 187 | EJ24: 4 | EK24: 2007 | EL24: 35 | EM24: 1 | EO24: Kevin Scott | EP24: CB | EQ24: 1996 | ER24: 4 | ES24: 0 | ET24: 1996-1999 | EU24: 33 | EV24: 0 | EX24: Craig MacGillivray | EY24: GK | EZ24: 2021-2022 | FA24: 49 | FB24: 0 | FC24: 2018-2020 | FD24: 126 | FE24: 0 | FG24: Darel Russell | FH24: CDM | FI24: 2011 | FJ24: 11 | FK24: 2 | FL24: 2010-2011 | FM24: 27 | FN24: 0 | FP24: Matt Jackson | FQ24: CB | FR24: 1995 | FS24: 8 | FT24: 0 | FU24: 1996 | FV24: 7 | FW24: 0 | GH24: Darren Ward | GI24: CB | GJ24: 2008 | GK24: 16 | GL24: 0 | GM24: 2007-2008 | GN24: 31 | GO24: 0
A25: Frank Nouble | B25: ST | C25: 2010 | D25: 9 | E25: 1 | F25: 2009-2011 | G25: 13 | H25: 1 | AT25: Jesurun Rak Sakyi | AU25: RW | AV25: 2022 | AW25: 49 | AX25: 15 | AY25: 2024 | AZ25: 35 | BA25: 7 | BC25: Alfie May | BD25: ST | BE25: 2023 | BF25: 47 | BG25: 25 | BH25: 2024 | BI25: 49 | BJ25: 16 | BU25: Darren Pratley | BV25: CM | BW25: 2018-2020 | BX25: 107 | BY25: 5 | BZ25: 2011-2017 | CA25: 189 | CB25: 16 | CV25: Jamie Ward | CW25: ST | CX25: 2018 | CY25: 10 | CZ25: 1 | DA25: 2017 | DB25: 4 | DC25: 0 | DE25: Mathias Svensson | DF25: ST | DG25: 1999-2003 | DH25: 70 | DI25: 7 | DJ25: 2003 | DK25: 10 | DL25: 3 | DN25: Darren Ward | DO25: CB | DP25: 2008 | DQ25: 16 | DR25: 0 | DS25: 2001-2012 | DT25: 237 | DU25: 6 | EO25: Oliver Skipp | EP25: CM | EQ25: 2026- | ER25: 1* | ES25: 0* | ET25: 2020-2021 | EU25: 45 | EV25: 1 | EX25: Tom McIntyre | EY25: CB | EZ25: 2024 | FA25: 10 | FB25: 0 | FC25: 2023-2024 | FD25: 14 | FE25: 0 | FG25: Scott Sinclair | FH25: LW, RW | FI25: 2007 | FJ25: 3 | FK25: 0 | FL25: 2019-2021 | FM25: 85 | FN25: 14 | FP25: Todd Kane | FQ25: RB | FR25: 2022 | FS25: 5 | FT25: 0 | FU25: 2019-2020 | FV25: 65 | FW25: 3 | GH25: Michał Żyro | GI25: ST | GJ25: 2017 | GK25: 13 | GL25: 3 | GM25: 2015-2017 | GN25: 15 | GO25: 3
A26: Scott Parker | B26: CM | C26: 1997-2003 | D26: 128 | E26: 9 | F26: 2007-2011 | G26: 113 | H26: 10 | AT26: Andy Reid | AU26: CAM | AV26: 2006-2007 | AW26: 38 | AX26: 8 | AY26: 2010 | AZ26: 9 | BA26: 2 | BC26: Michael Morrison | BD26: CB | BE26: 2011-2014 | BF26: 138 | BG26: 6 | BH26: 2014-2018 | BI26: 183 | BJ26: 14 | BU26: John Salako | BV26: CM | BW26: 1999-2001 | BX26: 46 | BY26: 2 | BZ26: 1997 | CA26: 7 | CB26: 0 | CV26: Tony Watt | CW26: ST | CX26: 2014-2017 | CY26: 56 | CZ26: 10 | DA26: 2015 | DB26: 9 | DC26: 2 | DE26: Andy Todd | DF26: CB | DG26: 1999-2001 | DH26: 40 | DI26: 1 | DJ26: 2007-2008 | DK26: 30 | DL26: 1 | DN26: Josh Wright | DO26: CM | DP26: 2008 | DQ26: 2 | DR26: 0 | DS26: 2011-2014 | DT26: 47 | DU26: 1 | EO26: Graham Stuart | EP26: CM | EQ26: 1998-2004 | ER26: 148 | ES26: 21 | ET26: 2004 | EU26: 8 | EV26: 0 | EX26: Izale McLeod | EY26: ST | EZ26: 2007-2009 | FA26: 31 | FB26: 3 | FC26: 2012 | FD26: 24 | FE26: 10 | FG26: Akpo Sodje | FH26: ST | FI26: 2009-2010 | FJ26: 40 | FK26: 5 | FL26: 2012 | FM26: 14 | FN26: 4 | FP26: Charlie Kelman | FQ26: ST | FR26: 2025 | FS26: 36 | FT26: 7 | FU26: 2020-2023 | FV26: 26 | FW26: 0
A27: Dan Potts | B27: LB | C27: 2024 | D27: 1 | E27: 0 | F27: 2011-2014 | G27: 6 | H27: 0 | AT27: Kyel Reid | AU27: LM | AV27: 2009-2010 | AW27: 49 | AX27: 5 | AY27: 2009 | AZ27: 7 | BA27: 0 | BC27: Thomas Myhre | BD27: GK | BE27: 2005-2006 | BF27: 21 | BG27: 0 | BH27: 1999 | BI27: 7 | BJ27: 0 | BU27: Marvin Sordell | BV27: ST | BW27: 2013 | BX27: 31 | BY27: 7 | BZ27: 2011-2012 | CA27: 25 | CB27: 4 | CV27: Jonny Williams | CW27: CAM | CX27: 2018-2020 | CY27: 63 | CZ27: 2 | DA27: 2020 | DB27: 9 | DC27: 0 | DE27: Marcus Tudgay | DF27: ST | DG27: 2013 | DH27: 2 | DI27: 0 | DJ27: 2002-2004 | DK27: 71 | DL27: 15 | EO27: Mathias Svensson | EP27: ST | EQ27: 1999-2003 | ER27: 70 | ES27: 7 | ET27: 2003-2004 | EU27: 42 | EV27: 11 | EX27: Michael Morrison | EY27: CB | EZ27: 2011-2014 | FA27: 138 | FB27: 6 | FC27: 2022 | FD27: 25 | FE27: 0 | FG27: Connor Wickham | FH27: ST | FI27: 2023 | FJ27: 4 | FK27: 1 | FL27: 2021 | FM27: 2 | FN27: 0 | FP27: Carl Leaburn | FQ27: ST | FR27: 1992-1997 | FS27: 203 | FT27: 38 | FU27: 2001 | FV27: 1 | FW27: 0
A28: Diego Poyet | B28: CM | C28: 2013-2015 | D28: 27 | E28: 0 | F28: 2014-2015 | G28: 5 | H28: 0 | AT28: Matthew Spring | AU28: CM | AV28: 2008-2009 | AW28: 25 | AX28: 2 | AY28: 2008 | AZ28: 11 | BA28: 1 | BC28: Ricky Otto | BD28: LW | BE28: 1996 | BF28: 7 | BG28: 0 | BH28: 1994-1997 | BI28: 46 | BJ28: 6 | BU28: Andy Todd | BV28: CB | BW28: 1999-2001 | BX28: 40 | BY28: 1 | BZ28: 1995-1999 | CA28: 84 | CB28: 2 | DE28: Martyn Waghorn | DF28: ST | DG28: 2008 | DH28: 7 | DI28: 1 | DJ28: 2018-2023 | DK28: 148 | DL28: 37 | EX28: Yassin Moutaouakil | EY28: RB | EZ28: 2007-2008 | FA28: 21 | FB28: 0 | FC28: 2012-2013 | FD28: 32 | FE28: 0 | FP28: Kevin Lisbie | FQ28: ST | FR28: 1996-2006 | FS28: 155 | FT28: 16 | FU28: 2000 | FV28: 2 | FW28: 0
A29: Darren Randolph | B29: GK | C29: 2006-2009 | D29: 14 | E29: 0 | F29: 2015-2022 | G29: 47 | H29: 0 | AT29: Lyle Taylor | AU29: ST | AV29: 2018-2019 | AW29: 64 | AX29: 35 | AY29: 2013 | AZ29: 20 | BA29: 2 | BC29: Gary Poole | BD29: RB | BE29: 1996-1997 | BF29: 16 | BG29: 1 | BH29: 1994-1996 | BI29: 72 | BJ29: 0 | BU29: Ricardo Vaz Tê | BV29: ST | BW29: 2015 | BX29: 12 | BY29: 0 | BZ29: 2003-2008 | CA29: 63 | CB29: 3 | DE29: Jamie Ward | DF29: ST | DG29: 2018 | DH29: 10 | DI29: 1 | DJ29: 2010-2014 | DK29: 142 | DL29: 34 | EX29: Andy Petterson | EY29: GK | EZ29: 1994-1999 | FA29: 72 | FB29: 0 | FC29: 1998-2000 | FD29: 32 | FE29: 0 | FP29: Kazenga LuaLua | FQ29: LW | FR29: 2023 | FS29: 4 | FT29: 0 | FU29: 2016-2017 | FV29: 19 | FW29: 1
A30: Kyel Reid | B30: LW | C30: 2009-2010 | D30: 49 | E30: 5 | F30: 2005-2007 | G30: 3 | H30: 0 | AT30: Carl Tiler | AU30: CB | AV30: 1998-2000 | AW30: 45 | AX30: 2 | AY30: 1996-1997 | AZ30: 23 | BA30: 2 | BC30: Darren Randolph | BD30: GK | BE30: 2006-2009 | BF30: 14 | BG30: 0 | BH30: 2013-2014 | BI30: 92 | BJ30: 0 | BU30: Lawrie Wilson | BV30: RM, RB | BW30: 2012-2014 | BX30: 99 | BY30: 6 | BZ30: 2015-2016 | CA30: 36 | CB30: 2 | DE30: Conor Washington | DF30: ST | DG30: 2020-2021 | DH30: 75 | DI30: 22 | DJ30: 2023-2024 | DK30: 25 | DL30: 4 | EX30: Joe Pigott | EY30: ST | EZ30: 2013-2014 | FA30: 13 | FB30: 0 | FC30: 2022 | FD30: 39 | FE30: 6 | FP30: Josh Parker | FQ30: ST | FR30: 2018 | FS30: 10 | FT30: 0 | FU30: 2009-2010 | FV30: 5 | FW30: 0
A31: Mark Robson | B31: LW | C31: 1993-1996 | D31: 105 | E31: 9 | F31: 1992-1993 | G31: 47 | H31: 8 | AT31: Jamie Ward | AU31: ST | AV31: 2018 | AW31: 10 | AX31: 1 | AY31: 2008-2010 | AZ31: 63 | BA31: 9 | BC31: Gary Rowett | BD31: RB | BE31: 2002-2003 | BF31: 13 | BG31: 1 | BH31: 1998-2000 | BI31: 87 | BJ31: 6 | DE31: Louie Watson | DF31: CM | DG31: 2023 | DH31: 23 | DI31: 0 | DJ31: 2020-2021 | DK31: 40 | DL31: 2 | EX31: Dan Potts | EY31: LB | EZ31: 2024 | FA31: 1 | FB31: 0 | FC31: 2013 | FD31: 5 | FE31: 0 | FP31: Gavin Peacock | FQ31: CM | FR31: 2001 | FS31: 5 | FT31: 0 | FU31: 1996-2001 | FV31: 190 | FW31: 35
A32: Mike Small | B32: ST | C32: 1993 | D32: 2 | E32: 0 | F32: 1992 | G32: 9 | H32: 0 | AT32: Conor Washington | AU32: ST | AV32: 2020-2021 | AW32: 75 | AX32: 22 | AY32: 2018 | AZ32: 16 | BA32: 0 | BC32: Andrew Shinnie | BD32: CM | BE32: 2020 | BF32: 29 | BG32: 3 | BH32: 2013-2016 | BI32: 71 | BJ32: 5 | DE32: Simon Webster | DF32: CB | DG32: 1992-1993 | DH32: 43 | DI32: 2 | DJ32: 1995 | DK32: 3 | DL32: 0 | EX32: Lee Power | EY32: ST | EZ32: 1992 | FA32: 5 | FB32: 0 | FC32: 1993 | FD32: 2 | FE32: 0 | FP32: Simon Royce | FQ32: GK | FR32: 1998-2003 | FS32: 9 | FT32: 0 | FU32: 2002-2006 | FV32: 79 | FW32: 0
A33: Alexandre Song | B33: CDM | C33: 2006 | D33: 12 | E33: 0 | F33: 2014-2015 | G33: 46 | H33: 0 | BC33: Scott Sinclair | BD33: LW, RW | BE33: 2007 | BF33: 3 | BG33: 0 | BH33: 2008 | BI33: 14 | BJ33: 0 | EX33: Linvoy Primus | EY33: CB | EZ33: 1992-2008 | FA33: 14 | FB33: 1 | FC33: 2000-2008 | FD33: 198 | FE33: 5 | FP33: Scott Sinclair | FQ33: LW, RW | FR33: 2007 | FS33: 3 | FT33: 0 | FU33: 2007 | FV33: 9 | FW33: 1
A34: Jonathan Spector | B34: CB, RB | C34: 2005 | D34: 20 | E34: 0 | F34: 2006-2010 | G34: 102 | H34: 1 | BC34: Jonathan Spector | BD34: RB, CB | BE34: 2005 | BF34: 20 | BG34: 0 | BH34: 2011-2016 | BI34: 166 | BJ34: 0 | EX34: Therry Racon | EY34: CM | EZ34: 2007-2010 | FA34: 98 | FB34: 7 | FC34: 2012-2013 | FD34: 31 | FE34: 0 | FP34: Matthew Smith | FQ34: CAM | FR34: 2019 | FS34: 2 | FT34: 0 | FU34: 2019 | FV34: 10 | FW34: 0
A35: Svetoslav Todorov | B35: ST | C35: 2007-2008 | D35: 20 | E35: 3 | F35: 2000-2001 | G35: 13 | H35: 1 | BC35: Lyle Taylor | BD35: ST | BE35: 2018-2019 | BF35: 64 | BG35: 35 | BH35: 2021 | BI35: 14 | BJ35: 5 | EX35: Abdul Razak | EY35: CM | EZ35: 2012 | FA35: 2 | FB35: 0 | FC35: 2011 | FD35: 3 | FE35: 0 | FP35: Paul Smyth | FQ35: LW, RW | FR35: 2020 | FS35: 14 | FT35: 1 | FU35: 2017-2025 | FV35: 152 | FW35: 13
A36: Ricardo Vaz Tê | B36: ST | C36: 2015 | D36: 12 | E36: 0 | F36: 2011-2014 | G36: 52 | H36: 15 | BC36: Carl Tiler | BD36: CB | BE36: 1998-2000 | BF36: 45 | BG36: 2 | BH36: 2000 | BI36: 1 | BJ36: 0 | EX36: Darel Russell | EY36: CDM | EZ36: 2011 | FA36: 11 | FB36: 2 | FC36: 2012 | FD36: 17 | FE36: 0 | FP36: Akpo Sodje | FQ36: ST | FR36: 2009-2010 | FS36: 40 | FT36: 5 | FU36: 2000-2001 | FV36: 0 | FW36: 0
A37: Simon Webster | B37: CB | C37: 1992-1993 | D37: 43 | E37: 2 | F37: 1994 | G37: 5 | H37: 0 | BC37: Djimi Traoré | BD37: LB | BE37: 2006 | BF37: 11 | BG37: 0 | BH37: 2008 | BI37: 3 | BJ37: 0 | EX37: Alexey Smertin | EY37: CDM | EZ37: 2005 | FA37: 18 | FB37: 0 | FC37: 2003 | FD37: 26 | FE37: 0 | FP37: Yun Suk-young | FQ37: LB | FR37: 2015 | FS37: 9 | FT37: 0 | FU37: 2013-2015 | FV37: 33 | FW37: 1
BC38: Chris Whyte | BD38: CB | BE38: 1995-1996 | BF38: 11 | BG38: 0 | BH38: 1993-1995 | BI38: 68 | BJ38: 1 | EX38: Sam Sodje | EY38: CB | EZ38: 2007-2009 | FA38: 54 | FB38: 7 | FC38: 2012 | FD38: 9 | FE38: 0 | FP38: Jerome Thomas | FQ38: LW, RW | FR38: 2003-2008 | FS38: 103 | FT38: 7 | FU38: 2001-2002 | FV38: 10 | FW38: 3
BC39: Rhoys Wiggins | BD39: LB | BE39: 2011-2014 | BF39: 124 | BG39: 1 | BH39: 2016 | BI39: 2 | BJ39: 0 | EX39: Jayden Stockley | EY39: ST | EZ39: 2020-2022 | FA39: 87 | FB39: 28 | FC39: 2015 | FD39: 12 | FE39: 2 | FP39: Darren Ward | FQ39: CB | FR39: 2008 | FS39: 16 | FT39: 0 | FU39: 1999 | FV39: 14 | FW39: 0
BC40: Paul Williams | BD40: ST | BE40: 1995 | BF40: 9 | BG40: 0 | BH40: 1994 | BI40: 11 | BJ40: 0 | EX40: John Sullivan | EY40: GK | EZ40: 2010-2011 | FA40: 7 | FB40: 0 | FC40: 2013 | FD40: 6 | FE40: 0 | FP40: Conor Washington | FQ40: ST | FR40: 2020-2021 | FS40: 75 | FT40: 22 | FU40: 2015-2018 | FV40: 98 | FW40: 14
EX41: Mathias Svensson | EY41: ST | EZ41: 1999-2003 | FA41: 70 | FB41: 7 | FC41: 1996-1998 | FD41: 45 | FE41: 10 | FP41: Ben Watson | FQ41: CM | FR41: 2020-2021 | FS41: 40 | FT41: 1 | FU41: 2009 | FV41: 16 | FW41: 2
EX42: Jerome Thomas | EY42: LM, RM | EZ42: 2003-2008 | FA42: 103 | FB42: 7 | FC42: 2008 | FD42: 3 | FE42: 0 | FP42: Luke Young | FQ42: RB | FR42: 2001-2006 | FS42: 187 | FT42: 4 | FU42: 2011-2013 | FV42: 24 | FW42: 2
EX43: Carl Tiler | EY43: CB | EZ43: 1998-2000 | FA43: 45 | FB43: 2 | FC43: 2000-2002 | FD43: 19 | FE43: 1
EX44: Svetoslav Todorov | EY44: ST | EZ44: 2007-2008 | FA44: 20 | FB44: 3 | FC44: 2001-2006 | FD44: 77 | FE44: 33
EX45: Djimi Traoré | EY45: LB | EZ45: 2006 | FA45: 11 | FB45: 0 | FC45: 2006-2007 | FD45: 13 | FE45: 0
EX46: Luke Varney | EY46: ST | EZ46: 2007-2008 | FA46: 57 | FB46: 10 | FC46: 2011 | FD46: 30 | FE46: 6

Sheet AwayFixtures
A1: Location | B1: Home Team | C1: Date | D1: Away Team | E1: Result
A3: London Stadium | B3: West Ham United | C3: 22-08-2026 | D3: Charlton Athletic
A5: The Hawthorns | B5: West Bromwich Albion | C5: 02-09-2026 | D5: Charlton Athletic
A6: bet365 Stadium | B6: Stoke City | C6: 05-09-2026 | D6: Charlton Athletic
A9: Cardiff City Stadium | B9: Cardiff City | C9: 19-09-2026 | D9: Charlton Athletic
A11: Turf Moor | B11: Burnley | C11: 13-10-2026 | D11: Charlton Athletic
A12: Vicarage Road | B12: Watford | C12: 17-10-2026 | D12: Charlton Athletic
A14: Riverside Stadium | B14: Middlesbrough | C14: 31-10-2026 | D14: Charlton Athletic
A17: Molineux Stadium | B17: Wolverhampton Wanderers | C17: 21-11-2026 | D17: Charlton Athletic
A19: Ewood Park | B19: Blackburn Rovers | C19: 28-11-2026 | D19: Charlton Athletic
A21: Racecourse Ground | B21: Wrexham | C21: 08-12-2026 | D21: Charlton Athletic
A23: The Den | B23: Millwall | C23: 19-12-2026 | D23: Charlton Athletic
A25: Carrow Road | B25: Norwich City | C25: 29-12-2026 | D25: Charlton Athletic
... A47: LNER Stadium | B47: Lincoln City | C47: 01-05-2027 | D47: Charlton Athletic

Sheet ChrisDartWilliams
A1: Player | B1: Apps | C1: Goals
A2: Derek Hales | B2: 623 | C2: 0
A3: Stuart Leary | B3: 591 | C3: 107
A4: Mike Flanagan | B4: 530 | C4: 38
A5: Keith Peacock | B5: 450 | C5: 16
A6: Johnny Summers | B6: 435 | C6: 26
A7: Charlie Vaughan | B7: 418 | C7: 26
A8: Billy Kiernan | B8: 403 | C8: 163
A9: Eddie Firmani | B9: 401 | C9: 93
A10: Gordon Hurst | B10: 396 | C10: 120
A11: Harold Hobbis | B11: 396 | C11: 11
A12: Sam Lawrie | B12: 393 | C12: 81
A13: Martin Robinson | B13: 372 | C13: 38
... A477: Andy Salako | B477: 0 | C477: 0
A478: Steve Gatting
A479: John Bumstead
A480: Gary Nelson
A481: Leroy Rosenior
A482: John Darlington
A483: Mark Tivey
A484: John Hendry
A485: Derek Warden
A486: Peter Garland
A487: Paul Sturgess
A488: Steve Houghton
A489: Paul Linger
... A718: C Sichenje

Sheet DoubleClubbleArsenal
A1: Arsenal — Aston Villa | I1: Arsenal — Sunderland | Q1: Arsenal — Brighton & Hove Albion | Y1: Arsenal — Nottingham Forest | AG1: Arsenal — Liverpool | AO1: Arsenal — Newcastle United | AW1: Arsenal — Brentford | BE1: Arsenal — Tottenham Hotspur | BM1: Arsenal — Crystal Palace | BU1: Arsenal — Fulham | CC1: Arsenal — Hull City | CK1: Arsenal — Manchester City | CS1: Arsenal — Ipswich Town | DA1: Arsenal — Manchester United | DI1: Arsenal — Chelsea | DQ1: Arsenal — Coventry City | DY1: Arsenal — AFC Bournemouth | EG1: Arsenal — Leeds United | EO1: Arsenal — Everton
A2: 29-08-2026 | I2: 46365 | Q2: 19-09-2026 | Y2: 17-10-2026 | AG2: 31-10-2026 | AO2: 21-11-2026 | AW2: 46065 | BE2: 46154 | BM2: 27-12-2026 | BU2: 30-12-2026 | CC2: 16-01-2027 | CK2: 30-01-2027 | CS2: 46662 | DA2: 27-02-2027 | DI2: 13-03-2027 | DQ2: 46664 | DY2: 24-04-2027 | EG2: 46604 | EO2: 23-05-2027
A3: Players | C3: Arsenal | F3: Aston Villa | I3: Players | K3: Arsenal | N3: Sunderland | Q3: Players | S3: Arsenal | V3: Brighton & Hove Albion | Y3: Players | AA3: Arsenal | AD3: Nottingham Forest | AG3: Players | AI3: Arsenal | AL3: Liverpool | AO3: Players | AQ3: Arsenal | AT3: Newcastle United | AW3: Players | AY3: Arsenal | BB3: Brentford | BE3: Players | BG3: Arsenal | BJ3: Tottenham Hotspur | BM3: Players | BO3: Arsenal | BR3: Crystal Palace | BU3: Players | BW3: Arsenal | BZ3: Fulham | CC3: Players | CE3: Arsenal | CH3: Hull City | CK3: Players | CM3: Arsenal | CP3: Manchester City | CS3: Players | CU3: Arsenal | CX3: Ipswich Town | DA3: Players | DC3: Arsenal | DF3: Manchester United | DI3: Players | DK3: Arsenal | DN3: Chelsea | DQ3: Players | DS3: Arsenal | DV3: Coventry City | DY3: Players | EA3: Arsenal | ED3: AFC Bournemouth | EG3: Players | EI3: Arsenal | EL3: Leeds United | EO3: Players | EQ3: Arsenal | ET3: Everton
A4: Players | B4: Position | C4: Years | D4: Played | E4: Scored | F4: Years | G4: Played | H4: Scored | I4: Players | J4: Position | K4: Years | L4: Played | M4: Scored | N4: Years | O4: Played | P4: Scored | Q4: Players | R4: Position | S4: Years | T4: Played | U4: Scored | V4: Years | W4: Played | X4: Scored | Y4: Players | Z4: Position | AA4: Years | AB4: Played | AC4: Scored | AD4: Years | AE4: Played | AF4: Scored | AG4: Players | AH4: Position | AI4: Years | AJ4: Played | AK4: Scored | AL4: Years | AM4: Played | AN4: Scored | AO4: Players | AP4: Position | AQ4: Years | AR4: Played | AS4: Scored | AT4: Years | AU4: Played | AV4: Scored | AW4: Players | AX4: Position | AY4: Years | AZ4: Played | BA4: Scored | BB4: Years | BC4: Played | BD4: Scored | BE4: Players | BF4: Position | BG4: Years | BH4: Played | BI4: Scored | BJ4: Years | BK4: Played | BL4: Scored | BM4: Players | BN4: Position | BO4: Years | BP4: Played | BQ4: Scored | BR4: Years | BS4: Played | BT4: Scored | BU4: Players | BV4: Position | BW4: Years | BX4: Played | BY4: Scored | BZ4: Years | CA4: Played | CB4: Scored | CC4: Players | CD4: Position | CE4: Years | CF4: Played | CG4: Scored | CH4: Years | CI4: Played | CJ4: Scored | CK4: Players | CL4: Position | CM4: Years | CN4: Played | CO4: Scored | CP4: Years | CQ4: Played | CR4: Scored | CS4: Players | CT4: Position | CU4: Years | CV4: Played | CW4: Scored | CX4: Years | CY4: Played | CZ4: Scored | DA4: Players | DB4: Position | DC4: Years | DD4: Played | DE4: Scored | DF4: Years | DG4: Played | DH4: Scored | DI4: Players | DJ4: Position | DK4: Years | DL4: Played | DM4: Scored | DN4: Years | DO4: Played | DP4: Scored | DQ4: Players | DR4: Position | DS4: Years | DT4: Played | DU4: Scored | DV4: Years | DW4: Played | DX4: Scored | DY4: Players | DZ4: Position | EA4: Years | EB4: Played | EC4: Scored | ED4: Years | EE4: Played | EF4: Scored | EG4: Players | EH4: Position | EI4: Years | EJ4: Played | EK4: Scored | EL4: Years | EM4: Played | EN4: Scored | EO4: Players | EP4: Position | EQ4: Years | ER4: Played | ES4: Scored | ET4: Years | EU4: Played | EV4: Scored
A5: Calum Chambers | B5: DF | C5: 2014-2021 | D5: 123 | E5: 6 | F5: 2021-2023 | G5: 35 | H5: 1 | I5: Nicklas Bendtner | J5: FW | K5: 2011 | L5: 28 | M5: 8 | N5: 2007-2013 | O5: 136 | P5: 32 | Q5: Chuba Akpom | R5: FW | S5: 2013-2017 | T5: 21 | U5: 5 | V5: 2016 | W5: 10 | X5: 0 | Y5: Chuba Akpom | Z5: FW | AA5: 2013-2017 | AB5: 21 | AC5: 5 | AD5: 2014 | AE5: 7 | AF5: 0 | AG5: Nicolas Anelka | AH5: FW | AI5: 1996-1998 | AJ5: 72 | AK5: 24 | AL5: 2001 | AM5: 20 | AN5: 4 | AO5: Sol Campbell | AP5: DF | AQ5: 2001-2009 | AR5: 187 | AS5: 10 | AT5: 2010 | AU5: 7 | AV5: 0 | AW5: Chuba Akpom | AX5: FW | AY5: 2013-2017 | AZ5: 21 | BA5: 5 | BB5: 2013 | BC5: 4 | BD5: 0 | BE5: Emmanuel Adebayor | BF5: FW | BG5: 2005-2008 | BH5: 125 | BI5: 54 | BJ5: 2011-2014 | BK5: 106 | BL5: 40 | BM5: Emmanuel Adebayor | BN5: FW | BO5: 2005-2008 | BP5: 125 | BQ5: 54 | BR5: 2015 | BS5: 15 | BT5: 1 | BU5: Luís Boa Morte | BV5: FW | BW5: 1997-1999 | BX5: 29 | BY5: 2 | BZ5: 2000-2006 | CA5: 210 | CB5: 46 | CC5: Chuba Akpom | CD5: FW | CE5: 2013-2017 | CF5: 21 | CG5: 5 | CH5: 2015 | CI5: 40 | CJ5: 7 | CK5: Emmanuel Adebayor | CL5: FW | CM5: 2005-2008 | CN5: 125 | CO5: 54 | CP5: 2009-2010 | CQ5: 38 | CR5: 19 | CS5: Chuba Akpom | CT5: FW | CU5: 2013-2017 | CV5: 21 | CW5: 5 | CX5: 2025-2026 | CY5: 35 | CZ5: 4 | DA5: Henrikh Mkhitaryan | DB5: MF | DC5: 2017-2019 | DD5: 59 | DE5: 9 | DF5: 2016-2017 | DG5: 63 | DH5: 13 | DI5: Nicolas Anelka | DJ5: FW | DK5: 1996-1998 | DL5: 72 | DM5: 24 | DN5: 2007-2011 | DO5: 162 | DP5: 50 | DQ5: Chuba Akpom | DR5: FW | DS5: 2013-2017 | DT5: 21 | DU5: 5 | DV5: 2013 | DW5: 6 | DX5: 0 | DY5: Kepa Arrizabalaga | DZ5: GK | EA5: 2025-2026 | EB5: 13 | EC5: 0 | ED5: 2024 | EE5: 35 | EF5: 0 | EG5: Kyle Bartley | EH5: DF | EI5: 2009 | EJ5: 1 | EK5: 0 | EL5: 2016 | EM5: 50 | EN5: 6 | EO5: Mikel Arteta | EP5: MF | EQ5: 2011-2015 | ER5: 137 | ES5: 15 | ET5: 2004-2011 | EU5: 186 | EV5: 31
A6: Ezri Konsa | B6: DF | C6: 2026 | D6: 5 | E6: 0 | F6: 2019-2025 | G6: 284 | H6: 12 | I6: Steve Bould | J6: DF | K6: 1999-2000 | L6: 21 | M6: 0 | N6: 1991-1998 | O6: 183 | P6: 2 | Q6: Graham Barrett | R6: FW | S6: 1999 | T6: 2 | U6: 0 | V6: 2002 | W6: 30 | X6: 1 | Y6: Nicklas Bendtner | Z6: FW | AA6: 2007-2013 | AB6: 136 | AC6: 32 | AD6: 2016 | AE6: 17 | AF6: 2 | AG6: Yossi Benayoun | AH6: MF | AI6: 2011 | AJ6: 22 | AK6: 5 | AL6: 2007-2009 | AM6: 120 | AN6: 25 | AO6: Mathieu Debuchy | AP6: DF | AQ6: 2014-2017 | AR6: 31 | AS6: 4 | AT6: 2012-2013 | AU6: 43 | AV6: 1 | AW6: Josh Dasilva | AX6: MF | AY6: 2016-2017 | AZ6: 3 | BA6: 1 | BB6: 2018-2026 | BC6: 157 | BD6: 22 | BE6: David Bentley | BF6: MF | BG6: 2003 | BH6: 1 | BI6: 0 | BJ6: 2008-2010 | BK6: 47 | BL6: 3 | BM6: Tommy Black | BN6: MF | BO6: 1999 | BP6: 1 | BQ6: 0 | BR6: 2000-2003 | BS6: 126 | BT6: 10 | BU6: Calum Chambers | BV6: DF | BW6: 2014-2021 | BX6: 123 | BY6: 6 | BZ6: 2018 | CA6: 33 | CB6: 2 | CC6: Isaac Hayden | CD6: MF | CE6: 2014 | CF6: 1 | CG6: 0 | CH6: 2015 | CI6: 24 | CJ6: 1 | CK6: Nicolas Anelka | CL6: FW | CM6: 1996-1998 | CN6: 72 | CO6: 24 | CP6: 2002-2004 | CQ6: 93 | CR6: 40 | CS6: Jay Emmanuel-Thomas | CT6: FW | CU6: 2010 | CV6: 2 | CW6: 0 | CX6: 2011-2012 | CY6: 71 | CZ6: 8 | DA6: Robin van Persie | DB6: FW | DC6: 2004-2011 | DD6: 239 | DE6: 114 | DF6: 2012-2014 | DG6: 100 | DH6: 55 | DI6: Kepa Arrizabalaga | DJ6: GK | DK6: 2025-2026 | DL6: 13 | DM6: 0 | DN6: 2018-2022 | DO6: 163 | DP6: 0 | DQ6: Graham Barrett | DR6: FW | DS6: 1999 | DT6: 2 | DU6: 0 | DV6: 2003-2004 | DW6: 55 | DX6: 6 | DY6: Vince Bartram | DZ6: GK | EA6: 1994 | EB6: 11 | EC6: 0 | ED6: 1992-1993 | EE6: 86 | EF6: 0 | EG6: Paul Dickov | EH6: FW | EI6: 1992-1996 | EJ6: 21 | EK6: 3 | EL6: 2009 | EM6: 4 | EN6: 0 | EO6: Kevin Campbell | EP6: FW | EQ6: 1991-1994 | ER6: 101 | ES6: 23 | ET6: 1998-2004 | EU6: 145 | EV6: 45
A7: Henri Lansbury | B7: MF | C7: 2009-2011 | D7: 3 | E7: 0 | F7: 2016-2020 | G7: 56 | H7: 4 | I7: Justin Hoyte | J7: DF | K7: 2005 | L7: 27 | M7: 1 | N7: 2002-2007 | O7: 41 | P7: 1 | Q7: Paul Dickov | R7: FW | S7: 1992-1996 | T7: 21 | U7: 3 | V7: 1993 | W7: 8 | X7: 5 | Y7: Kevin Campbell | Z7: FW | AA7: 1991-1994 | AB7: 101 | AC7: 23 | AD7: 1995-1997 | AE7: 83 | AF7: 32 | AG7: Jimmy Carter | AH7: MF | AI7: 1992-1994 | AJ7: 19 | AK7: 2 | AL7: 1991 | AM7: 1 | AN7: 0 | AO7: Bruno Guimarães | AP7: MF | AQ7: 2026 | AR7: 5 | AS7: 1 | AT7: 2021-2025 | AU7: 195 | AV7: 31 | AW7: Paul Davis | AX7: MF | AY7: 1991-1994 | AZ7: 35 | BA7: 1 | BB7: 1995 | BC7: 5 | BD7: 0 | BE7: Sol Campbell | BF7: DF | BG7: 2001-2009 | BH7: 187 | BI7: 10 | BJ7: 1992-2000 | BK7: 257 | BL7: 10 | BM7: Marouane Chamakh | BN7: FW | BO7: 2010-2012 | BP7: 51 | BQ7: 11 | BR7: 2013-2015 | BS7: 64 | BT7: 9 | BU7: Emmanuel Frimpong | BV7: MF | BW7: 2011 | BX7: 9 | BY7: 0 | BZ7: 2012 | CA7: 6 | CB7: 0 | CC7: Sebastian Larsson | CD7: MF | CE7: 2005 | CF7: 4 | CG7: 0 | CH7: 2017 | CI7: 40 | CJ7: 2 | CK7: Gaël Clichy | CL7: DF | CM7: 2003-2010 | CN7: 228 | CO7: 1 | CP7: 2011-2016 | CQ7: 186 | CR7: 3 | CS7: Francis Jeffers | CT7: FW | CU7: 2001-2002 | CV7: 29 | CW7: 4 | CX7: 2006 | CY7: 9 | CZ7: 4 | DA7: Mikaël Silvestre | DB7: DF | DC7: 2008-2009 | DD7: 35 | DE7: 3 | DF7: 1999-2007 | DG7: 313 | DH7: 8 | DI7: Pierre-Emerick Aubameyang | DJ7: FW | DK7: 2017-2021 | DL7: 163 | DM7: 92 | DN7: 2022 | DO7: 21 | DP7: 3 | DQ7: Julian Gray | DR7: MF | DS7: 1999 | DT7: 1 | DU7: 0 | DV7: 2007-2008 | DW7: 29 | DX7: 4 | DY7: Ryan Garry | DZ7: DF | EA7: 2002 | EB7: 1 | EC7: 0 | ED7: 2007-2010 | EE7: 77 | EF7: 3 | EG7: Glen Kamara | EH7: MF | EI7: 2014-2016 | EJ7: 1 | EK7: 0 | EL7: 2023 | EM7: 39 | EN7: 0 | EO7: Stephen Hughes | EP7: MF | EQ7: 1994-1999 | ER7: 54 | ES7: 5 | ET7: 1999-2000 | EU7: 29 | EV7: 1
A8: Emiliano Martínez | B8: GK | C8: 2014-2020 | D8: 40 | E8: 0 | F8: 2020-2025 | G8: 255 | H8: 0 | I8: Sebastian Larsson | J8: MF | K8: 2011-2016 | L8: 184 | M8: 13 | N8: 2005 | O8: 4 | P8: 0 | Q8: Mark Flatts | R8: MF | S8: 1992-1994 | T8: 16 | U8: 0 | V8: 1993 | W8: 10 | X8: 1 | Y8: Carl Jenkinson | Z8: DF | AA8: 2011-2018 | AB8: 66 | AC8: 3 | AD8: 2019-2020 | AE8: 15 | AF8: 0 | AG8: Alex Oxlade-Chamberlain | AH8: MF | AI8: 2011-2017 | AJ8: 181 | AK8: 17 | AL8: 2017-2022 | AM8: 148 | AN8: 18 | AO8: Isaac Hayden | AP8: MF | AQ8: 2014 | AR8: 1 | AS8: 0 | AT8: 2016-2021 | AU8: 171 | AV8: 7 | AW8: Ezri Konsa | AX8: DF | AY8: 2026 | AZ8: 5 | BA8: 0 | BB8: 2018 | BC8: 47 | BD8: 1 | BE8: William Gallas | BF8: DF | BG8: 2006-2009 | BH8: 127 | BI8: 13 | BJ8: 2010-2012 | BK8: 76 | BL8: 1 | BM8: Ashley Cole | BN8: DF | BO8: 1999-2005 | BP8: 201 | BQ8: 9 | BR8: 1999 | BS8: 14 | BT8: 1 | BU8: Julian Gray | BV8: MF | BW8: 1999 | BX8: 1 | BY8: 0 | BZ8: 2008 | CA8: 1 | CB8: 0 | CC8: Vito Mannone | CD8: GK | CE8: 2008-2012 | CF8: 23 | CG8: 0 | CH8: 2010-2011 | CI8: 31 | CJ8: 0 | CK8: Paul Dickov | CL8: FW | CM8: 1992-1996 | CN8: 21 | CO8: 3 | CP8: 1996-2006 | CQ8: 172 | CR8: 33 | CS8: Tyreece John-Jules | CT8: FW | CU8: 2017-2020 | CV8: 37 | CW8: 15 | CX8: 2022 | CY8: 18 | CZ8: 3 | DA8: Alexis Sánchez | DB8: FW | DC8: 2014-2017 | DD8: 163 | DE8: 79 | DF8: 2017-2018 | DG8: 45 | DH8: 5 | DI8: Yossi Benayoun | DJ8: MF | DK8: 2011 | DL8: 22 | DM8: 5 | DN8: 2010-2012 | DO8: 20 | DP8: 1 | DQ8: Viktor Gyökeres | DR8: FW | DS8: 2025-2026 | DT8: 59 | DU8: 21 | DV8: 2020-2022 | DW8: 113 | DX8: 43 | DY8: Neto | DZ8: GK | EA8: 2024 | EB8: 1 | EC8: 0 | ED8: 2022-2024 | EE8: 63 | EF8: 0 | EG8: John Lukic | EH8: GK | EI8: 1996-2000 | EJ8: 19 | EK8: 0 | EL8: 1992-1995 | EM8: 138 | EN8: 0 | EO8: Alex Iwobi | EP8: MF | EQ8: 2014-2018 | ER8: 150 | ES8: 15 | ET8: 2019-2023 | EU8: 140 | EV8: 9
A9: Paul Merson | B9: MF | C9: 1991-1996 | D9: 166 | E9: 30 | F9: 1998-2001 | G9: 117 | H9: 18 | I9: Vito Mannone | J9: GK | K9: 2013-2016 | L9: 73 | M9: 0 | N9: 2008-2012 | O9: 23 | P9: 0 | Q9: Viktor Gyökeres | R9: FW | S9: 2025-2026 | T9: 58 | U9: 21 | V9: 2017-2020 | W9: 34 | X9: 13 | Y9: Henri Lansbury | Z9: MF | AA9: 2009-2011 | AB9: 3 | AC9: 0 | AD9: 2012-2016 | AE9: 149 | AF9: 33 | AG9: Jermaine Pennant | AH9: MF | AI9: 2001-2004 | AJ9: 15 | AK9: 3 | AL9: 2006-2008 | AM9: 72 | AN9: 3 | AO9: Mikel Merino | AP9: MF | AQ9: 2024-2026 | AR9: 84 | AS9: 16 | AT9: 2017 | AU9: 25 | AV9: 1 | AW9: Scott Marshall | AX9: DF | AY9: 1992-1997 | AZ9: 24 | BA9: 1 | BB9: 1999-2002 | BC9: 75 | BD9: 16 | BM9: Paul Dickov | BN9: FW | BO9: 1992-1996 | BP9: 21 | BQ9: 3 | BR9: 2007 | BS9: 9 | BT9: 0 | BU9: Stephen Hughes | BV9: MF | BW9: 1994-1999 | BX9: 54 | BY9: 5 | BZ9: 1999 | CA9: 3 | CB9: 0 | CC9: Ray Parlour | CD9: MF | CE9: 1992-2003 | CF9: 377 | CG9: 26 | CH9: 2006 | CI9: 15 | CJ9: 0 | CK9: Neil Heaney | CM9: 1992-1993 | CN9: 6 | CO9: 0 | CP9: 1996-1998 | CQ9: 18 | CR9: 1 | CS9: Chris Kiwomya | CT9: FW | CU9: 1994 | CV9: 14 | CW9: 3 | CX9: 1992-1994 | CY9: 90 | CZ9: 18 | DA9: Danny Welbeck | DB9: FW | DC9: 2014-2018 | DD9: 128 | DE9: 33 | DF9: 2008-2014 | DG9: 112 | DH9: 24 | DI9: Ashley Cole | DJ9: DF | DK9: 1999-2005 | DL9: 201 | DM9: 9 | DN9: 2006-2013 | DO9: 292 | DP9: 7 | DQ9: John Hartson | DR9: FW | DS9: 1994-1996 | DT9: 55 | DU9: 14 | DV9: 2000 | DW9: 12 | DX9: 6 | DY9: Aaron Ramsdale | DZ9: GK | EA9: 2021-2024 | EB9: 89 | EC9: 0 | ED9: 2016-2019 | EE9: 37 | EF9: 0 | EG9: Illan Meslier | EH9: GK | EI9: 2026 | EJ9: 0 | EL9: 2019-2025 | EM9: 214 | EN9: 0 | EO9: Francis Jeffers | EP9: FW | EQ9: 2001-2002 | ER9: 29 | ES9: 4 | ET9: 1997-2003 | EU9: 67 | EV9: 18
A10: Robert Pirès | B10: MF | C10: 2000-2005 | D10: 252 | E10: 73 | F10: 2010 | G10: 9 | H10: 0 | I10: Mart Poom | J10: GK | K10: 2002-2004 | L10: 58 | M10: 0 | N10: 2006 | O10: 1 | P10: 0 | Q10: Gavin Hoyte | R10: DF | S10: 2008 | T10: 1 | U10: 0 | V10: 2009 | W10: 18 | X10: 0 | Y10: Jordi Osei-Tutu | Z10: MF | AA10: 2016-2018 | AB10: 29 | AC10: 2 | AD10: 2021 | AE10: 4 | AF10: 0 | AG10: Raheem Sterling | AH10: FW | AI10: 2024 | AJ10: 28 | AK10: 1 | AL10: 2011-2014 | AM10: 119 | AN10: 22 | AO10: Aaron Ramsdale | AP10: GK | AQ10: 2021-2024 | AR10: 89 | AS10: 0 | AT10: 2025 | AU10: 23 | AV10: 0 | AW10: Reiss Nelson | AX10: MF | AY10: 2016-2024 | AZ10: 50 | BA10: 3 | BB10: 2025 | BC10: 14 | BD10: 1 | BM10: Eberechi Eze | BN10: MF | BO10: 2025-2026 | BP10: 58 | BQ10: 10 | BR10: 2020-2025 | BS10: 171 | BT10: 41 | BU10: Junichi Inamoto | BV10: MF | BW10: 2001 | BX10: 2 | BY10: 0 | BZ10: 2002-2003 | CA10: 46 | CB10: 4 | CC10: David Rocastle | CD10: MF | CE10: 1991 | CF10: 4 | CG10: 0 | CH10: 1997 | CI10: 10 | CJ10: 1 | CK10: Gabriel Jesus | CL10: FW | CM10: 2022-2025 | CN10: 123 | CO10: 32 | CP10: 2016-2021 | CQ10: 236 | CR10: 95 | CS10: Ainsley Maitland-Niles | CT10: DF | CU10: 2014-2021 | CV10: 151 | CW10: 3 | CX10: 2015 | CY10: 32 | CZ10: 2 | DI10: Lassana Diarra | DJ10: MF | DK10: 2007 | DL10: 10 | DM10: 0 | DN10: 2005-2006 | DO10: 20 | DP10: 0 | DQ10: Stephen Hughes | DR10: MF | DS10: 1994-1999 | DT10: 54 | DU10: 5 | DV10: 2004-2007 | DW10: 133 | DX10: 6 | DY10: Jack Wilshere | DZ10: MF | EA10: 2008-2017 | EB10: 169 | EC10: 12 | ED10: 2016-2020 | EE10: 43 | EF10: 2 | EG10: Eddie Nketiah | EH10: FW | EI10: 2016-2024 | EJ10: 206 | EK10: 65 | EL10: 2019 | EM10: 19 | EN10: 5 | EO10: Martin Keown | EP10: DF | EQ10: 1992-2003 | ER10: 347 | ES10: 7 | ET10: 1992 | EU10: 13 | EV10: 0
A11: David Platt | B11: MF | C11: 1995-1997 | D11: 92 | E11: 13 | F11: 1990 | G11: 4 | H11: 2 | I11: Stefan Schwarz | J11: MF | K11: 1999-2001 | L11: 67 | M11: 3 | N11: 1994 | O11: 34 | P11: 2 | Q11: Colin Pates | R11: DF | S11: 1991-1992 | T11: 9 | U11: 1 | V11: 1993-1994 | W11: 50 | X11: 0 | Y11: David Platt | Z11: MF | AA11: 1995-1997 | AB11: 92 | AC11: 13 | AD11: 1999-2000 | AE11: 5 | AF11: 0 | AG11: Michael Thomas | AH11: MF | AI11: 1991 | AJ11: 2 | AK11: 0 | AL11: 1992-1997 | AM11: 111 | AN11: 6 | AO11: Joe Willock | AP11: MF | AQ11: 2016-2020 | AR11: 105 | AS11: 18 | AT11: 2020-2026 | AU11: 188 | AV11: 21 | AW11: Christian Nørgaard | AX11: MF | AY11: 2025 | AZ11: 20 | BA11: 0 | BB11: 2019-2024 | BC11: 192 | BD11: 13 | BM11: Mathieu Flamini | BN11: MF | BO11: 2004-2015 | BP11: 216 | BQ11: 12 | BR11: 2016 | BS11: 13 | BT11: 0 | BU11: Alex Iwobi | BV11: MF | BW11: 2014-2018 | BX11: 150 | BY11: 15 | BZ11: 2023-2026 | CA11: 114 | CB11: 19 | CK11: Eddie McGoldrick | CL11: MF | CM11: 1993-1995 | CN11: 38 | CO11: 0 | CP11: 1996-1998 | CQ11: 40 | CR11: 0 | CS11: Paolo Vernazza | CT11: MF | CU11: 1997-2000 | CV11: 6 | CW11: 1 | CX11: 1998 | CY11: 2 | CZ11: 0 | DI11: Cesc Fàbregas | DJ11: MF | DK11: 2004-2010 | DL11: 267 | DM11: 48 | DN11: 2014-2018 | DO11: 199 | DP11: 22 | DQ11: Alan Miller | DR11: GK | DS11: 1991-1993 | DT11: 8 | DU11: 0 | DV11: 2000 | DW11: 1 | DX11: 0 | EG11: David O'Leary | EH11: DF | EI11: 1991-1992 | EJ11: 12 | EK11: 0 | EL11: 1993 | EM11: 10 | EN11: 0 | EO11: Anders Limpar | EP11: MF | EQ11: 1991-1993 | ER11: 36 | ES11: 3 | ET11: 1993-1996 | EU11: 66 | EV11: 5
A12: Philippe Senderos | B12: DF | C12: 2004-2007 | D12: 82 | E12: 4 | F12: 2014 | G12: 9 | H12: 0 | I12: Danny Welbeck | J12: FW | K12: 2010 | L12: 26 | M12: 6 | N12: 2014-2018 | O12: 128 | P12: 33 | Q12: Mathew Ryan | R12: GK | S12: 2020 | T12: 3 | U12: 0 | V12: 2017-2020 | W12: 123 | X12: 0 | Y12: Aaron Ramsey | Z12: MF | AA12: 2008-2018 | AB12: 338 | AC12: 58 | AD12: 2010 | AE12: 5 | AF12: 0 | AG12: Kolo Touré | AH12: DF | AI12: 2002-2008 | AJ12: 285 | AK12: 11 | AL12: 2013-2015 | AM12: 67 | AN12: 1 | AW12: Isaiah Rankin | AX12: FW | AY12: 1997 | AZ12: 1 | BA12: 0 | BB12: 2004-2005 | BC12: 78 | BD12: 15 | BM12: Julian Gray | BN12: MF | BO12: 1999 | BP12: 1 | BQ12: 0 | BR12: 2000-2003 | BS12: 125 | BT12: 11 | BU12: Bernd Leno | BV12: GK | BW12: 2018-2021 | BX12: 125 | BY12: 0 | BZ12: 2022-2026 | CA12: 160 | CB12: 0 | CK12: Samir Nasri | CL12: MF | CM12: 2008-2011 | CN12: 109 | CO12: 23 | CP12: 2011-2016 | CQ12: 161 | CR12: 21 | CS12: Richard Wright | CT12: GK | CU12: 2001 | CV12: 16 | CW12: 0 | CX12: 1994-2011 | CY12: 299 | CZ12: 0 | DI12: William Gallas | DJ12: DF | DK12: 2006-2009 | DL12: 127 | DM12: 13 | DN12: 2001-2005 | DO12: 194 | DP12: 13 | EG12: Jermaine Pennant | EH12: MF | EI12: 2001-2004 | EJ12: 15 | EK12: 3 | EL12: 2003 | EM12: 36 | EN12: 2 | EO12: Ainsley Maitland-Niles | EP12: DF | EQ12: 2014-2021 | ER12: 151 | ES12: 3 | ET12: 2026 | EU12: 2 | EV12: 1
A13: Stuart Taylor | B13: GK | C13: 2000-2002 | D13: 23 | E13: 0 | F13: 2005-2007 | G13: 12 | H13: 0 | I13: Granit Xhaka | J13: MF | K13: 2025-2026 | L13: 39 | M13: 1 | N13: 2016-2022 | O13: 297 | P13: 23 | Q13: Rami Shaaban | R13: GK | S13: 2002 | T13: 5 | U13: 0 | V13: 2004 | W13: 6 | X13: 0 | Y13: Nuno Tavares | Z13: DF | AA13: 2021 | AB13: 28 | AC13: 1 | AD13: 2023 | AE13: 12 | AF13: 0 | AW13: David Raya | AX13: GK | AY13: 2023-2026 | AZ13: 153 | BA13: 0 | BB13: 2019-2022 | BC13: 155 | BD13: 0 | BM13: Rob Holding | BN13: DF | BO13: 2016-2023 | BP13: 172 | BQ13: 6 | BR13: 2023-2024 | BS13: 6 | BT13: 0 | BU13: Reiss Nelson | BV13: FW | BW13: 2016-2024 | BX13: 127 | BY13: 26 | BZ13: 2024 | CA13: 12 | CB13: 2 | CK13: David Rocastle | CL13: MF | CM13: 1991 | CN13: 4 | CO13: 0 | CP13: 1993 | CQ13: 21 | CR13: 2 | DI13: Olivier Giroud | DJ13: FW | DK13: 2012-2017 | DL13: 237 | DM13: 96 | DN13: 2017-2020 | DO13: 119 | DP13: 39 | EG13: David Rocastle | EH13: MF | EI13: 1991 | EJ13: 4 | EK13: 0 | EL13: 1992-1993 | EM13: 28 | EN13: 2 | EO13: Shkodran Mustafi | EP13: DF | EQ13: 2016-2020 | ER13: 151 | ES13: 9 | ET13: 2009 | EU13: 1 | EV13: 0
Q14: Leandro Trossard | R14: FW | S14: 2022-2025 | T14: 174 | U14: 36 | V14: 2019-2022 | W14: 121 | X14: 25 | Y14: Armand Traoré | Z14: DF | AA14: 2007-2011 | AB14: 15 | AC14: 0 | AD14: 2016-2017 | AE14: 32 | AF14: 0 | AW14: Wojciech Szczęsny | AX14: GK | AY14: 2010-2014 | AZ14: 160 | BA14: 0 | BB14: 2009 | BC14: 28 | BD14: 0 | BM14: Andy Linighan | BN14: DF | BO14: 1991-1996 | BP14: 95 | BQ14: 6 | BR14: 1996-2000 | BS14: 111 | BT14: 4 | BU14: Ian Selley | BV14: MF | BW14: 1992-1996 | BX14: 40 | BY14: 0 | BZ14: 1997-1999 | CA14: 3 | CB14: 0 | CK14: Bacary Sagna | CL14: DF | CM14: 2007-2013 | CN14: 251 | CO14: 4 | CP14: 2014-2016 | CQ14: 85 | CR14: 0 | DI14: Kai Havertz | DJ14: MF, FW | DK14: 2023-2026 | DL14: 117 | DM14: 39 | DN14: 2020-2022 | DO14: 139 | DP14: 32 | EG14: Stuart Taylor | EH14: GK | EI14: 2000-2002 | EJ14: 23 | EK14: 0 | EL14: 2014 | EM14: 5 | EN14: 0 | EO14: Philippe Senderos | EP14: DF | EQ14: 2004-2007 | ER14: 82 | ES14: 4 | ET14: 2009 | EU14: 3 | EV14: 0
Q15: Matt Upson | R15: DF | S15: 1997-2001 | T15: 43 | U15: 0 | V15: 2012-2013 | W15: 61 | X15: 3 | Y15: Matt Turner | Z15: GK | AA15: 2022-2023 | AB15: 7 | AC15: 0 | AD15: 2023-2024 | AE15: 21 | AF15: 0 | AW15: Nico Yennaris | AX15: DF | AY15: 2011 | AZ15: 1 | BA15: 0 | BB15: 2013-2018 | BC15: 157 | BD15: 12 | BM15: Eddie McGoldrick | BN15: MF | BO15: 1993-1995 | BP15: 38 | BQ15: 0 | BR15: 1992 | BS15: 42 | BT15: 8 | BU15: Philippe Senderos | BV15: DF | BW15: 2004-2007 | BX15: 82 | BY15: 4 | BZ15: 2010-2013 | CA15: 59 | CB15: 2 | CK15: David Seaman | CL15: GK | CM15: 1991-2002 | CN15: 374 | CO15: 0 | CP15: 2003 | CQ15: 23 | CR15: 0 | DI15: Jorginho | DJ15: MF | DK15: 2022-2024 | DL15: 79 | DM15: 2 | DN15: 2018-2022 | DO15: 213 | DP15: 29 | EG15: Ben White | EH15: DF | EI15: 2021-2026 | EJ15: 196 | EK15: 7 | EL15: 2019 | EM15: 49 | EN15: 1 | EO15: Theo Walcott | EP15: FW | EQ15: 2006-2017 | ER15: 355 | ES15: 93 | ET15: 2017-2020 | EU15: 85 | EV15: 11
Q16: Danny Welbeck | R16: FW | S16: 2014-2018 | T16: 128 | U16: 33 | V16: 2020-2025 | W16: 201 | X16: 51 | Y16: Matt Upson | Z16: DF | AA16: 1997-2001 | AB16: 43 | AC16: 0 | AD16: 2000 | AE16: 1 | AF16: 0 | BM16: Eddie Nketiah | BN16: FW | BO16: 2016-2024 | BP16: 206 | BQ16: 65 | BR16: 2024-2026 | BS16: 59 | BT16: 11 | BU16: Emile Smith Rowe | BV16: MF,FW | BW16: 2016-2023 | BX16: 140 | BY16: 25 | BZ16: 2024-2026 | CA16: 88 | CB16: 12 | CK16: Raheem Sterling | CL16: FW | CM16: 2024 | CN16: 28 | CO16: 1 | CP16: 2015-2021 | CQ16: 338 | CR16: 131 | DI16: David Luiz | DJ16: DF | DK16: 2019-2020 | DL16: 73 | DM16: 4 | DN16: 2010-2018 | DO16: 218 | DP16: 17 | EO16: Richard Wright | EP16: GK | EQ16: 2001 | ER16: 16 | ES16: 0 | ET16: 2002-2006 | EU16: 60 | EV16: 0
Q17: Ben White | R17: DF | S17: 2021-2026 | T17: 195 | U17: 7 | V17: 2016-2020 | W17: 46 | X17: 0 | Y17: Ian Wright | Z17: FW | AA17: 1992-1997 | AB17: 195 | AC17: 106 | AD17: 1999 | AE17: 10 | AF17: 5 | BM17: Albert Sambi Lokonga | BN17: MF | BO17: 2021-2022 | BP17: 39 | BQ17: 0 | BR17: 2022 | BS17: 9 | BT17: 0 | BU17: Cédric Soares | BV17: DF | BW17: 2019-2023 | BX17: 65 | BY17: 2 | BZ17: 2022 | CA17: 8 | CB17: 0 | CK17: Sylvinho | CL17: DF | CM17: 1999-2000 | CN17: 71 | CO17: 5 | CP17: 2009 | CQ17: 10 | CR17: 0 | DI17: Noni Madueke | DJ17: FW | DK17: 2025-2026 | DL17: 48 | DM17: 9 | DN17: 2022-2025 | DO17: 90 | DP17: 19
Y18: Oleksandr Zinchenko | Z18: DF | AA18: 2022-2024 | AB18: 91 | AC18: 3 | AD18: 2025 | AE18: 10 | AF18: 0 | BM18: Yaya Sanogo | BN18: FW | BO18: 2013-2016 | BP18: 17 | BQ18: 5 | BR18: 2014 | BS18: 11 | BT18: 1 | BU18: Willian | BV18: MF,FW | BW18: 2020 | BX18: 37 | BY18: 1 | BZ18: 2022-2024 | CA18: 79 | CB18: 10 | CK18: Kolo Touré | CL18: DF | CM18: 2002-2008 | CN18: 285 | CO18: 11 | CP18: 2009-2012 | CQ18: 89 | CR18: 2 | DI18: Emiliano Martínez | DJ18: GK | DK18: 2014-2020 | DL18: 40 | DM18: 0 | DN18: 2026 | DO18: 3 | DP18: 0
BM19: Stuart Taylor | BN19: GK | BO19: 2000-2002 | BP19: 23 | BQ19: 0 | BR19: 2000 | BS19: 10 | BT19: 0 | CK19: Patrick Vieira | CL19: MF | CM19: 1996-2004 | CN19: 347 | CO19: 30 | CP19: 2009-2010 | CQ19: 35 | CR19: 3 | DI19: Emmanuel Petit | DJ19: MF | DK19: 1997-1999 | DL19: 100 | DM19: 9 | DN19: 2001-2003 | DO19: 60 | DP19: 2
BM20: Takehiro Tomiyasu | BN20: DF | BO20: 2021-2024 | BP20: 85 | BQ20: 2 | BR20: 2026 | BS20: 4 | BT20: 0 | CK20: Oleksandr Zinchenko | CL20: DF | CM20: 2022-2024 | CN20: 91 | CO20: 3 | CP20: 2017-2021 | CQ20: 128 | CR20: 2 | DI20: David Rocastle | DJ20: MF | DK20: 1991 | DL20: 4 | DM20: 0 | DN20: 1994-1995 | DO20: 29 | DP20: 0
BM21: Matt Turner | BN21: GK | BO21: 2022-2023 | BP21: 7 | BQ21: 0 | BR21: 2024 | BS21: 4 | BT21: 0 | DI21: Raheem Sterling | DJ21: FW | DK21: 2024 | DL21: 28 | DM21: 1 | DN21: 2022-2023 | DO21: 81 | DP21: 19
BM22: Matt Upson | BN22: DF | BO22: 1997-2001 | BP22: 43 | BQ22: 0 | BR22: 2000 | BS22: 7 | BT22: 0 | DI22: Danny Welbeck | DJ22: FW | DK22: 2014-2018 | DL22: 128 | DM22: 33 | DN22: 2026 | DO22: 4 | DP22: 3
DI23: Willian | DJ23: FW | DK23: 2020 | DL23: 37 | DM23: 1 | DN23: 2013-2019 | DO23: 333 | DP23: 63
DI24: Petr Čech | DJ24: GK | DK24: 2015-2018 | DL24: 139 | DM24: 0 | DN24: 2004-2020 | DO24: 443 | DP24: 0
A28: Pair | B28: Club A | C28: Club B | D28: Division | E28: Match Date | F28: FBref Link | G28: Link Status
A29: Arsenal – Aston Villa | B29: Arsenal | C29: Aston Villa | D29: Premier League | E29: 31/08/2026 | F29: https://fbref.com/en/friv/players-who-played-for-multiple-clubs-countries.fcgi?level=franch&t1=153995&t2=164959&t3=--&t4=-- | G29: Verified direct FBref pair page
A30: Arsenal – Sunderland | B30: Arsenal | C30: Sunderland | D30: Premier League | E30: 46365 | F30: https://fbref.com/en/friv/players-who-played-for-multiple-clubs-countries.fcgi?level=franch&t1=153995&t2=165900&t3=--&t4=-- | G30: Verified direct FBref pair page
A31: Arsenal – Brighton | B31: Arsenal | C31: Brighton & Hove Albion | D31: Premier League | E31: 19/09/2026 | F31: https://fbref.com/en/friv/players-who-played-for-multiple-clubs-countries.fcgi?level=franch&t1=153995&t2=172401&t3=--&t4=-- | G31: Verified direct FBref pair page
A32: Arsenal – Nottingham Forest | B32: Arsenal | C32: Nottingham Forest | D32: Premier League | E32: 17/10/2026 | F32: https://fbref.com/en/friv/players-who-played-for-multiple-clubs-countries.fcgi?level=franch&t1=153995&t2=174440&t3=--&t4=-- | G32: Verified direct FBref pair page
A33: Arsenal – Liverpool | B33: Arsenal | C33: Liverpool | D33: Premier League | E33: 46033 | F33: https://fbref.com/en/friv/players-who-played-for-multiple-clubs-countries.fcgi?level=franch&t1=153995&t2=164575&t3=--&t4=-- | G33: Verified direct FBref pair page
A34: Arsenal – Newcastle United | B34: Arsenal | C34: Newcastle United | D34: Premier League | E34: 21/11/2026 | F34: https://fbref.com/en/friv/players-who-played-for-multiple-clubs-countries.fcgi?level=franch&t1=153995&t2=169487&t3=--&t4=-- | G34: Verified direct FBref pair page
A35: Arsenal – Brentford | B35: Arsenal | C35: Brentford | D35: Premier League | E35: 46065 | F35: https://fbref.com/en/friv/players-who-played-for-multiple-clubs-countries.fcgi?level=franch&t1=153995&t2=172049&t3=--&t4=-- | G35: Verified direct FBref pair page
A36: Arsenal – Tottenham Hotspur | B36: Arsenal | C36: Tottenham Hotspur | D36: Premier League | E36: 46154 | F36: https://fbref.com/en/friv/players-who-played-for-multiple-clubs-countries.fcgi?level=franch&t1=153995&t2=157033&t3=--&t4=-- | G36: Verified direct FBref pair page
A37: Arsenal – Crystal Palace | B37: Arsenal | C37: Crystal Palace | D37: Premier League | E37: 27/12/2026 | F37: https://fbref.com/en/friv/players-who-played-for-multiple-clubs-countries.fcgi?level=franch&t1=153995&t2=158744&t3=--&t4=-- | G37: Verified direct FBref pair page
A38: Arsenal – Fulham | B38: Arsenal | C38: Fulham | D38: Premier League | E38: 30/12/2026 | F38: https://fbref.com/en/friv/players-who-played-for-multiple-clubs-countries.fcgi?level=franch&t1=153995&t2=176928&t3=--&t4=-- | G38: Verified direct FBref pair page
A39: Arsenal – Hull City | B39: Arsenal | C39: Hull City | D39: Premier League | E39: 16/01/2027 | F39: https://fbref.com/en/friv/players-who-played-for-multiple-clubs-countries.fcgi?level=franch&t1=153995&t2=170536&t3=--&t4=-- | G39: Verified direct FBref pair page
A40: Arsenal – Manchester City | B40: Arsenal | C40: Manchester City | D40: Premier League | E40: 30/01/2027 | F40: https://fbref.com/en/friv/players-who-played-for-multiple-clubs-countries.fcgi?level=franch&t1=153995&t2=170087&t3=--&t4=-- | G40: Verified direct FBref pair page
A41: Arsenal – Ipswich Town | B41: Arsenal | C41: Ipswich Town | D41: Premier League | E41: 46662 | F41: https://fbref.com/en/friv/players-who-played-for-multiple-clubs-countries.fcgi?level=franch&t1=153995&t2=169910&t3=--&t4=-- | G41: Verified direct FBref pair page
A42: Arsenal – Manchester United | B42: Arsenal | C42: Manchester United | D42: Premier League | E42: 27/02/2027 | F42: https://fbref.com/en/friv/players-who-played-for-multiple-clubs-countries.fcgi?level=franch&t1=153995&t2=154064&t3=--&t4=-- | G42: Verified direct FBref pair page
A43: Arsenal – Chelsea | B43: Arsenal | C43: Chelsea | D43: Premier League | E43: 13/03/2027 | F43: https://fbref.com/en/friv/players-who-played-for-multiple-clubs-countries.fcgi?level=franch&t1=153995&t2=172343&t3=--&t4=-- | G43: Verified direct FBref pair page
A44: Arsenal – Coventry City | B44: Arsenal | C44: Coventry City | D44: Premier League | E44: 46664 | F44: https://fbref.com/en/friv/players-who-played-for-multiple-clubs-countries.fcgi?level=franch&t1=153995&t2=176340&t3=--&t4=-- | G44: Verified direct FBref pair page
A45: Arsenal – AFC Bournemouth | B45: Arsenal | C45: AFC Bournemouth | D45: Premier League | E45: 24/04/2027 | F45: https://fbref.com/en/friv/players-who-played-for-multiple-clubs-countries.fcgi?level=franch&t1=153995&t2=159149&t3=--&t4=-- | G45: Verified direct FBref pair page
A46: Arsenal – Leeds United | B46: Arsenal | C46: Leeds United | D46: Premier League | E46: 46604 | F46: https://fbref.com/en/friv/players-who-played-for-multiple-clubs-countries.fcgi?level=franch&t1=153995&t2=160763&t3=--&t4=-- | G46: Verified direct FBref pair page
A47: Arsenal – Everton | B47: Arsenal | C47: Everton | D47: Premier League | E47: 23/05/2027 | F47: https://fbref.com/en/friv/players-who-played-for-multiple-clubs-countries.fcgi?level=franch&t1=153995&t2=172780&t3=--&t4=-- | G47: Verified direct FBref pair page

Sheet Arsenal
A1: Player | B1: Years | C1: Apps | D1: Min | E1: Goals | F1: Ast
A2: Tony Adams | B2: 1991-2001 | C2: 285 | D2: 25076 | E2: 13 | F2: 9
A3: Emmanuel Adebayor | B3: 2005-2008 | C3: 125 | D3: 9400 | E3: 54 | F3: 18
A4: Michelle Agyemang | B4: 2022-2023 | C4: 5 | D4: 23 | E4: 0 | F4: 0
A5: Chuba Akpom | B5: 2013-2017 | C5: 21 | D5: 1024 | E5: 5 | F5: 2
A6: Ryan Alebiosu | B6: 2019-2021 | C6: 29 | D6: 2235 | E6: 1 | F6: 6
A7: Rúnar Alex Rúnarsson | B7: 2020 | C7: 6 | D7: 466 | E7: 0 | F7: 0
A8: Jérémie Aliadière | B8: 2001-2006 | C8: 31 | D8: 764 | E8: 1 | F8: 1
A9: Manuel Almunia | B9: 2004-2010 | C9: 141 | D9: 12608 | E9: 0 | F9: 2
A10: Nicolas Anelka | B10: 1996-1998 | C10: 72 | D10: 4948 | E10: 24 | F10: 12
A11: Martin Angha | B11: 2012 | C11: 1 | D11: 7 | E11: 0 | F11: 0
A12: Andre Annous | B12: 2024-2026 | C12: 32 | D12: 2150 | E12: 8 | F12: 1
A13: José Antonio Reyes | B13: 2003-2005 | C13: 89 | D13: 5827 | E13: 17 | F13: 25
A14: Janni Arnth | B14: 2018 | C14: 6 | D14: 256 | E14: 1 | F14: 0
A15: Kepa Arrizabalaga | B15: 2025-2026 | C15: 13 | D15: 1166 | E15: 0 | F15: 0
A16: Andrey Arshavin | B16: 2008-2012 | C16: 123 | D16: 7285 | E16: 27 | F16: 26
A17: Mikel Arteta | B17: 2011-2015 | C17: 137 | D17: 10495 | E17: 15 | F17: 7
A18: Pierre-Emerick Aubameyang | B18: 2017-2021 | C18: 163 | D18: 12880 | E18: 92 | F18: 20
A19: Zach Awe | B19: 2020-2022 | C19: 31 | D19: 2617 | E19: 2 | F19: 0
A20: Miguel Azeez | B20: 2019-2023 | C20: 34 | D20: 2538 | E20: 4 | F20: 3
A21: Paige Bailey-Gayle | B21: 2018 | C21: 3 | D21: 102 | E21: 0 | F21: 0
A22: Brando Bailey-Joseph | B22: 2025 | C22: 11 | D22: 569 | E22: 1 | F22: 0
A23: Folarin Balogun | B23: 2017-2021 | C23: 66 | D23: 4190 | E23: 36 | F23: 8
A24: Mauro Bandeira | B24: 2021-2023 | C24: 21 | D24: 1271 | E24: 3 | F24: 1
A25: Júlio Baptista | B25: 2006 | C25: 28 | D25: 1242 | E25: 4 | F25: 2
A26: Graham Barrett | B26: 1999 | C26: 2 | D26: 10 | E26: 0 | F26: 0
A27: Kyle Bartley | B27: 2009 | C27: 1 | D27: 90 | E27: 0 | F27: 0
A28: Vince Bartram | B28: 1994 | C28: 11 | D28: 990 | E28: 0 | F28: 0
A29: Ona Batlle | B29: 2026 | C29: 2 | D29: 177 | E29: 0 | F29: 0
A30: Arsenal FC
A31: Player | B31: Years | C31: Apps | D31: Min | E31: Goals | F31: Ast
A32: Lisa Baum | B32: 2026 | C32: 2 | D32: 136 | E32: 1 | F32: 0
A33: Jennifer Beattie | B33: 2019-2023 | C33: 59 | D33: 3825 | E33: 4 | F33: 0
A34: Héctor Bellerín | B34: 2014-2021 | C34: 240 | D34: 19877 | E34: 9 | F34: 29
A35: Yossi Benayoun | B35: 2011 | C35: 22 | D35: 1100 | E35: 5 | F35: 1
A36: Nicklas Bendtner | B36: 2007-2013 | C36: 136 | D36: 6004 | E36: 32 | F36: 13
A37: Ismaël Bennacer | B37: 2015-2016 | C37: 13 | D37: 1065 | E37: 0 | F37: 1
A38: David Bentley | B38: 2003 | C38: 1 | D38: 61 | E38: 0 | F38: 0
A39: Dennis Bergkamp | B39: 1995-2005 | C39: 363 | D39: 25364 | E39: 98 | F39: 100
A40: Krystian Bielik | B40: 2015-2018 | C40: 15 | D40: 1201 | E40: 1 | F40: 0
A41: Mika Biereth | B41: 2021 | C41: 21 | D41: 1772 | E41: 10 | F41: 4
A42: Amaury Bischoff | B42: 2008 | C42: 1 | D42: 27 | E42: 0 | F42: 0
A43: Michael Black | B43: 1998 | C43: 1 | D43: 12 | E43: 0
A44: Tommy Black | B44: 1999 | C44: 1 | D44: 5 | E44: 0 | F44: 0
A45: Stina Blackstenius | B45: 2021-2026 | C45: 126 | D45: 6335 | E45: 44 | F45: 14
A46: Luís Boa Morte | B46: 1997-1999 | C46: 29 | D46: 956 | E46: 2 | F46: 0
A47: Marc Bola | B47: 2016 | C47: 6 | D47: 523 | E47: 0 | F47: 0
A48: Tolaji Bola | B48: 2016-2020 | C48: 49 | D48: 3948 | E48: 0 | F48: 6
A49: Anneke Borbe | B49: 2025-2026 | C49: 11 | D49: 990 | E49: 0 | F49: 0
A50: Steve Bould | B50: 1991-1998 | C50: 183 | D50: 15284 | E50: 2 | F50: 6
A51: Simone Boye Sørensen | B51: 2021 | C51: 7 | D51: 262 | E51: 0 | F51: 0
A52: Giovanni van Bronckhorst | B52: 2001-2002 | C52: 52 | D52: 3004 | E52: 2 | F52: 6
A53: Robbie Burton | B53: 2017-2019 | C53: 26 | D53: 2033 | E53: 5 | F53: 2
A54: Nathan Butler-Oyedeji | B54: 2020-2024 | C54: 53 | D54: 3236 | E54: 14 | F54: 9
A55: Fabián Caballero | B55: 1998 | C55: 1 | D55: 16 | E55: 0 | F55: 0
A56: Riccardo Calafiori | B56: 2024-2026 | C56: 70 | D56: 4136 | E56: 5 | F56: 7
A57: Mariona Caldentey | B57: 2024-2026 | C57: 68 | D57: 5525 | E57: 22 | F57: 11
A58: Joel Campbell | B58: 2014-2015 | C58: 39 | D58: 1915 | E58: 4 | F58: 5
A59: Kevin Campbell | B59: 1991-1994 | C59: 101 | D59: 7818 | E59: 23 | F59: 12
A60: Sol Campbell | B60: 2001-2009 | C60: 187 | D60: 16435 | E60: 10 | F60: 5
A61: Arsenal FC
A62: Player | B62: Years | C62: Apps | D62: Min | E62: Goals | F62: Ast
A63: Danielle Carter | B63: 2017-2018 | C63: 30 | D63: 1643 | E63: 6 | F63: 4
A64: Jimmy Carter | B64: 1992-1994 | C64: 19 | D64: 1158 | E64: 2 | F64: 0
A65: Steph Catley | B65: 2019-2026 | C65: 134 | D65: 9809 | E65: 4 | F65: 15
A66: Santi Cazorla | B66: 2012-2016 | C66: 164 | D66: 13557 | E66: 25 | F66: 41
A67: Dani Ceballos | B67: 2019-2020 | C67: 77 | D67: 4741 | E67: 2 | F67: 5
A68: Marouane Chamakh | B68: 2010-2012 | C68: 51 | D68: 2613 | E68: 11 | F68: 5
A69: Calum Chambers | B69: 2014-2021 | C69: 123 | D69: 8334 | E69: 6 | F69: 8
A70: Park Chu-young | B70: 2011 | C70: 3 | D70: 76 | E70: 0 | F70: 0
A71: Adrian Clarke | B71: 1994-1995 | C71: 7 | D71: 375 | E71: 0 | F71: 0
A72: Brayden Clarke | B72: 2024-2026 | C72: 27 | D72: 1801 | E72: 0 | F72: 0
A73: Gaël Clichy | B73: 2003-2010 | C73: 228 | D73: 18668 | E73: 1 | F73: 10
A74: Laia Codina | B74: 2023-2025 | C74: 38 | D74: 2006 | E74: 1 | F74: 1
A75: Ashley Cole | B75: 1999-2005 | C75: 201 | D75: 16916 | E75: 9 | F75: 16
A76: Shannon Cooke | B76: 2017 | C76: 2 | D76: 18 | E76: 0 | F76: 0
A77: Kyra Cooney-Cross | B77: 2023-2026 | C77: 53 | D77: 2526 | E77: 0 | F77: 5
A78: Louie Copley | B78: 2023-2025 | C78: 11 | D78: 850 | E78: 1 | F78: 0
A79: Francis Coquelin | B79: 2011-2017 | C79: 147 | D79: 8936 | E79: 0 | F79: 2
A80: Ben Cottrell | B80: 2018-2022 | C80: 44 | D80: 3446 | E80: 9 | F80: 3
A81: Amario Cozier-Duberry | B81: 2021-2023 | C81: 42 | D81: 3363 | E81: 14 | F81: 9
A82: Thomas Cruise | B82: 2009 | C82: 1 | D82: 90 | E82: 0 | F82: 0
A83: Pascal Cygan | B83: 2002-2005 | C83: 83 | D83: 6139 | E83: 3 | F83: 0
A84: Cătălin Cîrjan | B84: 2020-2022 | C84: 30 | D84: 1793 | E84: 3 | F84: 2
A85: Sabrina D'Angelo | B85: 2022-2023 | C85: 8 | D85: 720 | E85: 0 | F85: 0
A86: Tomas Danilevičius | B86: 2000 | C86: 2 | D86: 37 | E86: 0 | F86: 0
A87: Josh Dasilva | B87: 2016-2017 | C87: 30 | D87: 2024 | E87: 1 | F87: 5
A88: Paul Davis | B88: 1991-1994 | C88: 35 | D88: 2807 | E88: 1 | F88: 1
A89: Mathieu Debuchy | B89: 2014-2017 | C89: 31 | D89: 2471 | E89: 4 | F89: 1
A90: Arsenal FC
A91: Player | B91: Years | C91: Apps | D91: Min | E91: Goals | F91: Ast
A92: Anouk Denton | B92: 2020 | C92: 1 | D92: 1 | E92: 0 | F92: 0
A93: Denílson | B93: 2006-2010 | C93: 120 | D93: 8118 | E93: 8 | F93: 10
A94: Abou Diaby | B94: 2005-2014 | C94: 151 | D94: 9601 | E94: 18 | F94: 12
A95: Lassana Diarra | B95: 2007 | C95: 10 | D95: 482 | E95: 0 | F95: 0
A96: Kaba Diawara | B96: 1998 | C96: 12 | D96: 313 | E96: 0 | F96: 0
A97: Paul Dickov | B97: 1992-1996 | C97: 21 | D97: 881 | E97: 3 | F97: 2
A98: Jaden Dixon | B98: 2025-2026 | C98: 8 | D98: 342 | E98: 0 | F98: 0
A99: Lee Dixon | B99: 1991-2001 | C99: 343 | D99: 29186 | E99: 12 | F99: 19
A100: Johan Djourou | B100: 2005-2011 | C100: 105 | D100: 7776 | E100: 1 | F100: 1
...

Sheet Accrington Stanley
A1: Player | B1: Years | C1: Apps | D1: Min | E1: Goals | F1: Ast
A2: Korede Adedoyin | B2: 2021-2023 | C2: 52 | D2: 2422 | E2: 7 | F2: 2
A3: Leslie Adekoya | B3: 2021-2023 | C3: 16 | D3: 320 | E3: 1 | F3: 0
A4: James Alabi | B4: 2014 | C4: 3 | D4: 178 | E4: 0 | F4: 0
A5: Tom Aldred | B5: 2012-2014 | C5: 89 | D5: 8000 | E5: 4 | F5: 1
A6: Ajibola Alese | B6: 2019 | C6: 11 | D6: 726 | E6: 0 | F6: 0
A7: Sonny Aljofree | B7: 2024 | C7: 27 | D7: 2338 | E7: 3 | F7: 0
A8: Thomas Allan | B8: 2020 | C8: 6 | D8: 170 | E8: 0 | F8: 0
A9: Mauro Almeida | B9: 2006 | C9: 5 | D9: 390 | E9: 0 | F9: 0
A10: Yeboah Amankwah | B10: 2021 | C10: 25 | D10: 1862 | E10: 0 | F10: 0
A11: Pádraig Amond | B11: 2011-2012 | C11: 78 | D11: 5267 | E11: 16 | F11: 7
A12: Nick Anderton | B12: 2018 | C12: 22 | D12: 1809 | E12: 0 | F12: 0
A13: Josh Andrews | B13: 2023 | C13: 22 | D13: 1739 | E13: 6 | F13: 1
A14: Godwin Antwi | B14: 2006 | C14: 9 | D14: 774 | E14: 0 | F14: 1
A15: Luke Armstrong | B15: 2018 | C15: 16 | D15: 813 | E15: 3 | F15: 0
A16: Kenny Arthur | B16: 2007-2008 | C16: 66 | D16: 5876 | E16: 0 | F16: 0
A17: Bernard Ashley-Seal | B17: 2019 | C17: 5 | D17: 256 | E17: 0 | F17: 0
A18: Ryan Astley | B18: 2022 | C18: 27 | D18: 2369 | E18: 3 | F18: 0
A19: Rob Atkinson | B19: 2012-2014 | C19: 76 | D19: 6337 | E19: 4 | F19: 0
A20: Zach Awe | B20: 2024 | C20: 25 | D20: 2280 | E20: 1 | F20: 0
A21: Rikki Bains | B21: 2006 | C21: 3 | D21: 249 | E21: 0 | F21: 0
A22: Courtney Baker-Richardson | B22: 2019 | C22: 3 | D22: 182 | E22: 0 | F22: 1
A23: Ben Barclay | B23: 2019-2020 | C23: 36 | D23: 2798 | E23: 1 | F23: 1
A24: Daniel Barlaser | B24: 2018 | C24: 43 | D24: 3404 | E24: 2 | F24: 0
A25: Charlie Barnett | B25: 2010-2012 | C25: 96 | D25: 5672 | E25: 3 | F25: 10
A26: Anthony Barry | B26: 2014-2015 | C26: 23 | D26: 1141 | E26: 0 | F26: 0
A27: Jonathan Bateson | B27: 2010 | C27: 12 | D27: 1063 | E27: 0 | F27: 0
A28: Jake Batty | B28: 2024 | C28: 26 | D28: 1904 | E28: 0 | F28: 1
A29: Nathan Baxter | B29: 2020 | C29: 17 | D29: 1476 | E29: 0 | F29: 1
A30: James Beattie | B30: 2012 | C30: 25 | D30: 1565 | E30: 6 | F30: 3
A31: Omar Beckles | B31: 2016-2017 | C31: 50 | D31: 4437 | E31: 4 | F31: 3
A32: Cameron Belford | B32: 2012 | C32: 5 | D32: 450 | E32: 0 | F32: 0
A33: Jay Bell | B33: 2007-2008 | C33: 8 | D33: 645 | E33: 0 | F33: 0
A34: Tom Bender | B34: 2011 | C34: 2 | D34: 46 | E34: 0 | F34: 0
A35: Marcus Bettinelli | B35: 2013 | C35: 39 | D35: 3510 | E35: 0 | F35: 0
A36: Jake Bickerstaff | B36: 2023 | C36: 10 | D36: 559 | E36: 1 | F36: 0
A37: Colby Bishop | B37: 2019-2021 | C37: 115 | D37: 9630 | E37: 34 | F37: 10
A38: Adam Black | B38: 2009 | C38: 1 | D38: 2 | E38: 0 | F38: 0
A39: Simon Bloch Jorgensen | B39: 2017 | C39: 1 | D39: 90 | E39: 0 | F39: 0
A40: Gregg Blundell | B40: 2008 | C40: 2 | D40: 155 | E40: 0 | F40: 0
A41: Romuald Boco | B41: 2006-2016 | C41: 131 | D41: 8828 | E41: 22 | F41: 13
A42: Rory Boulding | B42: 2010 | C42: 15 | D42: 546 | E42: 2 | F42: 0
A43: Dean Bouzanis | B43: 2009 | C43: 14 | D43: 1165 | E43: 0 | F43: 0
A44: George Bowerman | B44: 2013-2014 | C44: 17 | D44: 888 | E44: 3 | F44: 2
A45: Graham Branch | B45: 2007 | C45: 22 | D45: 1683 | E45: 0 | F45: 0
A46: Charlie Brown | B46: 2024-2026 | C46: 44 | D46: 1875 | E46: 0 | F46: 3
A47: David Brown | B47: 2006-2007 | C47: 32 | D47: 1606 | E47: 5 | F47: 2
A48: Scott Brown | B48: 2015-2018 | C48: 118 | D48: 8011 | E48: 4 | F48: 2
A49: Gerardo Bruna | B49: 2014-2015 | C49: 10 | D49: 545 | E49: 0 | F49: 1
A50: Jack Buckley | B50: 2020 | C50: 0
A51: Cameron Burgess | B51: 2020-2021 | C51: 48 | D51: 4224 | E51: 4 | F51: 3
A52: Josef Bursik | B52: 2019 | C52: 16 | D52: 1440 | E52: 0 | F52: 0
A53: Alan Burton | B53: 2010-2011 | C53: 2 | D53: 112 | E53: 0 | F53: 0
A54: Matt Butcher | B54: 2020-2021 | C54: 79 | D54: 6238 | E54: 6 | F54: 7
A55: Nathan Butler-Oyedeji | B55: 2022 | C55: 11 | D55: 487 | E55: 0 | F55: 0
A56: Adam Buxton | B56: 2013-2015 | C56: 58 | D56: 4320 | E56: 2 | F56: 1
A57: Joel Byrom | B57: 2006 | C57: 1 | D57: 1 | E57: 0 | F57: 0
A58: Paul Carden | B58: 2007 | C58: 4 | D58: 343 | E58: 0 | F58: 0
A59: Matthew Carson | B59: 2021 | C59: 0
A60: Wilson Carvalho | B60: 2019 | C60: 10 | D60: 141 | E60: 0 | F60: 1
A61: Marcus Carver | B61: 2011-2015 | C61: 42 | D61: 1312 | E61: 2 | F61: 1
A62: Ryan Cassidy | B62: 2020 | C62: 13 | D62: 560 | E62: 2 | F62: 1
A63: Charlie Caton | B63: 2024-2026 | C63: 44 | D63: 2007 | E63: 9 | F63: 1
A64: James Caton | B64: 2013 | C64: 2 | D64: 80 | E64: 0 | F64: 0
A65: Peter Cavanagh | B65: 2006-2008 | C65: 74 | D65: 6498 | E65: 6 | F65: 5
A66: Aaron Chapman | B66: 2014-2017 | C66: 69 | D66: 6195 | E66: 0 | F66: 0
A67: Dion Charles | B67: 2019-2021 | C67: 86 | D67: 6889 | E67: 28 | F67: 7
A68: Luke Charman | B68: 2018 | C68: 1 | D68: 89 | E68: 0 | F68: 0
A69: Kieran Charnock | B69: 2008 | C69: 34 | D69: 3015 | E69: 0 | F69: 0
A70: Aidan Chippendale | B70: 2012 | C70: 6 | D70: 185 | E70: 0 | F70: 1
A71: Alex Cisak | B71: 2010 | C71: 21 | D71: 1890 | E71: 0 | F71: 0
A72: Sean Clare | B72: 2016 | C72: 9 | D72: 456 | E72: 1 | F72: 0
A73: Jordan Clark | B73: 2016-2019 | C73: 178 | D73: 14993 | E73: 23 | F73: 26
A74: Luke Clark | B74: 2012-2013 | C74: 7 | D74: 241 | E74: 0 | F74: 0
A75: Mitchell Clark | B75: 2021-2022 | C75: 68 | D75: 5819 | E75: 1 | F75: 6
A76: Jamie Clarke | B76: 2008 | C76: 15 | D76: 1003 | E76: 5 | F76: 0
A77: Danny Coid | B77: 2011 | C77: 21 | D77: 1350 | E77: 1 | F77: 0
A78: Séamus Conneely | B78: 2014-2026 | C78: 399 | D78: 30357 | E78: 15 | F78: 13
A79: Dara Costelloe | B79: 2024 | C79: 20 | D79: 1371 | E79: 5 | F79: 1
A80: Liam Coyle | B80: 2021-2026 | C80: 143 | D80: 10279 | E80: 2 | F80: 2
A81: Ian Craney | B81: 2006-2011 | C81: 98 | D81: 7407 | E81: 22 | F81: 20
A82: William Crellin | B82: 2024 | C82: 37 | D82: 3360 | E82: 0 | F82: 0
A83: Matt Crooks | B83: 2014-2015 | C83: 53 | D83: 4245 | E83: 8 | F83: 2
A84: Tom Dallison | B84: 2017 | C84: 4 | D84: 326 | E84: 1 | F84: 1
A85: Arron Davies | B85: 2016 | C85: 8 | D85: 474 | E85: 1 | F85: 0
A86: Scott Davies | B86: 2014 | C86: 19 | D86: 1710 | E86: 0 | F86: 0
A87: Tom Davies | B87: 2015 | C87: 35 | D87: 3138 | E87: 1 | F87: 1
A88: Andrew Dawber | B88: 2012-2014 | C88: 5 | D88: 316 | E88: 0 | F88: 0
A89: Nathan Delfouneso | B89: 2022 | C89: 5 | D89: 40 | E89: 0 | F89: 0
A90: Billy Dennehy | B90: 2007 | C90: 7 | D90: 210 | E90: 0 | F90: 0
A91: Jamie Devitt | B91: 2011 | C91: 16 | D91: 1230 | E91: 2 | F91: 0
A92: Owen Devonport | B92: 2023 | C92: 0
A93: Sadou Diallo | B93: 2019 | C93: 9 | D93: 528 | E93: 0 | F93: 0
A94: Bohan Dixon | B94: 2012 | C94: 6 | D94: 202 | E94: 0 | F94: 1
A95: Luke Dobie | B95: 2011 | C95: 4 | D95: 81 | E95: 0 | F95: 0
A96: Sean Doherty | B96: 2006 | C96: 20 | D96: 1011 | E96: 1 | F96: 3
A97: Janoi Donacien | B97: 2016-2018 | C97: 108 | D97: 9413 | E97: 1 | F97: 2
A98: Phil Doughty | B98: 2007 | C98: 3 | D98: 270 | E98: 0 | F98: 0
A99: Roscoe Dsane | B99: 2007 | C99: 22 | D99: 1537 | E99: 7 | F99: 4
A100: Adam Dugdale | B100: 2006 | C100: 2 | D100: 142 | E100: 0 | F100: 0
...

Sheet AFC Wimbledon
A1: Player | B1: Years | C1: Apps | D1: Min | E1: Goals | F1: Ast
A2: Nadjim Abdou | B2: 2017 | C2: 37 | D2: 2479 | E2: 2 | F2: 0
A3: Terry Ablade | B3: 2021 | C3: 12 | D3: 296 | E3: 0 | F3: 0
A4: Charles Ademeno | B4: 2011 | C4: 15 | D4: 541 | E4: 1 | F4: 0
A5: Dylan Adjei-Hersey | B5: 2021-2022 | C5: 3 | D5: 63 | E5: 0 | F5: 0
A6: Dan Agyei | B6: 2014 | C6: 0
A7: Toby Ajala | B7: 2012 | C7: 12 | D7: 989 | E7: 0 | F7: 2
A8: Semi Ajayi | B8: 2015 | C8: 5 | D8: 385 | E8: 0 | F8: 0
A9: Adebayo Akinfenwa | B9: 2014-2015 | C9: 89 | D9: 6135 | E9: 20 | F9: 7
A10: Cheye Alexander | B10: 2020-2021 | C10: 55 | D10: 3682 | E10: 0 | F10: 2
A11: Gary Alexander | B11: 2012 | C11: 18 | D11: 1292 | E11: 3 | F11: 2
A12: Reuben Amissah | B12: 2024 | C12: 0
A13: Jayden Antwi | B13: 2016 | C13: 1 | D13: 19 | E13: 0 | F13: 0
A14: Jayden Antwi | B14: 2016 | C14: 0
A15: Will Antwi | B15: 2012-2013 | C15: 41 | D15: 3264 | E15: 2 | F15: 0
A16: Kwesi Appiah | B16: 2013-2019 | C16: 75 | D16: 4213 | E16: 16 | F16: 5
A17: Chris Arthur | B17: 2013-2014 | C17: 27 | D17: 893 | E17: 1 | F17: 1
A18: Ossama Ashley | B18: 2018 | C18: 0
A19: Nathan Ashton | B19: 2009 | C19: 1 | D19: 81 | E19: 0 | F19: 0
A20: Ayoub Assal | B20: 2020-2022 | C20: 87 | D20: 6700 | E20: 21 | F20: 7
A21: Ade Azeez | B21: 2014-2015 | C21: 91 | D21: 2856 | E21: 13 | F21: 4
A22: Pim Balkestein | B22: 2011-2012 | C22: 30 | D22: 2441 | E22: 2 | F22: 2
A23: Jimmy Ball | B23: 2023-2024 | C23: 49 | D23: 2657 | E23: 2 | F23: 1
A24: Kofi Balmer | B24: 2023 | C24: 17 | D24: 1465 | E24: 1 | F24: 3
A25: Andy Barcham | B25: 2015-2018 | C25: 153 | D25: 11094 | E25: 16 | F25: 11
A26: Tyrone Barnett | B26: 2016 | C26: 40 | D26: 1402 | E26: 3 | F26: 1
A27: Adam Barrett | B27: 2014 | C27: 27 | D27: 2430 | E27: 1 | F27: 1
A28: Quaine Bartley | B28: 2021-2022 | C28: 9 | D28: 62 | E28: 0 | F28: 0
A29: Alex Bass | B29: 2023 | C29: 48 | D29: 4320 | E29: 0 | F29: 0
A30: Mads Bech Sørensen | B30: 2019 | C30: 9 | D30: 743 | E30: 0 | F30: 0
A31: Tom Beere | B31: 2014-2016 | C31: 32 | D31: 1213 | E31: 0 | F31: 0
A32: AFC Wimbledon
A33: Player | B33: Years | C33: Apps | D33: Min | E33: Goals | F33: Ast
A34: Alfie Bendle | B34: 2021-2022 | C34: 12 | D34: 274 | E34: 0 | F34: 0
A35: Alan Bennett | B35: 2012-2014 | C35: 69 | D35: 6009 | E35: 2 | F35: 1
A36: Dale Bennett | B36: 2012 | C36: 5 | D36: 393 | E36: 0 | F36: 0
A37: Hüseyin Biler | B37: 2019-2024 | C37: 39 | D37: 2539 | E37: 0 | F37: 2
A38: Andre Blackman | B38: 2010 | C38: 13 | D38: 1066 | E38: 0 | F38: 0
A39: Danny Blanchett | B39: 2009 | C39: 11 | D39: 990 | E39: 0 | F39: 0
A40: Nathan Broome | B40: 2021-2022 | C40: 9 | D40: 810 | E40: 0 | F40: 0
A41: Drewe Broughton | B41: 2010 | C41: 8 | D41: 293 | E41: 2 | F41: 0
A42: Lee Brown | B42: 2021-2023 | C42: 70 | D42: 5478 | E42: 0 | F42: 6
A43: Seb Brown | B43: 2009-2013 | C43: 124 | D43: 11115 | E43: 0 | F43: 0
A44: Marcus Browne | B44: 2024-2026 | C44: 58 | D44: 4005 | E44: 16 | F44: 3
A45: Omar Bugiel | B45: 2023-2025 | C45: 131 | D45: 8760 | E45: 26 | F45: 13
A46: Dannie Bulman | B46: 2014-2016 | C46: 132 | D46: 10684 | E46: 4 | F46: 3
A47: Tyler Burey | B47: 2018 | C47: 3 | D47: 73 | E47: 0 | F47: 0
A48: Josef Bursik | B48: 2016-2026 | C48: 2 | D48: 180 | E48: 0 | F48: 0
A49: Chris Bush | B49: 2010-2011 | C49: 35 | D49: 2556 | E49: 0 | F49: 0
A50: Neşet Can Bellikli | B50: 2017 | C50: 0
A51: Darius Charles | B51: 2015-2021 | C51: 80 | D51: 6610 | E51: 2 | F51: 3
A52: Ethan Chislett | B52: 2020-2022 | C52: 110 | D52: 6139 | E52: 15 | F52: 5
A53: Justin Clarke | B53: 2023 | C53: 0
A54: Ryan Clarke | B54: 2016 | C54: 8 | D54: 720 | E54: 0 | F54: 0
A55: Michael Collins | B55: 2013 | C55: 9 | D55: 786 | E55: 0 | F55: 0
A56: David Connolly | B56: 2014 | C56: 8 | D56: 220 | E56: 1 | F56: 0
A57: Dylan Connolly | B57: 2018-2019 | C57: 18 | D57: 619 | E57: 0 | F57: 1
A58: Jay Conroy | B58: 2009 | C58: 31 | D58: 2014 | E58: 0 | F58: 2
A59: Aaron Cosgrave | B59: 2021-2022 | C59: 9 | D59: 196 | E59: 1 | F59: 0
A60: Sam Cosgrove | B60: 2021 | C60: 15 | D60: 1073 | E60: 1 | F60: 0
A61: Matthew Cox | B61: 2020 | C61: 0
A62: Dániel Csóka | B62: 2020-2021 | C62: 43 | D62: 3489 | E62: 1 | F62: 0
A63: Luis Cumbers | B63: 2009 | C63: 4 | D63: 203 | E63: 1 | F63: 0
A64: AFC Wimbledon
A65: Player | B65: Years | C65: Apps | D65: Min | E65: Goals | F65: Ast
A66: Warren Cummings | B66: 2012 | C66: 9 | D66: 558 | E66: 0 | F66: 0
A67: Jack Currie | B67: 2020-2023 | C67: 87 | D67: 7070 | E67: 2 | F67: 2
A68: Ronan Curtis | B68: 2023 | C68: 16 | D68: 956 | E68: 5 | F68: 2
A69: Jesse Darko | B69: 2012 | C69: 12 | D69: 417 | E69: 0 | F69: 1
A70: Josh Davison | B70: 2022-2023 | C70: 82 | D70: 4780 | E70: 14 | F70: 5
A71: Joe Day | B71: 2019 | C71: 9 | D71: 810 | E71: 0 | F71: 0
A72: Ryan Delaney | B72: 2019 | C72: 15 | D72: 1232 | E72: 1 | F72: 1
A73: Brennan Dickenson | B73: 2012 | C73: 7 | D73: 357 | E73: 2 | F73: 0
A74: Kieran Djilali | B74: 2011-2012 | C74: 17 | D74: 497 | E74: 1 | F74: 0
A75: George Dobson | B75: 2020 | C75: 24 | D75: 1880 | E75: 1 | F75: 1
A76: Derek Duncan | B76: 2009 | C76: 22 | D76: 1177 | E76: 0 | F76: 1
A77: Alfie Egan | B77: 2016-2018 | C77: 13 | D77: 374 | E77: 0 | F77: 0
A78: Nathan Elder | B78: 2009 | C78: 18 | D78: 1092 | E78: 3 | F78: 1
A79: Tom Elliott | B79: 2015-2016 | C79: 85 | D79: 5077 | E79: 20 | F79: 5
A80: Jason Euell | B80: 2011 | C80: 9 | D80: 567 | E80: 0 | F80: 1
A81: Jim Fenlon | B81: 2012-2013 | C81: 36 | D81: 2680 | E81: 1 | F81: 2
A82: David Fisher | B82: 2022 | C82: 6 | D82: 152 | E82: 0 | F82: 0
A83: David Fitzpatrick | B83: 2014-2016 | C83: 13 | D83: 472 | E83: 1 | F83: 0
A84: Michael Folivi | B84: 2018-2019 | C84: 22 | D84: 1333 | E84: 2 | F84: 1
A85: Harry Forrester | B85: 2017 | C85: 39 | D85: 2167 | E85: 3 | F85: 4
A86: Marcus Forss | B86: 2019 | C86: 18 | D86: 1337 | E86: 11 | F86: 1
A87: Max Foulkes | B87: 2023 | C87: 0
A88: Osman Foyo | B88: 2024-2025 | C88: 11 | D88: 206 | E88: 0 | F88: 1
A89: Andy Frampton | B89: 2013-2014 | C89: 36 | D89: 2978 | E89: 5 | F89: 1
A90: George Francomb | B90: 2012-2017 | C90: 208 | D90: 15613 | E90: 11 | F90: 26
A91: Fraser Franks | B91: 2010-2011 | C91: 28 | D91: 1717 | E91: 2 | F91: 1
A92: Kwaku Frimpong | B92: 2022 | C92: 1 | D92: 1 | E92: 0 | F92: 0
A93: Barry Fuller | B93: 2013-2017 | C93: 222 | D93: 19720 | E93: 1 | F93: 14
A94: James Furlong | B94: 2024 | C94: 26 | D94: 948 | E94: 0 | F94: 1
A95: Dan Gallagher | B95: 2014-2016 | C95: 1 | D95: 1 | E95: 0 | F95: 0
A96: AFC Wimbledon
A97: Player | B97: Years | C97: Apps | D97: Min | E97: Goals | F97: Ast
A98: Luke Garrard | B98: 2009 | C98: 6 | D98: 443 | E98: 0 | F98: 0
A99: Tyler Garratt | B99: 2018 | C99: 9 | D99: 319 | E99: 0 | F99: 1
A100: Elliott Godfrey | B100: 2009 | C100: 18 | D100: 780 | E100: 1 | F100: 0
...

Sheet Aston Villa
A1: Player | B1: Years | C1: Apps | D1: Min | E1: Goals | F1: Ast
A2: Khalid Abdo | B2: 2017 | C2: 6 | D2: 303 | E2: 1 | F2: 0
A3: Tammy Abraham | B3: 2018-2026 | C3: 58 | D3: 3684 | E3: 28 | F3: 4
A4: Albert Adomah | B4: 2016-2018 | C4: 119 | D4: 7751 | E4: 22 | F4: 18
A5: Didier Agathe | B5: 2006 | C5: 5 | D5: 166 | E5: 0 | F5: 0
A6: Gabriel Agbonlahor | B6: 2005-2017 | C6: 352 | D6: 27495 | E6: 76 | F6: 36
A7: Karim El Ahmadi | B7: 2012-2014 | C7: 51 | D7: 3353 | E7: 3 | F7: 1
A8: Marc Albrighton | B8: 2008-2013 | C8: 87 | D8: 4850 | E8: 7 | F8: 10
A9: Asmita Ale | B9: 2020 | C9: 18 | D9: 1457 | E9: 0 | F9: 1
A10: Marcus Allbäck | B10: 2002-2003 | C10: 34 | D10: 1719 | E10: 6 | F10: 1
A11: Remi Allen | B11: 2021-2022 | C11: 22 | D11: 1862 | E11: 3 | F11: 0
A12: Alysson | B12: 2025-2026 | C12: 9 | D12: 180 | E12: 1 | F12: 0
A13: Jordan Amavi | B13: 2015-2016 | C13: 48 | D13: 3670 | E13: 0 | F13: 4
A14: Cameron Archer | B14: 2018-2023 | C14: 42 | D14: 2539 | E14: 14 | F14: 4
A15: Chloe Arthur | B15: 2020-2021 | C15: 34 | D15: 2299 | E15: 1 | F15: 0
A16: Anita Asante | B16: 2020-2021 | C16: 40 | D16: 3548 | E16: 2 | F16: 0
A17: Aimuamwonsa Asemota | B17: 2025-2026 | C17: 7 | D17: 630 | E17: 0 | F17: 0
A18: Marco Asensio | B18: 2024 | C18: 21 | D18: 1118 | E18: 8 | F18: 1
A19: Dalian Atkinson | B19: 1992-1994 | C19: 80 | D19: 6561 | E19: 24 | F19: 11
A20: Ludwig Augustinsson | B20: 2022 | C20: 5 | D20: 236 | E20: 0 | F20: 0
A21: Jordan Ayew | B21: 2015-2016 | C21: 58 | D21: 4309 | E21: 10 | F21: 5
A22: Leandro Bacuna | B22: 2013-2017 | C22: 128 | D22: 8999 | E22: 8 | F22: 7
A23: Jill Baijings | B23: 2024-2025 | C23: 15 | D23: 953 | E23: 0 | F23: 1
A24: Leon Bailey | B24: 2021-2025 | C24: 161 | D24: 8503 | E24: 21 | F24: 24
A25: Nathan Baker | B25: 2010-2016 | C25: 116 | D25: 8959 | E25: 1 | F25: 0
A26: Eirik Bakke | B26: 2005 | C26: 14 | D26: 685 | E26: 0 | F26: 0
A27: Boško Balaban | B27: 2001 | C27: 6 | D27: 134 | E27: 0 | F27: 0
A28: Barry Bannan | B28: 2008-2012 | C28: 66 | D28: 3646 | E28: 1 | F28: 4
A29: Phil Bardsley | B29: 2006 | C29: 13 | D29: 1147 | E29: 0 | F29: 1
A30: Ross Barkley | B30: 2020-2026 | C30: 82 | D30: 3637 | E30: 10 | F30: 3
A31: Milan Baroš | B31: 2005-2006 | C31: 42 | D31: 2907 | E31: 9 | F31: 4
A32: Aston Villa FC
A33: Player | B33: Years | C33: Apps | D33: Min | E33: Goals | F33: Ast
A34: Earl Barrett | B34: 1992-1994 | C34: 113 | D34: 10130 | E34: 1 | F34: 3
A35: Gareth Barry | B35: 1997-2008 | C35: 374 | D35: 31573 | E35: 43 | F35: 40
A36: Louie Barry | B36: 2019-2021 | C36: 22 | D36: 1758 | E36: 16 | F36: 1
A37: Borja Bastón | B37: 2019 | C37: 2 | D37: 18 | E37: 0 | F37: 0
A38: Jan Bednarek | B38: 2022 | C38: 4 | D38: 190 | E38: 0 | F38: 0
A39: Stefan Beinlich | B39: 1992-1993 | C39: 14 | D39: 644 | E39: 1 | F39: 1
A40: Joe Bennett | B40: 2012-2015 | C40: 31 | D40: 2121 | E40: 1 | F40: 2
A41: Darren Bent | B41: 2010-2014 | C41: 62 | D41: 4244 | E41: 21 | F41: 2
A42: Christian Benteke | B42: 2012-2014 | C42: 94 | D42: 7773 | E42: 44 | F42: 9
A43: Patrik Berger | B43: 2005-2007 | C43: 29 | D43: 1108 | E43: 2 | F43: 4
A44: Mathieu Berson | B44: 2004 | C44: 11 | D44: 630 | E44: 0 | F44: 0
A45: Ryan Bertrand | B45: 2013 | C45: 16 | D45: 1386 | E45: 0 | F45: 0
A46: Jon Bewers | B46: 1999 | C46: 1 | D46: 2 | E46: 0 | F46: 0
A47: Habib Beye | B47: 2009-2010 | C47: 9 | D47: 624 | E47: 0 | F47: 0
A48: Paul Birch | B48: 1990 | C48: 2 | D48: 180 | E48: 0
A49: Marco Bizot | B49: 2025-2026 | C49: 16 | D49: 1349 | E49: 0 | F49: 0
A50: Birkir Bjarnason | B50: 2016-2018 | C50: 52 | D50: 2783 | E50: 6 | F50: 3
A51: Corey Blackett-Taylor | B51: 2015-2018 | C51: 21 | D51: 1301 | E51: 5 | F51: 3
A52: Mark Blake | B52: 1990-1992 | C52: 1 | D52: 12 | E52: 0 | F52: 0
A53: Laura Blindkilde | B53: 2021-2023 | C53: 41 | D53: 2632 | E53: 0 | F53: 1
A54: Missy Bo Kearns | B54: 2024-2025 | C54: 26 | D54: 1748 | E54: 0 | F54: 3
A55: George Boateng | B55: 1999-2001 | C55: 105 | D55: 8516 | E55: 4 | F55: 1
A56: Chris Boden | B56: 1994 | C56: 1 | D56: 9 | E56: 0 | F56: 0
A57: Lamare Bogarde | B57: 2020-2026 | C57: 100 | D57: 6158 | E57: 0 | F57: 1
A58: Yannick Bolasie | B58: 2018 | C58: 21 | D58: 958 | E58: 2 | F58: 4
A59: Oscar Borg | B59: 2017 | C59: 14 | D59: 1109 | E59: 0 | F59: 2
A60: Aidan Borland | B60: 2023-2026 | C60: 46 | D60: 3636 | E60: 1 | F60: 4
A61: Mark Bosnich | B61: 1992-1998 | C61: 189 | D61: 16903 | E61: 0 | F61: 1
A62: Wilfred Bouma | B62: 2005-2007 | C62: 83 | D62: 6967 | E62: 1 | F62: 2
A63: Jordan Bowery | B63: 2012-2013 | C63: 19 | D63: 541 | E63: 0 | F63: 1
A64: Aston Villa FC
A65: Player | B65: Years | C65: Apps | D65: Min | E65: Goals | F65: Ast
A66: Chantelle Boye-Hlorkah | B66: 2021-2022 | C66: 22 | D66: 1057 | E66: 0 | F66: 0
A67: Michael Bradley | B67: 2010 | C67: 3 | D67: 31 | E67: 0 | F67: 0
A68: James Bree | B68: 2016-2018 | C68: 36 | D68: 2730 | E68: 2 | F68: 1
A69: Matthias Breitkreutz | B69: 1992-1993 | C69: 5 | D69: 275 | E69: 0 | F69: 0
A70: Mungo Bridge | B70: 2018-2021 | C70: 33 | D70: 2570 | E70: 0 | F70: 0
A71: Benjamin Broggio | B71: 2023-2026 | C71: 28 | D71: 1608 | E71: 6 | F71: 3
A72: Paul Browne | B72: 1995 | C72: 2 | D72: 180 | E72: 0 | F72: 0
A73: Emi Buendía | B73: 2021-2026 | C73: 157 | D73: 8296 | E73: 22 | F73: 18
A74: Mark Bunn | B74: 2015-2018 | C74: 21 | D74: 1875 | E74: 0 | F74: 0
A75: Bradley Burrowes | B75: 2024-2026 | C75: 24 | D75: 1790 | E75: 14 | F75: 4
A76: Darren Byfield | B76: 1997-1998 | C76: 8 | D76: 524 | E76: 0 | F76: 0
A77: Gary Cahill | B77: 2005-2007 | C77: 28 | D77: 2367 | E77: 1 | F77: 0
A78: Colin Calderwood | B78: 1998-1999 | C78: 26 | D78: 2051 | E78: 0 | F78: 0
A79: Benito Carbone | B79: 1999 | C79: 24 | D79: 1861 | E79: 3 | F79: 5
A80: John Carew | B80: 2006-2010 | C80: 115 | D80: 8078 | E80: 38 | F80: 9
A81: Diego Carlos | B81: 2022-2024 | C81: 56 | D81: 4033 | E81: 1 | F81: 0
A82: Franz Carr | B82: 1994-1995 | C82: 3 | D82: 106 | E82: 0 | F82: 0
A83: Theodore Carroll | B83: 2025-2026 | C83: 19 | D83: 1635 | E83: 1 | F83: 0
A84: Tom Carroll | B84: 2018 | C84: 2 | D84: 37 | E84: 0 | F84: 0
A85: Martin Carruthers | B85: 1992 | C85: 1 | D85: 1 | E85: 0 | F85: 0
A86: Samir Carruthers | B86: 2011 | C86: 3 | D86: 22 | E86: 0 | F86: 0
A87: Scott Carson | B87: 2007 | C87: 35 | D87: 3126 | E87: 0 | F87: 2
A88: Tony Cascarino | B88: 1990 | C88: 3 | D88: 237 | E88: 0
A89: Matty Cash | B89: 2020-2026 | C89: 231 | D89: 18257 | E89: 12 | F89: 15
A90: Calum Chambers | B90: 2021-2023 | C90: 35 | D90: 1694 | E90: 1 | F90: 1
A91: Gary Charles | B91: 1994-1998 | C91: 88 | D91: 6861 | E91: 4 | F91: 8
A92: Aston Villa FC
A93: Player | B93: Years | C93: Apps | D93: Min | E93: Goals | F93: Ast
A94: James Chester | B94: 2016-2019 | C94: 126 | D94: 11239 | E94: 12 | F94: 1
A95: Benjamin Chrisene | B95: 2020-2023 | C95: 20 | D95: 1507 | E95: 0 | F95: 1
A96: Caleb Chukwuemeka | B96: 2021-2022 | C96: 10 | D96: 708 | E96: 7 | F96: 6
A97: Carney Chukwuemeka | B97: 2019-2021 | C97: 42 | D97: 2510 | E97: 3 | F97: 5
A98: Aly Cissokho | B98: 2014-2016 | C98: 58 | D98: 4917 | E98: 0 | F98: 1
A99: Ciaran Clark | B99: 2009-2015 | C99: 143 | D99: 11747 | E99: 8 | F99: 4
A100: Mitchell Clark | B100: 2017-2018 | C100: 19 | D100: 1652 | E100: 0 | F100: 0
...

Sheet Barnet
A1: Player | B1: Years | C1: Apps | D1: Min | E1: Goals | F1: Ast
A2: Ahmed Abdulla | B2: 2012-2013 | C2: 29 | D2: 1701 | E2: 3 | F2: 1
A3: Charlee Adams | B3: 2018-2019 | C3: 46 | D3: 3615 | E3: 2 | F3: 0
A4: Charlie Adams | B4: 2013 | C4: 5 | D4: 317 | E4: 0 | F4: 0
A5: Tomi Adeloye | B5: 2020 | C5: 17 | D5: 946 | E5: 3
A6: Kwame Adjeman-Pamboe | B6: 2010 | C6: 1 | D6: 1 | E6: 0 | F6: 0
A7: Albert Adomah | B7: 2007-2009 | C7: 112 | D7: 9127 | E7: 19 | F7: 15
A8: Benjamin Aghadiuno | B8: 2017 | C8: 1 | D8: 9 | E8: 0 | F8: 0
A9: Benjy Aghadiuno | B9: 2017 | C9: 1 | D9: 54 | E9: 0 | F9: 0
A10: John Akinde | B10: 2014-2017 | C10: 172 | D10: 14711 | E10: 89 | F10: 18
A11: Sam Akinde | B11: 2016 | C11: 1 | D11: 6 | E11: 0 | F11: 0
A12: Simeon Akinola | B12: 2016-2019 | C12: 98 | D12: 5545 | E12: 22 | F12: 3
A13: Jean-Louis Akpa Akpro | B13: 2016-2017 | C13: 54 | D13: 2969 | E13: 5 | F13: 4
A14: Cliff Akurang | B14: 2007-2008 | C14: 45 | D14: 2579 | E14: 10 | F14: 2
A15: Cheye Alexander | B15: 2018-2019 | C15: 84 | D15: 7333 | E15: 2 | F15: 1
A16: Iffy Allen | B16: 2012-2013 | C16: 7 | D16: 233 | E16: 1 | F16: 0
A17: Oliver Allen | B17: 2006 | C17: 14 | D17: 624 | E17: 4 | F17: 1
A18: Justin Amaluzor | B18: 2015-2017 | C18: 23 | D18: 575 | E18: 0 | F18: 0
A19: Stevland Angus | B19: 2007 | C19: 1 | D19: 70 | E19: 0 | F19: 0
A20: Louie Annesley | B20: 2022 | C20: 2 | D20: 151 | E20: 0 | F20: 0
A21: Marvin Armstrong | B21: 2022-2023 | C21: 49 | D21: 1689 | E21: 2 | F21: 0
A22: Jake Askew | B22: 2021 | C22: 5 | D22: 450 | E22: 0
A23: Taiwo Atieno | B23: 2012 | C23: 4 | D23: 122 | E23: 1 | F23: 0
A24: Aymen Azaze | B24: 2018-2022 | C24: 20 | D24: 1738 | E24: 0
A25: Nicky Bailey | B25: 2005-2015 | C25: 93 | D25: 8059 | E25: 12 | F25: 7
A26: Courtney Baker-Richardson | B26: 2020 | C26: 17 | D26: 1087 | E26: 3
A27: Jack Barham | B27: 2018-2019 | C27: 25 | D27: 1183 | E27: 3 | F27: 0
A28: George Barker | B28: 2012 | C28: 1 | D28: 82 | E28: 0 | F28: 0
A29: Sam Barratt | B29: 2023 | C29: 6 | D29: 91 | E29: 0
A30: Grant Basey | B30: 2010 | C30: 11 | D30: 946 | E30: 1 | F30: 0
A31: Cédric Baseya | B31: 2011 | C31: 2 | D31: 38 | E31: 0 | F31: 0
A32: Barnet FC
A33: Player | B33: Years | C33: Apps | D33: Min | E33: Goals | F33: Ast
A34: Damian Batt | B34: 2005 | C34: 22 | D34: 1315 | E34: 0 | F34: 0
A35: Shaun Batt | B35: 2015-2016 | C35: 30 | D35: 1056 | E35: 1 | F35: 0
A36: Sam Beard | B36: 2020-2023 | C36: 74 | D36: 5689 | E36: 1 | F36: 0
A37: Craig Beattie | B37: 2012 | C37: 5 | D37: 160 | E37: 0 | F37: 0
A38: Rob Beckwith | B38: 2007-2008 | C38: 14 | D38: 1203 | E38: 0 | F38: 0
A39: Giosue Bellagambi | B39: 2024 | C39: 1 | D39: 90 | E39: 0 | F39: 0
A40: Mohamed Bettamer | B40: 2018 | C40: 5 | D40: 311 | E40: 0 | F40: 0
A41: Jerome Binnom-Williams | B41: 2020 | C41: 21 | D41: 1834 | E41: 0 | F41: 0
A42: Adam Birchall | B42: 2006-2008 | C42: 104 | D42: 6942 | E42: 19 | F42: 9
A43: Neal Bishop | B43: 2007-2008 | C43: 83 | D43: 7223 | E43: 3 | F43: 6
A44: Tommy Black | B44: 2008 | C44: 5 | D44: 310 | E44: 0 | F44: 0
A45: Andre Blackman | B45: 2017 | C45: 19 | D45: 1135 | E45: 0 | F45: 0
A46: Mason Bloomfield | B46: 2021 | C46: 20 | D46: 1179 | E46: 3
A47: Jack Blower | B47: 2023 | C47: 0
A48: Yannick Bolasie | B48: 2008-2009 | C48: 42 | D48: 2890 | E48: 5 | F48: 2
A49: Gary Borrowdale | B49: 2011 | C49: 11 | D49: 976 | E49: 0 | F49: 0
A50: Andre Boucaud | B50: 2018-2019 | C50: 25 | D50: 1531 | E50: 0 | F50: 0
A51: Ruben Bover | B51: 2016-2017 | C51: 30 | D51: 1579 | E51: 0 | F51: 0
A52: Ben Bowditch | B52: 2005 | C52: 6 | D52: 310 | E52: 0 | F52: 0
A53: Martyn Box | B53: 2018 | C53: 2 | D53: 20 | E53: 0 | F53: 0
A54: Gary Breen | B54: 2008-2009 | C54: 47 | D54: 4230 | E54: 0 | F54: 1
A55: Matthew Briggs | B55: 2017 | C55: 1 | D55: 16 | E55: 0 | F55: 0
A56: Dean Brill | B56: 2011 | C56: 36 | D56: 3240 | E56: 0 | F56: 0
A57: Richard Brindley | B57: 2017 | C57: 18 | D57: 1538 | E57: 1 | F57: 1
A58: Jordan Brown | B58: 2012-2013 | C58: 24 | D58: 2041 | E58: 0 | F58: 1
A59: Rhys Browne | B59: 2024-2025 | C59: 43 | D59: 1782 | E59: 8 | F59: 2
A60: Mitch Brundle | B60: 2021 | C60: 22 | D60: 1980 | E60: 3
A61: Zak Brunt | B61: 2023-2025 | C61: 96 | D61: 6592 | E61: 13 | F61: 7
A62: Rob Burch | B62: 2006 | C62: 6 | D62: 540 | E62: 0 | F62: 0
A63: Ryan Burge | B63: 2008 | C63: 1 | D63: 31 | E63: 0 | F63: 0
A64: Barnet FC
A65: Player | B65: Years | C65: Apps | D65: Min | E65: Goals | F65: Ast
A66: Harry Burgoyne | B66: 2016 | C66: 2 | D66: 180 | E66: 0 | F66: 0
A67: Sagi Burton | B67: 2007 | C67: 30 | D67: 2599 | E67: 1 | F67: 1
A68: Calum Butcher | B68: 2009 | C68: 3 | D68: 270 | E68: 0 | F68: 0
A69: Mark Byrne | B69: 2010-2013 | C69: 147 | D69: 11645 | E69: 19 | F69: 22
A70: Benjamin Büchel | B70: 2016 | C70: 4 | D70: 360 | E70: 0 | F70: 0
A71: Kieron Cadogan | B71: 2013 | C71: 22 | D71: 1443 | E71: 0 | F71: 1
A72: James Callan | B72: 2020-2022 | C72: 1 | D72: 46 | E72: 0
A73: Jamal Campbell-Ryce | B73: 2016-2017 | C73: 58 | D73: 4121 | E73: 5 | F73: 8
A74: Ashley Carew | B74: 2007-2008 | C74: 43 | D74: 2597 | E74: 2 | F74: 2
A75: Roberto Casabella | B75: 2013 | C75: 11 | D75: 757 | E75: 0 | F75: 0
A76: Tom Champion | B76: 2015-2016 | C76: 56 | D76: 3855 | E76: 2 | F76: 3
A77: Harry Chapman | B77: 2024 | C77: 22 | D77: 945 | E77: 4 | F77: 2
A78: Anthony Charles | B78: 2005-2006 | C78: 57 | D78: 4668 | E78: 0 | F78: 2
A79: Ashley Charles | B79: 2018 | C79: 4 | D79: 239 | E79: 0 | F79: 0
A80: Elliott Charles | B80: 2008-2009 | C80: 8 | D80: 46 | E80: 0 | F80: 0
A81: Okem Chime | B81: 2019 | C81: 2 | D81: 20 | E81: 0 | F81: 0
A82: Josh Clarke | B82: 2015 | C82: 10 | D82: 725 | E82: 3 | F82: 0
A83: Billy Clifford | B83: 2024 | C83: 21 | D83: 637 | E83: 0 | F83: 0
A84: Conor Clifford | B84: 2014 | C84: 13 | D84: 916 | E84: 1 | F84: 1
A85: Simon Clist | B85: 2005 | C85: 14 | D85: 1123 | E85: 0 | F85: 0
A86: Charlie Clough | B86: 2016-2017 | C86: 57 | D86: 4551 | E86: 1 | F86: 2
A87: Barry Cogan | B87: 2006 | C87: 39 | D87: 2824 | E87: 3 | F87: 3
A88: Shane Cojocarel | B88: 2016 | C88: 3 | D88: 63 | E88: 0 | F88: 0
A89: Ben Coker | B89: 2023-2024 | C89: 65 | D89: 4475 | E89: 2 | F89: 6
A90: Jake Cole | B90: 2008-2010 | C90: 87 | D90: 7830 | E90: 0 | F90: 0
A91: Danny Collinge | B91: 2022-2026 | C91: 155 | D91: 13260 | E91: 17 | F91: 5
A92: Jack Connors | B92: 2020 | C92: 6 | D92: 435 | E92: 0
A93: Raven Constable | B93: 2015 | C93: 0
A94: Lee Cook | B94: 2014 | C94: 40 | D94: 2764 | E94: 8 | F94: 5
A95: Luke Coulson | B95: 2016 | C95: 11 | D95: 329 | E95: 0 | F95: 0
A96: Barnet FC
A97: Player | B97: Years | C97: Apps | D97: Min | E97: Goals | F97: Ast
A98: Shaq Coulthirst | B98: 2017-2019 | C98: 86 | D98: 5977 | E98: 27 | F98: 4
A99: Tom Coulton | B99: 2010 | C99: 1 | D99: 90 | E99: 0 | F99: 0
A100: Mark Cousins | B100: 2018 | C100: 49 | D100: 4322 | E100: 0 | F100: 0
...

Sheet Barnsley
A1: Player | B1: Years | C1: Apps | D1: Min | E1: Goals | F1: Ast
A2: Brad Abbott | B2: 2014-2015 | C2: 6 | D2: 369 | E2: 0 | F2: 0
A3: Joe Ackroyd | B3: 2021-2023 | C3: 1 | D3: 16 | E3: 0 | F3: 0
A4: Jamil Adam | B4: 2009 | C4: 2 | D4: 48 | E4: 0 | F4: 0
A5: Corey Addai | B5: 2020 | C5: 0
A6: Miles Addison | B6: 2011 | C6: 11 | D6: 756 | E6: 0 | F6: 0
A7: Victor Adeboyejo | B7: 2017-2021 | C7: 91 | D7: 3031 | E7: 8 | F7: 1
A8: Jack Aitchison | B8: 2022 | C8: 22 | D8: 1176 | E8: 3 | F8: 0
A9: Danny Alcock | B9: 2003 | C9: 1 | D9: 63 | E9: 0 | F9: 0
A10: Luke Alker | B10: 2024-2026 | C10: 9 | D10: 539 | E10: 0 | F10: 0
A11: Ben Alnwick | B11: 2012 | C11: 10 | D11: 900 | E11: 0 | F11: 0
A12: Viv Anderson | B12: 1993-1994 | C12: 20 | E12: 3
A13: Jake Andrassy | B13: 2026 | C13: 0
A14: Matty Appleby | B14: 1996-2000 | C14: 139 | D14: 1056 | E14: 7 | F14: 0
A15: Owen Archdeacon | B15: 1992-1996 | C15: 127 | E15: 12
A16: Amir Ariely | B16: 2021 | C16: 0
A17: Diego Arismendi | B17: 2010 | C17: 31 | D17: 2154 | E17: 1 | F17: 0
A18: Adam Armstrong | B18: 2016 | C18: 35 | D18: 1999 | E18: 6 | F18: 3
A19: Aaron Atkinson | B19: 2023 | C19: 0
A20: Rob Atkinson | B20: 2003-2006 | C20: 8 | D20: 555 | E20: 0 | F20: 0
A21: Kevin Austin | B21: 1999-2000 | C21: 3 | E21: 0
A22: Neil Austin | B22: 1999-2006 | C22: 148 | D22: 11764 | E22: 0 | F22: 4
A23: Paul Bagshaw | B23: 1998-1999 | C23: 1 | E23: 0
A24: James Bailey | B24: 2014 | C24: 28 | D24: 1931 | E24: 0 | F24: 0
A25: Scott Banks | B25: 2025 | C25: 22 | D25: 1229 | E25: 3 | F25: 4
A26: Chris Barker | B26: 1998-2001 | C26: 113 | D26: 3871 | E26: 3 | F26: 2
A27: Darren Barnard | B27: 1997-2001 | C27: 170 | D27: 5889 | E27: 28 | F27: 10
A28: Harvey Barnes | B28: 2017 | C28: 25 | D28: 1558 | E28: 5 | F28: 2
A29: Connor Barratt | B29: 2025 | C29: 5 | D29: 237 | E29: 0 | F29: 0
A30: Connor Barrett | B30: 2024 | C30: 5 | D30: 179 | E30: 0 | F30: 0
A31: Carl Barrowclough | B31: 2000-2002 | C31: 12 | D31: 109 | E31: 0 | F31: 0
A32: Barnsley FC
A33: Player | B33: Years | C33: Apps | D33: Min | E33: Goals | F33: Ast
A34: Amine Bassi | B34: 2021 | C34: 16 | D34: 1289 | E34: 2 | F34: 5
A35: Gavin Bassinder | B35: 1998-1999 | C35: 0 | E35: 0
A36: Duane Beckett | B36: 1996 | C36: 0 | E36: 0
A37: Luke Beckett | B37: 1995-1996 | C37: 0 | E37: 0
A38: Tony Bedeau | B38: 2001 | C38: 3 | D38: 54 | E38: 0 | F38: 0
A39: Robert Bengtsson Bärkroth | B39: 1999 | C39: 0 | E39: 0
A40: Steven Bennett | B40: 2010 | C40: 4 | D40: 55 | E40: 0 | F40: 0
A41: Troy Bennett | B41: 1992-1996 | C41: 2 | E41: 0
A42: Daniel Benson | B42: 2021 | C42: 0
A43: Josh Benson | B43: 2021-2024 | C43: 87 | D43: 3857 | E43: 6 | F43: 6
A44: Marlon Beresford | B44: 2003 | C44: 14 | D44: 1190 | E44: 0 | F44: 0
A45: Curtis Bernard | B45: 1998-2000 | C45: 0 | E45: 0
A46: Luke Berry | B46: 2014 | C46: 35 | D46: 2606 | E46: 1 | F46: 2
A47: Leo Bertos | B47: 2000-2002 | C47: 12 | D47: 426 | E47: 1 | F47: 0
A48: Kevin Betsy | B48: 2001-2003 | C48: 94 | D48: 7836 | E48: 16 | F48: 11
A49: Bartosz Białkowski | B49: 2009 | C49: 2 | D49: 180 | E49: 0 | F49: 0
A50: Wayne Biggins | B50: 1992-1993 | C50: 47 | E50: 16
A51: Gary Birch | B51: 2003 | C51: 8 | D51: 715 | E51: 2 | F51: 0
A52: Jared Bird | B52: 2016-2018 | C52: 4 | D52: 130 | E52: 0 | F52: 0
A53: Charlie Bishop | B53: 1992-1996 | C53: 102 | E53: 1
A54: Clayton Blackmore | B54: 1998-1999 | C54: 7 | E54: 0
A55: Jonathan Bland | B55: 2023-2026 | C55: 67 | D55: 4517 | E55: 0 | F55: 3
A56: Nana Boakye-Yiadom | B56: 2014 | C56: 4 | D56: 28 | E56: 0 | F56: 0
A57: Simon Bochenski | B57: 1995-1996 | C57: 1 | E57: 0
A58: Chris Boden | B58: 1993 | C58: 4 | E58: 0
A59: Daniel Bogdanović | B59: 2008-2009 | C59: 45 | D59: 2673 | E59: 16 | F59: 3
A60: Jovo Bosančić | B60: 1996-1997 | C60: 42 | D60: 1192 | E60: 3 | F60: 0
A61: Michael Boulding | B61: 2003-2004 | C61: 35 | D61: 2433 | E61: 10 | F61: 0
A62: Tom Bradshaw | B62: 2016-2025 | C62: 112 | D62: 6873 | E62: 22 | F62: 4
A63: James Bree | B63: 2014-2016 | C63: 54 | D63: 4135 | E63: 0 | F63: 4
A64: Barnsley FC
A65: Player | B65: Years | C65: Apps | D65: Min | E65: Goals | F65: Ast
A66: David Bremang | B66: 2021 | C66: 2 | D66: 39 | E66: 0 | F66: 0
A67: Callum Brittain | B67: 2020-2021 | C67: 80 | D67: 6980 | E67: 0 | F67: 7
A68: David Brooke | B68: 1993-1996 | C68: 0 | E68: 0
A69: Jacob Brown | B69: 2016-2020 | C69: 78 | D69: 5701 | E69: 12 | F69: 15
A70: Keith Brown | B70: 1999-2000 | C70: 11 | E70: 0
A71: Reece Brown | B71: 2014 | C71: 16 | D71: 1165 | E71: 0 | F71: 2
A72: Josh Brownhill | B72: 2015 | C72: 22 | D72: 1836 | E72: 2 | F72: 0
A73: Marciano Bruma | B73: 2007-2008 | C73: 36 | D73: 2872 | E73: 0 | F73: 1
A74: Ian Bryson | B74: 1993 | C74: 16 | E74: 3
A75: Wayne Bullimore | B75: 1992-1993 | C75: 17 | E75: 0
A76: Martin Bullock | B76: 1993-2000 | C76: 157 | D76: 2195 | E76: 4 | F76: 8
A77: Tony Bullock | B77: 1996-2000 | C77: 66 | E77: 0
A78: Jacob Burns | B78: 2003-2005 | C78: 89 | D78: 7249 | E78: 6 | F78: 4
A79: Deon Burton | B79: 1998 | C79: 3 | E79: 0
A80: Mark Burton | B80: 1992-1995 | C80: 5 | E80: 0
A81: Jack Butland | B81: 2013 | C81: 13 | D81: 1170 | E81: 0 | F81: 0
A82: Ian Butler | B82: 1998 | C82: 0 | E82: 0
A83: Lee Butler | B83: 1992-1995 | C83: 77 | E83: 0
A84: Jacob Butterfield | B84: 2007-2011 | C84: 90 | D84: 5136 | E84: 8 | F84: 14
A85: David Button | B85: 2011 | C85: 9 | D85: 810 | E85: 0 | F85: 0
A86: Ákos Buzsáky | B86: 2012 | C86: 5 | D86: 327 | E86: 0 | F86: 0
A87: Mike-Steven Bähre | B87: 2018-2019 | C87: 65 | D87: 3815 | E87: 3 | F87: 6
A88: Nicky Cadden | B88: 2022-2023 | C88: 85 | D88: 6444 | E88: 8 | F88: 8
A89: Tony Caig | B89: 2003 | C89: 3 | D89: 270 | E89: 0 | F89: 0
A90: Jamal Campbell-Ryce | B90: 2007-2009 | C90: 90 | D90: 6987 | E90: 12 | F90: 6
A91: Matt Carbon | B91: 2004-2005 | C91: 50 | D91: 3491 | E91: 1 | F91: 2
A92: Stephen Carson | B92: 2003 | C92: 11 | D92: 802 | E92: 1 | F92: 3
A93: David Cataroche | B93: 1998-1999 | C93: 0 | E93: 0
A94: Dimitri Cavaré | B94: 2017-2019 | C94: 65 | D94: 5462 | E94: 3 | F94: 6
A95: Conor Chaplin | B95: 2019-2020 | C95: 86 | D95: 5902 | E95: 17 | F95: 8
A96: Barnsley FC
A97: Player | B97: Years | C97: Apps | D97: Min | E97: Goals | F97: Ast
A98: Harry Chapman | B98: 2015 | C98: 11 | D98: 344 | E98: 1 | F98: 0
A99: Theo Chapman | B99: 2022-2023 | C99: 6 | D99: 189 | E99: 0 | F99: 0
A100: Steve Chettle | B100: 1999-2001 | C100: 92 | D100: 2762 | E100: 2 | F100: 0
...

Sheet Birmingham City
A1: Player | B1: Years | C1: Apps | D1: Min | E1: Goals | F1: Ast
A2: Gary Ablett | B2: 1996-1999 | C2: 104 | E2: 1
A3: Carl Adams | B3: 1992 | C3: 0 | E3: 0
A4: Charlee Adams | B4: 2015 | C4: 2 | D4: 71 | E4: 0 | F4: 0
A5: Ché Adams | B5: 2016-2018 | C5: 123 | D5: 8446 | E5: 38 | F5: 9
A6: Dele Adebola | B6: 1997-2000 | C6: 129 | E6: 31
A7: Tom Adeyemi | B7: 2013 | C7: 35 | D7: 2707 | E7: 1 | F7: 1
A8: Kemy Agustien | B8: 2008 | C8: 18 | D8: 1076 | E8: 0 | F8: 0
A9: Emanuel Aiwum | B9: 2023 | C9: 25 | D9: 2031 | E9: 0 | F9: 0
A10: Scott Allan | B10: 2013 | C10: 5 | D10: 236 | E10: 0 | F10: 0
A11: Ryan Allsop | B11: 2024-2026 | C11: 54 | D11: 4889 | E11: 0 | F11: 1
A12: Suzu Amano | B12: 2026 | C12: 1 | D12: 7 | E12: 0 | F12: 0
A13: Darren Ambrose | B13: 2012-2013 | C13: 7 | D13: 356 | E13: 0 | F13: 0
A14: Keshi Anderson | B14: 2023-2025 | C14: 86 | D14: 4534 | E14: 8 | F14: 9
A15: Darren Anderton | B15: 2004 | C15: 20 | D15: 868 | E15: 3 | F15: 1
A16: Chuks Aneke | B16: 2021 | C16: 21 | D16: 562 | E16: 2 | F16: 0
A17: Chloe Arthur | B17: 2018-2019 | C17: 31 | D17: 2493 | E17: 1 | F17: 2
A18: Koby Arthur | B18: 2012-2015 | C18: 15 | D18: 665 | E18: 0 | F18: 0
A19: Peter Atherton | B19: 2000 | C19: 10 | E19: 0
A20: Freda Ayisi | B20: 2017 | C20: 14 | D20: 442 | E20: 0 | F20: 0
A21: Juninho Bacuna | B21: 2021-2023 | C21: 111 | D21: 7528 | E21: 13 | F21: 15
A22: Sophie Baggaley | B22: 2017-2026 | C22: 5 | D22: 450 | E22: 0 | F22: 0
A23: Odin Bailey | B23: 2017-2020 | C23: 8 | D23: 132 | E23: 1 | F23: 0
A24: Geraldo Bajrami | B24: 2019 | C24: 3 | D24: 270 | E24: 0 | F24: 0
A25: Fred Barber | B25: 1995 | C25: 1 | E25: 0
A26: Paul Barnes | B26: 1995-1996 | C26: 15 | E26: 7
A27: Steve Barnes | B27: 1995-1998 | C27: 3 | E27: 0
A28: Dave Barnett | B28: 1993-1996 | C28: 46 | E28: 0
A29: Andrew Barrowman | B29: 2003 | C29: 1 | D29: 3 | E29: 0 | F29: 0
A30: Kyle Bartley | B30: 2013 | C30: 17 | D30: 1244 | E30: 3 | F30: 0
A31: Jon Bass | B31: 1994-2000 | C31: 68 | E31: 0
A32: Birmingham City FC
A33: Player | B33: Years | C33: Apps | D33: Min | E33: Goals | F33: Ast
A34: Briar Bateman | B34: 2025 | C34: 12 | D34: 931 | E34: 2 | F34: 2
A35: James Beadle | B35: 2025-2026 | C35: 46 | D35: 4140 | E35: 0 | F35: 0
A36: Jean Beausejour | B36: 2010-2011 | C36: 43 | D36: 3070 | E36: 4 | F36: 4
A37: Jason Beckford | B37: 1992-1994 | C37: 3 | E37: 1
A38: Jérémie Bela | B38: 2019-2021 | C38: 101 | D38: 6776 | E38: 9 | F38: 17
A39: Amari'i Bell | B39: 2013 | C39: 1 | D39: 90 | E39: 0 | F39: 0
A40: Jobe Bellingham | B40: 2021-2022 | C40: 39 | D40: 1677 | E40: 0 | F40: 0
A41: Jude Bellingham | B41: 2019 | C41: 44 | D41: 2926 | E41: 4 | F41: 2
A42: Nicklas Bendtner | B42: 2006 | C42: 42 | D42: 3384 | E42: 11 | F42: 7
A43: Ian Bennett | B43: 1993-2003 | C43: 287 | D43: 2981 | E43: 0 | F43: 0
A44: Marcus Bent | B44: 2008 | C44: 33 | D44: 1678 | E44: 3 | F44: 2
A45: David Bentley | B45: 2010 | C45: 13 | D45: 821 | E45: 0 | F45: 1
A46: Christian Benítez | B46: 2009 | C46: 30 | D46: 1935 | E46: 3 | F46: 5
A47: John Beresford | B47: 1999 | C47: 1 | E47: 0
A48: Ann-Katrin Berger | B48: 2017-2018 | C48: 27 | D48: 2384 | E48: 0 | F48: 0
A49: Zaid Betteka | B49: 2024-2025 | C49: 18 | D49: 1289 | E49: 4 | F49: 5
A50: Krystian Bielik | B50: 2016-2025 | C50: 122 | D50: 9137 | E50: 2 | F50: 1
A51: Max Bird | B51: 2026 | C51: 1 | D51: 11 | E51: 0 | F51: 0
A52: Mathew Birley | B52: 2005 | C52: 1 | D52: 26 | E52: 0 | F52: 0
A53: Simon Black | B53: 1993-1995 | C53: 2 | E53: 0
A54: Tyler Blackett | B54: 2013 | C54: 8 | D54: 508 | E54: 0 | F54: 2
A55: Robbie Blake | B55: 2004 | C55: 11 | D55: 335 | E55: 2 | F55: 0
A56: Laura Blindkilde | B56: 2019 | C56: 1 | D56: 4 | E56: 0 | F56: 0
A57: Robert Bloxham | B57: 1995 | C57: 0 | E57: 0
A58: Mick Bodley | B58: 1994 | C58: 3 | E58: 0
A59: Jeremie Boga | B59: 2017 | C59: 34 | D59: 2219 | E59: 2 | F59: 3
A60: Omar Bogle | B60: 2018 | C60: 16 | D60: 434 | E60: 1 | F60: 0
A61: Hameur Bouazza | B61: 2008 | C61: 16 | D61: 859 | E61: 1 | F61: 2
A62: Papa Bouba Diop | B62: 2012 | C62: 2 | D62: 105 | E62: 1 | F62: 0
A63: Jason Bowen | B63: 1995-1997 | C63: 48 | E63: 7
A64: Birmingham City FC
A65: Player | B65: Years | C65: Apps | D65: Min | E65: Goals | F65: Ast
A66: Lee Bowyer | B66: 2008-2010 | C66: 81 | D66: 6551 | E66: 10 | F66: 5
A67: Caolan Boyd-Munce | B67: 2019-2021 | C67: 20 | D67: 1091 | E67: 0 | F67: 1
A68: Lee Bradbury | B68: 1998 | C68: 7 | E68: 0
A69: Cohen Bramall | B69: 2017 | C69: 8 | D69: 621 | E69: 0 | F69: 0
A70: Ellie Brazil | B70: 2017 | C70: 6 | D70: 441 | E70: 0 | F70: 0
A71: Gary Breen | B71: 1995-1996 | C71: 40 | E71: 2
A72: Nicolai Brock-Madsen | B72: 2015-2017 | C72: 8 | D72: 288 | E72: 0 | F72: 0
A73: Alexandra Brooks | B73: 2018-2019 | C73: 0
A74: Georgia Brougham | B74: 2019-2020 | C74: 21 | D74: 1890 | E74: 0 | F74: 0
A75: Kenny Brown | B75: 1996-1997 | C75: 11 | E75: 0
A76: Reece Brown | B76: 2013-2016 | C76: 18 | D76: 550 | E76: 0 | F76: 0
A77: Alex Bruce | B77: 2005 | C77: 6 | D77: 276 | E77: 0 | F77: 0
A78: Steve Bruce | B78: 1995-1998 | C78: 72 | E78: 2
A79: Lee Buchanan | B79: 2023-2026 | C79: 40 | D79: 3224 | E79: 1 | F79: 0
A80: Will Buckley | B80: 2015 | C80: 10 | D80: 461 | E80: 1 | F80: 0
A81: Gary Bull | B81: 1994-1995 | C81: 16 | E81: 6
A82: James Bunch | B82: 1995 | C82: 0 | E82: 0
A83: Mark Burchill | B83: 2000 | C83: 13 | E83: 4
A84: Chris Burke | B84: 2011-2013 | C84: 137 | D84: 10322 | E84: 25 | F84: 28
A85: Oliver Burke | B85: 2023 | C85: 23 | D85: 1098 | E85: 0 | F85: 0
A86: Ryan Burke | B86: 2019 | C86: 1 | D86: 19 | E86: 0 | F86: 0
A87: Dan Burn | B87: 2013 | C87: 24 | D87: 2033 | E87: 1 | F87: 1
A88: William Burrell | B88: 2025-2026 | C88: 22 | D88: 1897 | E88: 2 | F88: 1
A89: David Burrows | B89: 2000-2001 | C89: 25 | D89: 898 | E89: 0 | F89: 0
A90: Jack Butland | B90: 2012 | C90: 46 | D90: 4140 | E90: 0 | F90: 0
A91: Nicky Butt | B91: 2005 | C91: 24 | D91: 1924 | E91: 3 | F91: 0
A92: Arkadiusz Bąk | B92: 2001 | C92: 4 | D92: 193 | E92: 0 | F92: 0
A93: Paul Caddis | B93: 2012-2016 | C93: 154 | D93: 13385 | E93: 16 | F93: 11
A94: Steven Caldwell | B94: 2011-2012 | C94: 81 | D94: 7098 | E94: 1 | F94: 1
A95: Lee Camp | B95: 2018-2019 | C95: 86 | D95: 7770 | E95: 0 | F95: 1
A96: Birmingham City FC
A97: Player | B97: Years | C97: Apps | D97: Min | E97: Goals | F97: Ast
A98: DJ Campbell | B98: 2005-2006 | C98: 43 | D98: 1806 | E98: 9 | F98: 1
A99: Stuart Campbell | B99: 1999 | C99: 2 | E99: 0
A100: Tate Campbell | B100: 2020-2022 | C100: 13 | D100: 938 | E100: 0 | F100: 0
...

Sheet Blackburn Rovers
A1: Player | B1: Years | C1: Apps | D1: Min | E1: Goals | F1: Ast
A2: Tosin Adarabioyo | B2: 2019 | C2: 35 | D2: 3056 | E2: 3 | F2: 1
A3: Dapo Afolayan | B3: 2025-2026 | C3: 17 | D3: 801 | E3: 3 | F3: 1
A4: Yakubu Aiyegbeni | B4: 2011 | C4: 30 | D4: 2442 | E4: 17 | F4: 2
A5: Hope Akpan | B5: 2015-2016 | C5: 66 | D5: 4792 | E5: 5 | F5: 0
A6: Ryan Alebiosu | B6: 2025-2026 | C6: 48 | D6: 3901 | E6: 1 | F6: 6
A7: Lorenzo Amoruso | B7: 2003-2004 | C7: 20 | D7: 1624 | E7: 3 | F7: 0
A8: Anders Andersson | B8: 1997-1999 | C8: 4 | D8: 78 | E8: 0 | F8: 0
A9: Patrik Andersson | B9: 1992-1993 | C9: 12 | D9: 516 | E9: 0 | F9: 0
A10: Martin Andresen | B10: 2003 | C10: 11 | D10: 861 | E10: 0 | F10: 0
A11: Keith Andrews | B11: 2008-2010 | C11: 70 | D11: 4734 | E11: 5 | F11: 0
A12: Louie Annesley | B12: 2018-2022 | C12: 39 | D12: 3047 | E12: 1 | F12: 0
A13: Marcus Antonsson | B13: 2017 | C13: 34 | D13: 1930 | E13: 8 | F13: 3
A14: Adam Armstrong | B14: 2017-2020 | C14: 160 | D14: 12024 | E14: 64 | F14: 17
A15: Tom Atcheson | B15: 2023-2026 | C15: 54 | D15: 4237 | E15: 1 | F15: 4
A16: Mark Atkins | B16: 1992-1995 | C16: 87 | D16: 6048 | E16: 12 | F16: 5
A17: Daniel Ayala | B17: 2020-2022 | C17: 61 | D17: 4512 | E17: 4 | F17: 2
A18: Yasin Ayari | B18: 2023 | C18: 14 | D18: 487 | E18: 0 | F18: 1
A19: Markus Babbel | B19: 2003 | C19: 26 | D19: 2126 | E19: 3 | F19: 3
A20: Dino Baggio | B20: 2003 | C20: 11 | D20: 258 | E20: 1 | F20: 0
A21: Lewis Baker | B21: 2024 | C21: 14 | D21: 686 | E21: 1 | F21: 0
A22: Ryan Baldacchino | B22: 1999 | C22: 0 | E22: 0
A23: Alex Baptiste | B23: 2014 | C23: 34 | D23: 2801 | E23: 3 | F23: 0
A24: Moussa Baradji | B24: 2025-2026 | C24: 33 | D24: 1815 | E24: 2 | F24: 0
A25: Sam Barnes | B25: 2017-2023 | C25: 40 | D25: 3273 | E25: 3 | F25: 1
A26: Modou Barrow | B26: 2015 | C26: 5 | D26: 172 | E26: 0 | F26: 0
A27: Danny Batth | B27: 2024 | C27: 41 | D27: 3344 | E27: 2 | F27: 0
A28: David Batty | B28: 1993-1995 | C28: 59 | D28: 5168 | E28: 1 | F28: 3
A29: Jake Batty | B29: 2021-2025 | C29: 32 | D29: 2464 | E29: 2 | F29: 3
A30: Yıldıray Baştürk | B30: 2009 | C30: 1 | D30: 45 | E30: 0 | F30: 0
A31: James Beattie | B31: 1996-1997 | C31: 4 | D31: 131 | E31: 0 | F31: 0
A32: Blackburn Rovers FC
A33: Player | B33: Years | C33: Apps | D33: Min | E33: Goals | F33: Ast
A34: Owen Beck | B34: 2024 | C34: 26 | D34: 2054 | E34: 1 | F34: 2
A35: Amari'i Bell | B35: 2017-2020 | C35: 99 | D35: 7989 | E35: 3 | F35: 2
A36: Andy Bell | B36: 2000 | C36: 0 | E36: 0
A37: Craig Bellamy | B37: 2005 | C37: 27 | D37: 2015 | E37: 13 | F37: 2
A38: Benjani | B38: 2010 | C38: 18 | D38: 662 | E38: 3 | F38: 0
A39: Elliott Bennett | B39: 2015-2020 | C39: 193 | D39: 14192 | E39: 9 | F39: 15
A40: Marcus Bent | B40: 2000-2001 | C40: 37 | D40: 246 | E40: 8 | F40: 1
A41: David Bentley | B41: 2005-2012 | C41: 117 | D41: 9622 | E41: 16 | F41: 17
A42: Henning Berg | B42: 1992-2002 | C42: 260 | D42: 18947 | E42: 7 | F42: 9
A43: Eyal Berkovic | B43: 2000 | C43: 11 | E43: 2
A44: Bruno Berner | B44: 2006-2007 | C44: 3 | D44: 270 | E44: 0 | F44: 0
A45: Leon Best | B45: 2012-2013 | C45: 14 | D45: 737 | E45: 2 | F45: 0
A46: Gady Beyuku | B46: 2026 | C46: 2 | D46: 54 | E46: 0 | F46: 0
A47: Michael Bingham | B47: 1999-2000 | C47: 0 | E47: 0
A48: Mame Biram Diouf | B48: 2010 | C48: 27 | D48: 1630 | E48: 3 | F48: 1
A49: Nick Blackman | B49: 2011 | C49: 1 | D49: 7 | E49: 0 | F49: 0
A50: Nathan Blake | B50: 1998-2001 | C50: 54 | D50: 982 | E50: 13 | F50: 0
A51: Liam Blakeman | B51: 1999-2000 | C51: 0 | E51: 0
A52: Thomas Bloxham | B52: 2022-2024 | C52: 17 | D52: 1113 | E52: 5 | F52: 0
A53: Lars Bohinen | B53: 1995-1997 | C53: 58 | D53: 3963 | E53: 7 | F53: 5
A54: Jay Bothroyd | B54: 2004 | C54: 11 | D54: 488 | E54: 1 | F54: 0
A55: Jarrad Branthwaite | B55: 2020 | C55: 10 | D55: 900 | E55: 0 | F55: 0
A56: Luke Brennan | B56: 2018-2021 | C56: 39 | D56: 2030 | E56: 5 | F56: 7
A57: Ben Brereton Díaz | B57: 2018-2022 | C57: 180 | D57: 11682 | E57: 49 | F57: 12
A58: Callum Brittain | B58: 2022-2024 | C58: 115 | D58: 8501 | E58: 3 | F58: 13
A59: Marlon Broomes | B59: 1997-2000 | C59: 32 | D59: 1223 | E59: 1 | F59: 0
A60: Chris Brown | B60: 2014-2015 | C60: 41 | D60: 1811 | E60: 0 | F60: 3
A61: James Brown | B61: 2021-2022 | C61: 8 | D61: 656 | E61: 0 | F61: 1
A62: Jason Brown | B62: 2006-2009 | C62: 9 | D62: 696 | E62: 0 | F62: 0
A63: Keith Brown | B63: 1999 | C63: 0 | E63: 0
A64: Blackburn Rovers FC
A65: Player | B65: Years | C65: Apps | D65: Min | E65: Goals | F65: Ast
A66: Richard Brown | B66: 1992 | C66: 2 | D66: 174 | E66: 0 | F66: 0
A67: Wes Brown | B67: 2016 | C67: 6 | D67: 247 | E67: 1 | F67: 0
A68: John Buckley | B68: 2017-2025 | C68: 208 | D68: 12127 | E68: 11 | F68: 20
A69: Mark Bunn | B69: 2010-2011 | C69: 6 | D69: 495 | E69: 0 | F69: 0
A70: Ben Burgess | B70: 1999-2000 | C70: 2 | E70: 0
A71: Daniel Butterworth | B71: 2017-2022 | C71: 62 | D71: 3833 | E71: 14 | F71: 6
A72: Jack Byrne | B72: 2016 | C72: 7 | D72: 503 | E72: 0 | F72: 0
A73: Paul Caddis | B73: 2017-2018 | C73: 21 | D73: 1725 | E73: 0 | F73: 2
A74: Tom Cairney | B74: 2013-2014 | C74: 82 | D74: 6436 | E74: 8 | F74: 13
A75: DJ Campbell | B75: 2012-2013 | C75: 14 | D75: 704 | E75: 0 | F75: 0
A76: Todd Cantwell | B76: 2024-2026 | C76: 77 | D76: 5397 | E76: 9 | F76: 11
A77: Lee Carsley | B77: 1998-2000 | C77: 46 | D77: 636 | E77: 10 | F77: 0
A78: Hayden Carter | B78: 2017-2026 | C78: 156 | D78: 12228 | E78: 4 | F78: 6
A79: Eiran Cashin | B79: 2025 | C79: 19 | D79: 1617 | E79: 1 | F79: 1
A80: Robert Chamberlain | B80: 1999-2000 | C80: 0 | E80: 0
A81: Harry Chapman | B81: 2017-2021 | C81: 51 | D81: 2388 | E81: 9 | F81: 10
A82: Pascal Chimbonda | B82: 2009-2010 | C82: 30 | D82: 2338 | E82: 1 | F82: 1
A83: Benjamin Chrisene | B83: 2023 | C83: 19 | D83: 1011 | E83: 0 | F83: 0
A84: Lenni Cirino | B84: 2020-2023 | C84: 29 | D84: 2290 | E84: 0 | F84: 4
A85: Leighton Clarkson | B85: 2021 | C85: 7 | D85: 328 | E85: 0 | F85: 0
A86: Andy Cole | B86: 2001-2003 | C86: 87 | D86: 7039 | E86: 27 | F86: 14
A87: Chris Coleman | B87: 1995-1996 | C87: 28 | D87: 2449 | E87: 0 | F87: 0
A88: Craig Conway | B88: 2013-2018 | C88: 199 | D88: 13523 | E88: 22 | F88: 36
A89: Jimmy Corbett | B89: 1999-2000 | C89: 0 | E89: 0
A90: Gordon Cowans | B90: 1992 | C90: 24 | D90: 2124 | E90: 1 | F90: 4
A91: Amario Cozier-Duberry | B91: 2024 | C91: 23 | D91: 779 | E91: 1 | F91: 0
A92: Gary Croft | B92: 1996-1999 | C92: 40 | D92: 2956 | E92: 1 | F92: 1
A93: Greg Cunningham | B93: 2019 | C93: 10 | D93: 826 | E93: 0 | F93: 1
A94: John Curtis | B94: 2000-2002 | C94: 61 | D94: 1098 | E94: 0 | F94: 0
A95: Bradley Dack | B95: 2017-2022 | C95: 180 | D95: 12219 | E95: 59 | F95: 28
A96: Blackburn Rovers FC
A97: Player | B97: Years | C97: Apps | D97: Min | E97: Goals | F97: Ast
A98: Martin Dahlin | B98: 1997-1999 | C98: 27 | D98: 1357 | E98: 4 | F98: 1
A99: Christian Dailly | B99: 1998-2000 | C99: 72 | D99: 1424 | E99: 4 | F99: 0
A100: Scott Dann | B100: 2011-2013 | C100: 98 | D100: 8710 | E100: 5 | F100: 7
...

Sheet Blackpool
A1: Player | B1: Years | C1: Apps | D1: Min | E1: Goals | F1: Ast
A2: Gary Ablett | B2: 1999 | C2: 10 | E2: 1
A3: Charlie Adam | B3: 2008-2010 | C3: 91 | D3: 7819 | E3: 30 | F3: 17
A4: Miles Addison | B4: 2014 | C4: 5 | D4: 450 | E4: 0 | F4: 0
A5: Dan Agyei | B5: 2017 | C5: 9 | D5: 167 | E5: 0 | F5: 0
A6: Will Aimson | B6: 2015-2017 | C6: 57 | D6: 4504 | E6: 0 | F6: 1
A7: Tom Aldred | B7: 2014-2016 | C7: 99 | D7: 8797 | E7: 7 | F7: 2
A8: Martin Aldridge | B8: 1998-1999 | C8: 27 | E8: 7
A9: Craig Allardyce | B9: 1994-1996 | C9: 1 | E9: 0
A10: Ryan Allsop | B10: 2017 | C10: 23 | D10: 2070 | E10: 0 | F10: 0
A11: Louis Almond | B11: 2013 | C11: 1 | D11: 35 | E11: 0 | F11: 0
A12: Jak Alnwick | B12: 2019 | C12: 24 | D12: 2099 | E12: 0 | F12: 0
A13: Sone Aluko | B13: 2008 | C13: 1 | D13: 3 | E13: 0 | F13: 0
A14: Karoy Anderson | B14: 2025-2026 | C14: 23 | D14: 1705 | E14: 2 | F14: 0
A15: Keshi Anderson | B15: 2020-2022 | C15: 63 | D15: 4255 | E15: 8 | F15: 6
A16: Stuart Anderson | B16: 2004 | C16: 4 | D16: 84 | E16: 0 | F16: 0
A17: Nick Anderton | B17: 2017-2019 | C17: 20 | D17: 1482 | E17: 0 | F17: 0
A18: Cameron Antwi | B18: 2020-2021 | C18: 1 | D18: 68 | E18: 0 | F18: 0
A19: Rob Apter | B19: 2020-2024 | C19: 53 | D19: 3554 | E19: 8 | F19: 8
A20: Zachary Ashworth | B20: 2024-2026 | C20: 45 | D20: 2800 | E20: 1 | F20: 1
A21: Will Avon | B21: 2018 | C21: 0
A22: Elkan Baggott | B22: 2024 | C22: 19 | D22: 1396 | E22: 0 | F22: 1
A23: Neil Bailey | B23: 1992-1994 | C23: 9 | E23: 0
A24: Daniel Ballard | B24: 2020 | C24: 27 | D24: 2411 | E24: 2 | F24: 0
A25: Dominic Ballard | B25: 2024 | C25: 21 | D25: 929 | E25: 1 | F25: 0
A26: Dave Bamber | B26: 1992-1994 | C26: 48 | E26: 17
A27: Mike Bamber | B27: 1999 | C27: 0 | E27: 0
A28: Ewan Bange | B28: 2019-2020 | C28: 0
A29: Al Bangura | B29: 2009 | C29: 9 | D29: 166 | E29: 0 | F29: 0
A30: Scott Banks | B30: 2025 | C30: 17 | D30: 529 | E30: 2 | F30: 1
A31: Steve Banks | B31: 1995-1998 | C31: 150 | E31: 0
A32: Blackpool FC
A33: Player | B33: Years | C33: Apps | D33: Min | E33: Goals | F33: Ast
A34: Barry Bannan | B34: 2009 | C34: 20 | D34: 753 | E34: 1 | F34: 2
A35: Alex Baptiste | B35: 2008-2012 | C35: 170 | D35: 15046 | E35: 8 | F35: 8
A36: Fred Barber | B36: 1995 | C36: 1 | E36: 0
A37: David Bardsley | B37: 1998-1999 | C37: 64 | E37: 0
A38: Harvey Bardsley | B38: 2025 | C38: 0
A39: Shaun Barker | B39: 2006-2008 | C39: 134 | D39: 11945 | E39: 5 | F39: 10
A40: Tom Barkhuizen | B40: 2013-2014 | C40: 22 | D40: 704 | E40: 1 | F40: 0
A41: Andy Barlow | B41: 1995-1996 | C41: 80 | E41: 2
A42: Kevin Barnes | B42: 1998 | C42: 4 | E42: 0
A43: Phil Barnes | B43: 1997-2003 | C43: 141 | D43: 5668 | E43: 0 | F43: 0
A44: Andrew Barrowman | B44: 2004 | C44: 2 | D44: 40 | E44: 0 | F44: 0
A45: Chris Basham | B45: 2010-2013 | C45: 85 | D45: 6227 | E45: 5 | F45: 4
A46: Marcus Bean | B46: 2005-2006 | C46: 32 | D46: 2538 | E46: 2 | F46: 2
A47: James Beattie | B47: 2010 | C47: 9 | D47: 433 | E47: 0 | F47: 3
A48: Claus Bech Jørgensen | B48: 2006-2008 | C48: 100 | D48: 6493 | E48: 6 | F48: 7
A49: Roman Bednář | B49: 2011 | C49: 9 | D49: 350 | E49: 1 | F49: 2
A50: Chris Beech | B50: 1992-1996 | C50: 82 | E50: 4
A51: Jake Beesley | B51: 2021-2024 | C51: 71 | D51: 3503 | E51: 13 | F51: 3
A52: Paul Beesley | B52: 1998-2000 | C52: 18 | E52: 0
A53: Junior Bent | B53: 1997-2000 | C53: 103 | E53: 5
A54: Neal Bishop | B54: 2013 | C54: 35 | D54: 2640 | E54: 1 | F54: 0
A55: Ian Black | B55: 2016 | C55: 10 | D55: 246 | E55: 0 | F55: 0
A56: Tyler Blackett | B56: 2013 | C56: 5 | D56: 423 | E56: 0 | F56: 0
A57: Andre Blackman | B57: 2014 | C57: 3 | D57: 122 | E57: 0 | F57: 0
A58: Nick Blackman | B58: 2008 | C58: 5 | D58: 178 | E58: 1 | F58: 0
A59: Matthew Blinkhorn | B59: 2001-2005 | C59: 42 | D59: 1339 | E59: 5 | F59: 1
A60: Tom Bloxham | B60: 2024-2026 | C60: 68 | D60: 3830 | E60: 12 | F60: 8
A61: Jason Blunt | B61: 1998 | C61: 2 | E61: 0
A62: Jacob Blyth | B62: 2015 | C62: 8 | D62: 578 | E62: 2 | F62: 0
A63: Daniel Bogdanović | B63: 2011 | C63: 8 | D63: 165 | E63: 2 | F63: 0
A64: Blackpool FC
A65: Player | B65: Years | C65: Apps | D65: Min | E65: Goals | F65: Ast
A66: Marc Bola | B66: 2018-2019 | C66: 47 | D66: 4056 | E66: 2 | F66: 4
A67: Richie Bond | B67: 1992 | C67: 1 | E67: 0
A68: Terry Bondo | B68: 2024-2025 | C68: 6 | D68: 63 | E68: 0 | F68: 0
A69: Myles Boney | B69: 2014-2018 | C69: 2 | D69: 95 | E69: 0 | F69: 0
A70: Mark Bonner | B70: 1992-1998 | C70: 175 | E70: 14
A71: Hameur Bouazza | B71: 2009 | C71: 19 | D71: 1026 | E71: 1 | F71: 3
A72: Josh Bowler | B72: 2021-2026 | C72: 110 | D72: 7278 | E72: 17 | F72: 9
A73: Steven Boyack | B73: 2004 | C73: 1 | D73: 22 | E73: 0 | F73: 0
A74: Emmerson Boyce | B74: 2015 | C74: 26 | D74: 1740 | E74: 0 | F74: 0
A75: Gary Brabin | B75: 1996-1998 | C75: 63 | E75: 5
A76: Darren Bradshaw | B76: 1994-1997 | C76: 67 | E76: 1
A77: Chris Brandon | B77: 2006 | C77: 5 | D77: 324 | E77: 2 | F77: 1
A78: Liam Bridcutt | B78: 2022 | C78: 4 | D78: 182 | E78: 0 | F78: 0
A79: Charlie Brier | B79: 2026 | C79: 0
A80: Gary Briggs | B80: 1992-1994 | C80: 66 | E80: 2
A81: David Brightwell | B81: 1996 | C81: 2 | E81: 0
A82: Kirk Broadfoot | B82: 2012-2013 | C82: 65 | D82: 5726 | E82: 2 | F82: 1
A83: Marlon Broomes | B83: 2008 | C83: 1 | D83: 7 | E83: 0 | F83: 0
A84: Jordan Brown | B84: 2025-2026 | C84: 53 | D84: 4003 | E84: 1 | F84: 5
A85: Phil Brown | B85: 1994-1995 | C85: 44 | E85: 5
A86: Richard Brown | B86: 1995 | C86: 3 | E86: 0
A87: Gerardo Bruna | B87: 2011-2012 | C87: 2 | D87: 19 | E87: 0 | F87: 0
A88: Marvin Bryan | B88: 1995-1999 | C88: 182 | E88: 4
A89: Martin Bullock | B89: 2001-2004 | C89: 153 | D89: 8126 | E89: 4 | F89: 19
A90: Joe Bunney | B90: 2018 | C90: 5 | D90: 354 | E90: 0 | F90: 0
A91: Ben Burgess | B91: 2006-2009 | C91: 126 | D91: 7653 | E91: 23 | F91: 8
A92: Dave Burgess | B92: 1992 | C92: 20 | E92: 0
A93: David Burke | B93: 1994-1995 | C93: 23 | E93: 0
A94: Jamie Burns | B94: 2002-2005 | C94: 47 | D94: 2842 | E94: 1 | F94: 2
A95: Steve Bushell | B95: 1998-2000 | C95: 79 | E95: 6
A96: Blackpool FC
A97: Player | B97: Years | C97: Apps | D97: Min | E97: Goals | F97: Ast
A98: Rocky Bushiri | B98: 2019 | C98: 5 | D98: 265 | E98: 0 | F98: 0
A99: Andy Butler | B99: 2009 | C99: 7 | D99: 484 | E99: 0 | F99: 0
A100: Tony Butler | B100: 1996-2005 | C100: 131 | D100: 2296 | E100: 1 | F100: 0
...

Sheet Bolton Wanderers
A1: Player | B1: Years | C1: Apps | D1: Min | E1: Goals | F1: Ast
A2: Dave Abimbola | B2: 2024 | C2: 4 | D2: 104 | E2: 0 | F2: 0
A3: Victor Adeboyejo | B3: 2022-2024 | C3: 85 | D3: 4384 | E3: 16 | F3: 3
A4: Benik Afobe | B4: 2012 | C4: 20 | D4: 717 | E4: 2 | F4: 1
A5: Dapo Afolayan | B5: 2020-2022 | C5: 93 | D5: 6469 | E5: 17 | F5: 7
A6: Will Aimson | B6: 2021-2022 | C6: 39 | D6: 3111 | E6: 1 | F6: 1
A7: Bülent Akın | B7: 2002 | C7: 1 | D7: 5 | E7: 0 | F7: 0
A8: Matthew Alexander | B8: 2019-2020 | C8: 1 | D8: 90 | E8: 0 | F8: 0
A9: Hasney Aljofree | B9: 1996-1999 | C9: 14 | D9: 180 | E9: 0 | F9: 0
A10: Ben Alnwick | B10: 2016-2019 | C10: 93 | D10: 8294 | E10: 0 | F10: 1
A11: Marcos Alonso | B11: 2010-2012 | C11: 35 | D11: 2949 | E11: 5 | F11: 2
A12: Mikel Alonso | B12: 2007 | C12: 10 | D12: 540 | E12: 0 | F12: 0
A13: Xavier Amaechi | B13: 2021 | C13: 11 | D13: 304 | E13: 1 | F13: 1
A14: Sammy Ameobi | B14: 2016-2018 | C14: 89 | D14: 6874 | E14: 11 | F14: 8
A15: Shola Ameobi | B15: 2015 | C15: 10 | D15: 605 | E15: 2 | F15: 0
A16: Bright Amoateng | B16: 2020 | C16: 1 | D16: 20 | E16: 0 | F16: 0
A17: Ben Amos | B17: 2014-2016 | C17: 53 | D17: 4657 | E17: 0 | F17: 0
A18: Keshi Anderson | B18: 2016 | C18: 9 | D18: 302 | E18: 1 | F18: 0
A19: Ben Andreucci | B19: 2023-2024 | C19: 0
A20: Keith Andrews | B20: 2012-2013 | C20: 26 | D20: 2046 | E20: 4 | F20: 0
A21: Pierre-Yves André | B21: 2002 | C21: 9 | D21: 180 | E21: 0 | F21: 0
A22: Nicolas Anelka | B22: 2006-2007 | C22: 57 | D22: 4853 | E22: 22 | F22: 6
A23: Rob Apter | B23: 2025 | C23: 13 | D23: 704 | E23: 0 | F23: 1
A24: Scott Arfield | B24: 2024 | C24: 16 | D24: 567 | E24: 0 | F24: 1
A25: Adam Armstrong | B25: 2017 | C25: 23 | D25: 1286 | E25: 3 | F25: 2
A26: Zachary Ashworth | B26: 2023 | C26: 20 | D26: 919 | E26: 3 | F26: 2
A27: Ibrahim Ba | B27: 2003 | C27: 9 | D27: 245 | E27: 0 | F27: 0
A28: Theo Bair | B28: 2026 | C28: 2 | D28: 76 | E28: 0 | F28: 1
A29: Amadou Bakayoko | B29: 2021-2022 | C29: 57 | D29: 2241 | E29: 12 | F29: 4
A30: Ryan Baldacchino | B30: 2000 | C30: 0 | E30: 0
A31: Salva Ballesta | B31: 2002 | C31: 5 | D31: 131 | E31: 0 | F31: 0
A32: Bolton Wanderers FC
A33: Player | B33: Years | C33: Apps | D33: Min | E33: Goals | F33: Ast
A34: Steve Banks | B34: 1998-2001 | C34: 21 | D34: 90 | E34: 0 | F34: 0
A35: Barry Bannan | B35: 2014 | C35: 16 | D35: 1372 | E35: 0 | F35: 3
A36: Alex Baptiste | B36: 2013-2021 | C36: 95 | D36: 7626 | E36: 5 | F36: 4
A37: Anthony Barness | B37: 2000-2004 | C37: 93 | D37: 5175 | E37: 0 | F37: 0
A38: Chris Basham | B38: 2008-2009 | C38: 19 | D38: 711 | E38: 1 | F38: 1
A39: Nathan Baxter | B39: 2023-2024 | C39: 64 | D39: 5715 | E39: 0 | F39: 0
A40: Gavin Bazunu | B40: 2026 | C40: 2 | D40: 180 | E40: 0 | F40: 0
A41: Peter Beardsley | B41: 1997 | C41: 17 | D41: 1197 | E41: 2 | F41: 0
A42: Owen Beck | B42: 2022 | C42: 6 | D42: 208 | E42: 0 | F42: 0
A43: Jermaine Beckford | B43: 2013-2014 | C43: 49 | D43: 2842 | E43: 9 | F43: 2
A44: Mark Beevers | B44: 2016-2018 | C44: 131 | D44: 11696 | E44: 12 | F44: 0
A45: Tal Ben Haim | B45: 2004-2006 | C45: 95 | D45: 7908 | E45: 1 | F45: 0
A46: Guðni Bergsson | B46: 1994-2002 | C46: 270 | D46: 11445 | E46: 23 | F46: 4
A47: Corey Blackett-Taylor | B47: 2025 | C47: 7 | D47: 347 | E47: 2 | F47: 1
A48: Nathan Blake | B48: 1995-1998 | C48: 107 | D48: 4294 | E48: 38 | F48: 5
A49: Robbie Blake | B49: 2010-2011 | C49: 9 | D49: 52 | E49: 1 | F49: 0
A50: Fredi Bobic | B50: 2001 | C50: 16 | D50: 1077 | E50: 4 | F50: 2
A51: Ádám Bogdán | B51: 2010-2014 | C51: 107 | D51: 9573 | E51: 0 | F51: 0
A52: Jack Bonham | B52: 2025-2026 | C52: 27 | D52: 2430 | E52: 0 | F52: 0
A53: Jordan Boon | B53: 2019 | C53: 4 | D53: 173 | E53: 0 | F53: 0
A54: Jared Borgetti | B54: 2005 | C54: 26 | D54: 872 | E54: 4 | F54: 0
A55: Con Boutsianis | B55: 1999 | C55: 0 | E55: 0
A56: Dedryck Boyata | B56: 2011 | C56: 14 | D56: 1122 | E56: 1 | F56: 0
A57: Daniel Braaten | B57: 2007 | C57: 11 | D57: 435 | E57: 1 | F57: 0
A58: Conor Bradley | B58: 2022 | C58: 44 | D58: 3809 | E58: 6 | F58: 4
A59: Keith Branagan | B59: 1992-1999 | C59: 214 | D59: 5790 | E59: 0 | F59: 0
A60: Liam Bridcutt | B60: 2019 | C60: 11 | D60: 848 | E60: 0 | F60: 0
A61: Harry Brockbank | B61: 2017-2021 | C61: 33 | D61: 2119 | E61: 0 | F61: 0
A62: Nathan Broome | B62: 2025 | C62: 0
A63: Eddie Brown | B63: 2019 | C63: 6 | D63: 440 | E63: 0 | F63: 0
A64: Bolton Wanderers FC
A65: Player | B65: Years | C65: Apps | D65: Min | E65: Goals | F65: Ast
A66: Mickey Brown | B66: 1992 | C66: 6 | E66: 0
A67: Phil Brown | B67: 1992-1994 | C67: 82 | E67: 7
A68: De'Marlio Brown-Sterling | B68: 2019 | C68: 3 | D68: 113 | E68: 0 | F68: 0
A69: Lewis Brunt | B69: 2026 | C69: 5 | D69: 321 | E69: 0 | F69: 0
A70: Kean Bryan | B70: 2019 | C70: 6 | D70: 534 | E70: 1 | F70: 0
A71: Wayne Buchanan | B71: 2000 | C71: 0 | E71: 0
A72: Will Buckley | B72: 2017-2019 | C72: 65 | D72: 3548 | E72: 7 | F72: 3
A73: Joe Bunney | B73: 2019 | C73: 2 | D73: 74 | E73: 0 | F73: 0
A74: David Burke | B74: 1992-1994 | C74: 55 | E74: 0
A75: Reece Burke | B75: 2017 | C75: 26 | D75: 1980 | E75: 1 | F75: 0
A76: Wayne Burnett | B76: 1995-1996 | C76: 2 | D76: 22 | E76: 0 | F76: 0
A77: Mason Burstow | B77: 2025 | C77: 48 | D77: 2572 | E77: 12 | F77: 4
A78: Danny Butterfield | B78: 2012 | C78: 6 | D78: 200 | E78: 0 | F78: 0
A79: Jacob Butterfield | B79: 2012 | C79: 8 | D79: 297 | E79: 0 | F79: 0
A80: Lewis Buxton | B80: 2016 | C80: 9 | D80: 765 | E80: 0 | F80: 0
A81: Gary Cahill | B81: 2007-2011 | C81: 134 | D81: 11940 | E81: 13 | F81: 5
A82: Mark Came | B82: 1992 | C82: 4 | E82: 0
A83: Andy Campbell | B83: 2000 | C83: 6 | E83: 0
A84: Harry Campbell | B84: 2015 | C84: 0
A85: Iván Campo | B85: 2002-2007 | C85: 176 | D85: 13572 | E85: 13 | F85: 7
A86: Vincent Candela | B86: 2004 | C86: 10 | D86: 780 | E86: 0 | F86: 0
A87: Franz Carr | B87: 1997 | C87: 5 | D87: 131 | E87: 0 | F87: 0
A88: Dion Charles | B88: 2021-2024 | C88: 134 | D88: 9068 | E88: 50 | F88: 6
A89: Simon Charlton | B89: 2000-2003 | C89: 120 | D89: 7894 | E89: 0 | F89: 4
A90: Harry Charsley | B90: 2017 | C90: 1 | D90: 54 | E90: 0 | F90: 0
A91: Adam Chicksen | B91: 2019 | C91: 17 | D91: 1393 | E91: 0 | F91: 0
A92: Cyrus Christie | B92: 2025-2026 | C92: 25 | D92: 1299 | E92: 0 | F92: 1
A93: Lee Chung-yong | B93: 2009-2014 | C93: 179 | D93: 12664 | E93: 17 | F93: 22
A94: Gérald Cid | B94: 2007 | C94: 12 | D94: 932 | E94: 0 | F94: 0
A95: Ibrahim Cissoko | B95: 2025 | C95: 28 | D95: 1046 | E95: 4 | F95: 0
A96: Bolton Wanderers FC
A97: Player | B97: Years | C97: Apps | D97: Min | E97: Goals | F97: Ast
A98: Chris Clarke | B98: 1992-1994 | C98: 0 | E98: 0
A99: Matt Clarke | B99: 2000 | C99: 8 | E99: 0
A100: Max Clayton | B100: 2014-2016 | C100: 29 | D100: 1195 | E100: 2 | F100: 1
...

Sheet Bournemouth
A1: Player | B1: Years | C1: Apps | D1: Min | E1: Goals | F1: Ast
A2: Max Aarons | B2: 2023-2024 | C2: 27 | D2: 1557 | E2: 0 | F2: 1
A3: Tyler Adams | B3: 2023-2026 | C3: 66 | D3: 4478 | E3: 2 | F3: 5
A4: Miles Addison | B4: 2011-2012 | C4: 34 | D4: 3060 | E4: 1 | F4: 1
A5: Amine Adli | B5: 2025 | C5: 33 | D5: 1254 | E5: 3 | F5: 1
A6: Daniel Adu-Adjei | B6: 2022-2024 | C6: 1 | D6: 2 | E6: 0 | F6: 0
A7: Benik Afobe | B7: 2015-2017 | C7: 70 | D7: 3520 | E7: 11 | F7: 3
A8: Lionel Ainsworth | B8: 2006 | C8: 7 | D8: 189 | E8: 0 | F8: 0
A9: Nathan Aké | B9: 2016-2019 | C9: 121 | D9: 10489 | E9: 11 | F9: 5
A10: Ryan Allsop | B10: 2012-2016 | C10: 24 | D10: 2044 | E10: 0 | F10: 0
A11: Darren Anderton | B11: 2006-2008 | C11: 66 | D11: 5406 | E11: 12 | F11: 7
A12: Ian Andrews | B12: 1994-1996 | C12: 64 | E12: 0
A13: Stevland Angus | B13: 2000 | C13: 9 | E13: 0
A14: Jaidon Anthony | B14: 2020-2024 | C14: 93 | D14: 5499 | E14: 12 | F14: 10
A15: Julian Araujo | B15: 2024-2025 | C15: 14 | D15: 590 | E15: 0 | F15: 0
A16: Kepa Arrizabalaga | B16: 2024 | C16: 35 | D16: 3180 | E16: 0 | F16: 0
A17: Harry Arter | B17: 2010-2020 | C17: 241 | D17: 18575 | E17: 28 | F17: 17
A18: Jamie Ashdown | B18: 2002 | C18: 2 | D18: 180 | E18: 0 | F18: 0
A19: Warren Aspinall | B19: 1993-1994 | C19: 33 | E19: 9
A20: Christian Atsu | B20: 2015 | C20: 2 | D20: 156 | E20: 0 | F20: 1
A21: John Bailey | B21: 1995-2000 | C21: 149 | E21: 6
A22: Stuart Barfoot | B22: 1994 | C22: 2 | E22: 0
A23: Lee Barnard | B23: 2012 | C23: 15 | D23: 1203 | E23: 4 | F23: 1
A24: Adam Barrett | B24: 2011 | C24: 21 | D24: 1631 | E24: 1 | F24: 0
A25: Marvin Bartley | B25: 2007-2010 | C25: 113 | D25: 8036 | E25: 3 | F25: 3
A26: Vince Bartram | B26: 1992-1993 | C26: 86 | E26: 0
A27: Mathieu Baudry | B27: 2010-2011 | C27: 10 | D27: 551 | E27: 1 | F27: 0
A28: Peter Beadle | B28: 1992 | C28: 9 | E28: 2
A29: Russell Beardsmore | B29: 1993-1999 | C29: 178 | E29: 4
A30: Claus Bech Jørgensen | B30: 1998-2003 | C30: 104 | D30: 1406 | E30: 14 | F30: 4
A31: AFC Bournemouth
A32: Player | B32: Years | C32: Apps | D32: Min | E32: Goals | F32: Ast
A33: Asmir Begović | B33: 2007-2020 | C33: 119 | D33: 10710 | E33: 0 | F33: 1
A34: Narada Bernard | B34: 2000-2002 | C34: 29 | D34: 274 | E34: 0 | F34: 0
A35: Mohamed Berthé | B35: 1998 | C35: 15 | E35: 2
A36: Ryan Bertrand | B36: 2006 | C36: 5 | D36: 450 | E36: 0 | F36: 0
A37: Leon Best | B37: 2006 | C37: 15 | D37: 1088 | E37: 3 | F37: 0
A38: Kevin Betsy | B38: 1999 | C38: 5 | E38: 0
A39: Owen Bevan | B39: 2022 | C39: 2 | D39: 56 | E39: 0 | F39: 0
A40: Nicholas Bignall | B40: 2010 | C40: 5 | D40: 242 | E40: 0 | F40: 0
A41: Philip Billing | B41: 2019-2025 | C41: 199 | D41: 13520 | E41: 31 | F41: 20
A42: David Birmingham | B42: 2000-2001 | C42: 4 | E42: 0
A43: Alan Blayney | B43: 2002 | C43: 2 | D43: 180 | E43: 0 | F43: 0
A44: Roger Boli | B44: 1998-1999 | C44: 6 | E44: 0
A45: Artur Boruc | B45: 2014-2019 | C45: 129 | D45: 11640 | E45: 0 | F45: 0
A46: Lee Bradbury | B46: 2007-2010 | C46: 127 | D46: 9833 | E46: 10 | F46: 11
A47: Robbie Brady | B47: 2021 | C47: 7 | D47: 221 | E47: 0 | F47: 0
A48: Jason Brissett | B48: 1994-1997 | C48: 124 | E48: 8
A49: Karl Broadhurst | B49: 1998-2006 | C49: 185 | D49: 9753 | E49: 3 | F49: 0
A50: David Brooks | B50: 2018-2026 | C50: 182 | D50: 9395 | E50: 24 | F50: 19
A51: Shaun Brooks | B51: 1992-1994 | C51: 1 | E51: 0
A52: Marcus Browning | B52: 2002-2006 | C52: 188 | D52: 13866 | E52: 3 | F52: 8
A53: Ajani Burchall | B53: 2020 | C53: 1 | D53: 4 | E53: 0 | F53: 0
A54: Chris Burns | B54: 1993 | C54: 14 | E54: 1
A55: Matt Butcher | B55: 2015-2018 | C55: 2 | D55: 104 | E55: 0 | F55: 0
A56: Steve Butler | B56: 1992 | C56: 1 | E56: 0
A57: David Button | B57: 2008 | C57: 4 | D57: 360 | E57: 0 | F57: 0
A58: Lewis Buxton | B58: 2002-2003 | C58: 43 | D58: 3389 | E58: 0 | F58: 1
A59: AFC Bournemouth
A60: Player | B60: Years | C60: Apps | D60: Min | E60: Goals | F60: Ast
A61: Nathan Byrne | B61: 2011 | C61: 9 | D61: 736 | E61: 0 | F61: 0
A62: Gary Cahill | B62: 2021 | C62: 22 | D62: 1939 | E62: 0 | F62: 1
A63: Brennan Camp | B63: 2019-2021 | C63: 2 | D63: 91 | E63: 0 | F63: 0
A64: Lee Camp | B64: 2013-2014 | C64: 46 | D64: 4118 | E64: 0 | F64: 0
A65: Todd Cantwell | B65: 2021 | C65: 12 | D65: 684 | E65: 0 | F65: 0
A66: Baily Cargill | B66: 2014-2016 | C66: 11 | D66: 943 | E66: 0 | F66: 0
A67: Josh Carmichael | B67: 2011-2012 | C67: 4 | D67: 219 | E67: 0 | F67: 0
A68: Cameron Carter-Vickers | B68: 2020 | C68: 24 | D68: 2115 | E68: 1 | F68: 0
A69: Chris Casper | B69: 1995 | C69: 16 | E69: 1
A70: Gary Chivers | B70: 1993-1994 | C70: 31 | E70: 2
A71: Iyseden Christie | B71: 1996 | C71: 4 | E71: 0
A72: Ryan Christie | B72: 2021-2026 | C72: 181 | D72: 12009 | E72: 13 | F72: 17
A73: Jean-François Christophe | B73: 2007 | C73: 10 | D73: 486 | E73: 1 | F73: 0
A74: Steve Claridge | B74: 2006 | C74: 1 | D74: 57 | E74: 0 | F74: 0
A75: Nathaniel Clyne | B75: 2018 | C75: 15 | D75: 1233 | E75: 0 | F75: 1
A76: Owen Coll | B76: 1995-1997 | C76: 24 | E76: 0
A77: Jack Collison | B77: 2013 | C77: 4 | D77: 360 | E77: 0 | F77: 0
A78: Alan Connell | B78: 2002-2009 | C78: 104 | D78: 4182 | E78: 13 | F78: 4
A79: Matthew Connolly | B79: 2006 | C79: 5 | D79: 286 | E79: 1 | F79: 0
A80: Lewis Cook | B80: 2016-2026 | C80: 282 | D80: 20323 | E80: 3 | F80: 15
A81: Steve Cook | B81: 2011-2021 | C81: 379 | D81: 33041 | E81: 21 | F81: 10
A82: Richard Cooke | B82: 1992 | C82: 12 | E82: 0
A83: Stephen Cooke | B83: 2001-2006 | C83: 51 | D83: 2423 | E83: 3 | F83: 5
A84: Shaun Cooper | B84: 2005-2011 | C84: 211 | D84: 16855 | E84: 1 | F84: 3
A85: Jack Cork | B85: 2006 | C85: 7 | D85: 559 | E85: 0 | F85: 0
A86: Harry Cornick | B86: 2014 | C86: 1 | D86: 21 | E86: 0 | F86: 0
A87: AFC Bournemouth
A88: Player | B88: Years | C88: Apps | D88: Min | E88: Goals | F88: Ast
A89: Leo Cotterell | B89: 1996-1997 | C89: 9 | E89: 0
A90: Steve Cotterill | B90: 1993-1995 | C90: 45 | E90: 15
A91: Mohamed Coulibaly | B91: 2013 | C91: 7 | D91: 159 | E91: 0 | F91: 0
A92: James Coutts | B92: 2004-2005 | C92: 12 | D92: 272 | E92: 0 | F92: 0
A93: Ian Cox | B93: 1995-1999 | C93: 172 | E93: 16
A94: Martin Cranie | B94: 2004 | C94: 3 | D94: 193 | E94: 0 | F94: 0
A95: Warren Cummings | B95: 2000-2011 | C95: 259 | D95: 19964 | E95: 7 | F95: 20
A96: Jamie Cureton | B96: 1995 | C96: 5 | E96: 0
A97: Malcom Dacosta | B97: 2025-2026 | C97: 1 | D97: 58 | E97: 0 | F97: 1
A98: Lauri Dalla Valle | B98: 2010 | C98: 8 | D98: 365 | E98: 2 | F98: 0
A99: Charlie Daniels | B99: 2011-2019 | C99: 257 | D99: 22013 | E99: 17 | F99: 23
A100: Arnaut Danjuma | B100: 2019-2020 | C100: 50 | D100: 3316 | E100: 15 | F100: 8
...

Sheet Bradford City
A1: Player | B1: Years | C1: Apps | D1: Min | E1: Goals | F1: Ast
A2: Zema Abbey | B2: 2004 | C2: 6 | D2: 440 | E2: 1 | F2: 0
A3: Joe Adams | B3: 2024 | C3: 1 | D3: 17 | E3: 0 | F3: 0
A4: Tayo Adaramola | B4: 2024 | C4: 16 | D4: 1255 | E4: 0 | F4: 3
A5: Dele Adebola | B5: 2004 | C5: 15 | D5: 1150 | E5: 3 | F5: 0
A6: Tom Adeyemi | B6: 2010 | C6: 34 | D6: 2613 | E6: 5 | F6: 1
A7: Chisom Afoka | B7: 2023 | C7: 3 | D7: 143 | E7: 0 | F7: 0
A8: Simon Ainge | B8: 2006-2008 | C8: 14 | D8: 758 | E8: 0 | F8: 0
A9: Hope Akpan | B9: 2018-2019 | C9: 53 | D9: 3772 | E9: 5 | F9: 2
A10: Jak Alnwick | B10: 2014 | C10: 1 | D10: 90 | E10: 0 | F10: 0
A11: Jermaine Anderson | B11: 2018-2019 | C11: 20 | D11: 1154 | E11: 2 | F11: 0
A12: Paul Anderson | B12: 2015-2016 | C12: 16 | D12: 617 | E12: 0 | F12: 0
A13: Lee Angol | B13: 2021-2022 | C13: 38 | D13: 2097 | E13: 7 | F13: 2
A14: Alun Armstrong | B14: 2003 | C14: 6 | D14: 537 | E14: 1 | F14: 0
A15: Craig Armstrong | B15: 2004 | C15: 7 | D15: 398 | E15: 0 | F15: 0
A16: Glenn Arne Hansen | B16: 1995 | C16: 0 | E16: 0
A17: Paul Arnison | B17: 2008 | C17: 27 | D17: 2164 | E17: 0 | F17: 1
A18: Harrison Ashby | B18: 2025 | C18: 8 | D18: 274 | E18: 0 | F18: 0
A19: Moses Ashikodi | B19: 2006 | C19: 8 | D19: 650 | E19: 2 | F19: 1
A20: Peter Atherton | B20: 2000-2004 | C20: 94 | D20: 7986 | E20: 3 | F20: 3
A21: Chris Atkinson | B21: 2013 | C21: 4 | D21: 167 | E21: 0 | F21: 0
A22: Will Atkinson | B22: 2011-2012 | C22: 54 | D22: 3225 | E22: 2 | F22: 4
A23: Phil Babb | B23: 1992 | C23: 0 | E23: 0
A24: Scott Bairstow | B24: 1992 | C24: 0 | E24: 0
A25: Adam Baker | B25: 2011 | C25: 1 | D25: 10 | E25: 0 | F25: 0
A26: Aden Baldwin | B26: 2024-2026 | C26: 76 | D26: 6130 | E26: 4 | F26: 1
A27: David Ball | B27: 2018 | C27: 39 | D27: 2947 | E27: 6 | F27: 3
A28: Scott Banks | B28: 2022 | C28: 32 | D28: 1990 | E28: 6 | F28: 4
A29: Andy Barlow | B29: 1993 | C29: 2 | E29: 0
A30: Lachlan Barr | B30: 2017 | C30: 1 | D30: 14 | E30: 0 | F30: 0
A31: Xavier Barrau | B31: 2006 | C31: 3 | D31: 102 | E31: 2 | F31: 0
A32: Bradford City AFC
A33: Player | B33: Years | C33: Apps | D33: Min | E33: Goals | F33: Ast
A34: Alex Bass | B34: 2021 | C34: 21 | D34: 1890 | E34: 0 | F34: 0
A35: Matthew Bates | B35: 2013 | C35: 22 | D35: 1810 | E35: 0 | F35: 0
A36: Jonathan Bateson | B36: 2009 | C36: 21 | D36: 1417 | E36: 0 | F36: 0
A37: Peter Beagrie | B37: 1997-2000 | C37: 131 | D37: 3676 | E37: 20 | F37: 6
A38: Claus Bech Jørgensen | B38: 2001-2002 | C38: 50 | D38: 3884 | E38: 12 | F38: 7
A39: Jake Beesley | B39: 2026 | C39: 8 | D39: 573 | E39: 0 | F39: 1
A40: Jay Benn | B40: 2024 | C40: 14 | D40: 1069 | E40: 0 | F40: 3
A41: Wayne Benn | B41: 1993-1995 | C41: 10 | E41: 0
A42: Kyle Bennett | B42: 2013 | C42: 18 | D42: 1125 | E42: 1 | F42: 1
A43: Mason Bennett | B43: 2014 | C43: 12 | D43: 439 | E43: 1 | F43: 0
A44: Craig Bentham | B44: 2004-2007 | C44: 30 | D44: 1776 | E44: 0 | F44: 0
A45: Marlon Beresford | B45: 2003 | C45: 5 | D45: 450 | E45: 0 | F45: 0
A46: Ole Bjørn Sundgot | B46: 1996-1997 | C46: 25 | E46: 6
A47: Tommy Black | B47: 2006 | C47: 4 | D47: 246 | E47: 0 | F47: 0
A48: Noel Blake | B48: 1992-1993 | C48: 39 | E48: 3
A49: Robbie Blake | B49: 1996-2000 | C49: 127 | D49: 2936 | E49: 30 | F49: 1
A50: Kwame Boateng | B50: 2016 | C50: 0
A51: Tolaji Bola | B51: 2022 | C51: 4 | D51: 182 | E51: 0 | F51: 0
A52: Adam Bolder | B52: 2009 | C52: 14 | D52: 1225 | E52: 1 | F52: 0
A53: Paul Bolland | B53: 1997-1998 | C53: 12 | E53: 0
A54: Michael Boulding | B54: 2008-2009 | C54: 65 | D54: 4010 | E54: 15 | F54: 3
A55: Rory Boulding | B55: 2008-2009 | C55: 3 | D55: 79 | E55: 0 | F55: 0
A56: Mark Bower | B56: 1997-2008 | C56: 231 | D56: 19673 | E56: 12 | F56: 4
A57: Jordan Bowery | B57: 2015 | C57: 3 | D57: 97 | E57: 0 | F57: 0
A58: Ian Bowling | B58: 1992-1995 | C58: 36 | E58: 0
A59: Michael Branch | B59: 2003 | C59: 33 | D59: 2409 | E59: 6 | F59: 1
A60: Chris Brandon | B60: 2008-2009 | C60: 27 | D60: 1401 | E60: 2 | F60: 0
A61: Guy Branston | B61: 2011 | C61: 16 | D61: 1399 | E61: 1 | F61: 1
A62: Joe Brennan | B62: 2014 | C62: 0
A63: Marc Bridge-Wilkinson | B63: 2004-2006 | C63: 87 | D63: 7579 | E63: 11 | F63: 13
A64: Bradford City AFC
A65: Player | B65: Years | C65: Apps | D65: Min | E65: Goals | F65: Ast
A66: David Brightwell | B66: 1995-1996 | C66: 24 | E66: 0
A67: David Brown | B67: 2007 | C67: 5 | D67: 145 | E67: 1 | F67: 0
A68: Joe Brown | B68: 2005-2006 | C68: 19 | D68: 547 | E68: 1 | F68: 0
A69: Reece Brown | B69: 2010 | C69: 3 | D69: 270 | E69: 0 | F69: 0
A70: Michael Bryan | B70: 2011 | C70: 8 | D70: 375 | E70: 0 | F70: 0
A71: Kai Brünker | B71: 2017-2018 | C71: 29 | D71: 898 | E71: 0 | F71: 0
A72: Wayne Bullimore | B72: 1995-1996 | C72: 2 | E72: 0
A73: Lee Bullock | B73: 2007-2011 | C73: 121 | D73: 9208 | E73: 5 | F73: 4
A74: Oliver Burke | B74: 2014 | C74: 2 | D74: 139 | E74: 0 | F74: 0
A75: Reece Burke | B75: 2015 | C75: 36 | D75: 3075 | E75: 2 | F75: 0
A76: Rumarn Burrell | B76: 2020 | C76: 2 | D76: 12 | E76: 0 | F76: 0
A77: Jacob Butterfield | B77: 2018 | C77: 15 | D77: 1019 | E77: 1 | F77: 0
A78: Neill Byrne | B78: 2024-2025 | C78: 40 | D78: 3001 | E78: 3 | F78: 0
A79: Danny Cadamarteri | B79: 2001-2005 | C79: 91 | D79: 6200 | E79: 7 | F79: 10
A80: Paul Caddis | B80: 2018 | C80: 29 | D80: 2440 | E80: 2 | F80: 1
A81: Jorge Cadete | B81: 1999 | C81: 7 | D81: 264 | E81: 0 | F81: 0
A82: Steven Caldwell | B82: 2001 | C82: 9 | D82: 810 | E82: 0 | F82: 0
A83: David Campbell | B83: 1992 | C83: 0 | E83: 0
A84: Niall Canavan | B84: 2020-2021 | C84: 36 | D84: 3066 | E84: 1 | F84: 1
A85: Benito Carbone | B85: 2000-2001 | C85: 42 | D85: 3444 | E85: 10 | F85: 7
A86: Juan Carricondo | B86: 2001-2002 | C86: 26 | D86: 949 | E86: 1 | F86: 2
A87: Tony Carss | B87: 1993-1994 | C87: 0 | E87: 0
A88: Henry Cartwright | B88: 2026 | C88: 5 | D88: 153 | E88: 0 | F88: 0
A89: Harry Chapman | B89: 2022-2023 | C89: 51 | D89: 2678 | E89: 2 | F89: 5
A90: Adam Chicksen | B90: 2017-2018 | C90: 50 | D90: 4146 | E90: 0 | F90: 3
A91: Chibuzor Chilaka | B91: 2010 | C91: 4 | D91: 107 | E91: 0 | F91: 0
A92: Billy Clarke | B92: 2014-2020 | C92: 161 | D92: 10113 | E92: 30 | F92: 21
A93: Matt Clarke | B93: 1999-2000 | C93: 38 | D93: 3404 | E93: 0 | F93: 0
A94: Matthew Clarke | B94: 2006-2009 | C94: 88 | D94: 7345 | E94: 4 | F94: 1
A95: Nathan Clarke | B95: 2015-2016 | C95: 29 | D95: 2266 | E95: 0 | F95: 3
A96: Bradford City AFC
A97: Player | B97: Years | C97: Apps | D97: Min | E97: Goals | F97: Ast
A98: Tom Clarke | B98: 2008 | C98: 6 | D98: 448 | E98: 0 | F98: 0
A99: Lewis Clarkson | B99: 2013 | C99: 1 | D99: 4 | E99: 0 | F99: 0
A100: Adam Clayton | B100: 2022 | C100: 14 | D100: 1081 | E100: 0 | F100: 3
...

Sheet Brentford
A1: Player | B1: Years | C1: Apps | D1: Min | E1: Goals | F1: Ast
A2: Nathan Abbey | B2: 2006 | C2: 16 | D2: 1440 | E2: 0 | F2: 0
A3: Paul Abrahams | B3: 1994-1996 | C3: 35 | E3: 8
A4: Blair Adams | B4: 2011 | C4: 7 | D4: 510 | E4: 0 | F4: 0
A5: Charlie Adams | B5: 2012-2014 | C5: 4 | D5: 59 | E5: 0 | F5: 0
A6: Nicky Adams | B6: 2010 | C6: 7 | D6: 307 | E6: 0 | F6: 0
A7: Tom Adeyemi | B7: 2012 | C7: 30 | D7: 1821 | E7: 2 | F7: 2
A8: Patrick Agyemang | B8: 1999 | C8: 12 | E8: 0
A9: Lionel Ainsworth | B9: 2009 | C9: 9 | D9: 235 | E9: 0 | F9: 0
A10: Kristoffer Ajer | B10: 2021-2026 | C10: 130 | D10: 9261 | E10: 3 | F10: 6
A11: John Akinde | B11: 2009 | C11: 2 | D11: 143 | E11: 0 | F11: 0
A12: Chuba Akpom | B12: 2013 | C12: 4 | D12: 71 | E12: 0 | F12: 0
A13: Farid El Alagui | B13: 2012-2013 | C13: 23 | D13: 867 | E13: 4 | F13: 4
A14: Gary Alexander | B14: 2010-2011 | C14: 62 | D14: 4826 | E14: 21 | F14: 5
A15: Joe Allon | B15: 1992-1993 | C15: 45 | E15: 19
A16: Mikkel Andersen | B16: 2008 | C16: 1 | D16: 90 | E16: 0 | F16: 0
A17: Ijah Anderson | B17: 1995-2002 | C17: 202 | D17: 810 | E17: 4 | F17: 0
A18: Darren Annon | B18: 1993-1995 | C18: 20 | E18: 2
A19: Andy Ansah | B19: 1994-1995 | C19: 9 | E19: 2
A20: Jaidon Anthony | B20: 2026 | C20: 6 | D20: 292 | E20: 0 | F20: 3
A21: Mickaël Antoine-Curier | B21: 2002 | C21: 11 | D21: 898 | E21: 3 | F21: 1
A22: Theo Archibald | B22: 2017-2018 | C22: 3 | D22: 72 | E22: 0 | F22: 0
A23: Benjamin Arthur | B23: 2023-2025 | C23: 3 | D23: 171 | E23: 0 | F23: 0
A24: Frankie Artus | B24: 2008 | C24: 1 | D24: 13 | E24: 0 | F24: 0
A25: Carl Asaba | B25: 1994-1996 | C25: 54 | E25: 25
A26: Barry Ashby | B26: 1993-1996 | C26: 121 | E26: 4
A27: Warren Aspinall | B27: 1997-1998 | C27: 43 | E27: 5
A28: Kevin Austin | B28: 2000 | C28: 3 | E28: 0
A29: Brentford FC
A30: Player | B30: Years | C30: Apps | D30: Min | E30: Goals | F30: Ast
A31: Dennis Bailey | B31: 1994 | C31: 6 | E31: 3
A32: Ellery Balcombe | B32: 2016-2026 | C32: 2 | D32: 210 | E32: 0 | F32: 0
A33: Pim Balkestein | B33: 2009-2011 | C33: 39 | D33: 2939 | E33: 2 | F33: 1
A34: Ademola Bankole | B34: 2004-2005 | C34: 5 | D34: 431 | E34: 0 | F34: 0
A35: Shandon Baptiste | B35: 2019-2023 | C35: 77 | D35: 2590 | E35: 2 | F35: 5
A36: Yoann Barbet | B36: 2015-2018 | C36: 118 | D36: 9592 | E36: 7 | F36: 4
A37: Scott Barron | B37: 2012-2013 | C37: 14 | D37: 724 | E37: 0 | F37: 0
A38: Paul Barrowcliff | B38: 1997 | C38: 11 | E38: 0
A39: Grant Basey | B39: 2007 | C39: 8 | D39: 692 | E39: 0 | F39: 0
A40: Jamie Bates | B40: 1992-1998 | C40: 247 | E40: 12
A41: Ashley Bayes | B41: 1992 | C41: 2 | E41: 0
A42: Peter Beadle | B42: 2003 | C42: 1 | D42: 12 | E42: 0 | F42: 0
A43: Marcus Bean | B43: 2008-2011 | C43: 144 | D43: 10791 | E43: 14 | F43: 4
A44: Mads Bech Sørensen | B44: 2017-2022 | C44: 72 | D44: 5570 | E44: 4 | F44: 0
A45: Ian Benjamin | B45: 1993-1994 | C45: 15 | E45: 2
A46: Alan Bennett | B46: 2007-2009 | C46: 68 | D46: 5915 | E46: 2 | F46: 0
A47: Dale Bennett | B47: 2011 | C47: 5 | D47: 422 | E47: 1 | F47: 0
A48: Mickey Bennett | B48: 1992-1993 | C48: 46 | E48: 4
A49: Saïd Benrahma | B49: 2018-2020 | C49: 91 | D49: 6501 | E49: 30 | F49: 24
A50: Graham Benstead | B50: 1992-1997 | C50: 31 | E50: 0
A51: Marcus Bent | B51: 1995-1997 | C51: 70 | E51: 8
A52: Daniel Bentley | B52: 2016-2018 | C52: 125 | D52: 11234 | E52: 0 | F52: 0
A53: Luka Bentt | B53: 2025 | C53: 1 | D53: 1 | E53: 0 | F53: 0
A54: Saido Berahino | B54: 2011 | C54: 8 | D54: 467 | E54: 4 | F54: 0
A55: Mohamed Berthé | B55: 1998 | C55: 9 | E55: 0
A56: Betinho | B56: 2014 | C56: 1 | D56: 14 | E56: 0 | F56: 0
A57: Mads Bidstrup | B57: 2020-2021 | C57: 12 | D57: 372 | E57: 0 | F57: 2
A58: Jake Bidwell | B58: 2011-2015 | C58: 195 | D58: 16964 | E58: 2 | F58: 14
A59: Nicholas Bignall | B59: 2010 | C59: 6 | D59: 172 | E59: 0 | F59: 0
A60: Brentford FC
A61: Player | B61: Years | C61: Apps | D61: Min | E61: Goals | F61: Ast
A62: Andreas Bjelland | B62: 2015-2017 | C62: 65 | D62: 5130 | E62: 1 | F62: 4
A63: Lloyd Blackman | B63: 2002-2003 | C63: 4 | D63: 126 | E63: 0 | F63: 0
A64: Ryan Blake | B64: 2009 | C64: 1 | D64: 31 | E64: 0 | F64: 0
A65: Steven Blaney | B65: 1997 | C65: 5 | E65: 0
A66: Gary Blissett | B66: 1992-1993 | C66: 46 | E66: 21
A67: Jack Bonham | B67: 2013-2018 | C67: 5 | D67: 454 | E67: 0 | F67: 0
A68: Bob Booker | B68: 1992-1993 | C68: 3 | E68: 0
A69: John Bostock | B69: 2009 | C69: 9 | D69: 715 | E69: 2 | F69: 1
A70: Dean Bowditch | B70: 2008 | C70: 9 | D70: 716 | E70: 2 | F70: 0
A71: Danny Boxall | B71: 1998-2001 | C71: 68 | E71: 1
A72: Ethan Brierley | B72: 2023 | C72: 1 | D72: 43 | E72: 0 | F72: 0
A73: Paul Brooker | B73: 2005-2007 | C73: 71 | D73: 4788 | E73: 4 | F73: 11
A74: Drewe Broughton | B74: 1998 | C74: 1 | E74: 0
A75: Simon Brown | B75: 2007-2008 | C75: 27 | D75: 2281 | E75: 0 | F75: 0
A76: Wayne Brown | B76: 2007 | C76: 11 | D76: 515 | E76: 1 | F76: 0
A77: Derek Bryan | B77: 1997-2001 | C77: 50 | E77: 7
A78: Paul Buckle | B78: 1992-1993 | C78: 5 | E78: 0
A79: Nikki Bull | B79: 2009 | C79: 6 | D79: 474 | E79: 0 | F79: 0
A80: Ronnie Bull | B80: 2003 | C80: 20 | D80: 1763 | E80: 0 | F80: 1
A81: Ben Burgess | B81: 2001 | C81: 43 | E81: 17
A82: Deon Burton | B82: 2004 | C82: 40 | D82: 3181 | E82: 10 | F82: 3
A83: David Button | B83: 2013-2015 | C83: 136 | D83: 12176 | E83: 0 | F83: 0
A84: Nathan Byrne | B84: 2010 | C84: 11 | D84: 449 | E84: 0 | F84: 1
A85: DJ Campbell | B85: 2005 | C85: 23 | D85: 1325 | E85: 9 | F85: 2
A86: Scott Canham | B86: 1995-1997 | C86: 49 | E86: 1
A87: Sergi Canós | B87: 2015-2022 | C87: 244 | D87: 13552 | E87: 36 | F87: 28
A88: Karle Carder-Andrews | B88: 2006 | C88: 5 | D88: 141 | E88: 0 | F88: 0
A89: João Carlos Teixeira | B89: 2013 | C89: 2 | D89: 23 | E89: 0 | F89: 0
A90: Brentford FC
A91: Player | B91: Years | C91: Apps | D91: Min | E91: Goals | F91: Ast
A92: Trevor Carson | B92: 2010 | C92: 1 | D92: 90 | E92: 0 | F92: 0
A93: Fabio Carvalho | B93: 2024-2026 | C93: 35 | D93: 1369 | E93: 8 | F93: 4
A94: Grant Chalmers | B94: 1992-1993 | C94: 11 | E94: 1
A95: Darius Charles | B95: 2004-2007 | C95: 35 | D95: 1860 | E95: 1 | F95: 1
A96: Julian Charles | B96: 1999-2001 | C96: 12 | E96: 0
A97: Ilias Chatzitheodoridis | B97: 2016-2017 | C97: 4 | D97: 338 | E97: 0 | F97: 0
A98: Ben Chorley | B98: 2002 | C98: 2 | D98: 180 | E98: 0 | F98: 0
A99: Steve Claridge | B99: 2004 | C99: 4 | D99: 230 | E99: 0 | F99: 0
A100: Dean Clark | B100: 1997-2000 | C100: 4 | E100: 0
...

Sheet Bristol City
A1: Player | B1: Years | C1: Apps | D1: Min | E1: Goals | F1: Ast
A2: Adam El-Abd | B2: 2013-2015 | C2: 18 | D2: 1252 | E2: 0 | F2: 0
A3: Tammy Abraham | B3: 2016 | C3: 48 | D3: 3736 | E3: 26 | F3: 3
A4: Dele Adebola | B4: 2007-2008 | C4: 56 | D4: 4065 | E4: 16 | F4: 6
A5: Hakeeb Adelakun | B5: 2018-2020 | C5: 9 | D5: 386 | E5: 0 | F5: 1
A6: Albert Adomah | B6: 2010-2012 | C6: 131 | D6: 10097 | E6: 17 | F6: 27
A7: Benik Afobe | B7: 2019 | C7: 12 | D7: 739 | E7: 3 | F7: 0
A8: Kieran Agard | B8: 2014-2015 | C8: 70 | D8: 3902 | E8: 17 | F8: 4
A9: Lily Agg | B9: 2017 | C9: 3 | D9: 110 | E9: 1 | F9: 0
A10: Patrick Agyemang | B10: 2009 | C10: 7 | D10: 483 | E10: 0 | F10: 0
A11: Toby Ajala | B11: 2012 | C11: 2 | D11: 7 | E11: 0 | F11: 0
A12: John Akinde | B12: 2008-2010 | C12: 16 | D12: 479 | E12: 1 | F12: 0
A13: Megan Alexander | B13: 2017 | C13: 6 | D13: 532 | E13: 0 | F13: 0
A14: Flo Allen | B14: 2017-2020 | C14: 43 | D14: 2921 | E14: 0 | F14: 0
A15: Kevin Amankwaah | B15: 2002-2004 | C15: 11 | D15: 493 | E15: 0 | F15: 1
A16: Paul Anderson | B16: 2012 | C16: 29 | D16: 1585 | E16: 3 | F16: 2
A17: Calvin Andrew | B17: 2005 | C17: 3 | D17: 155 | E17: 0 | F17: 1
A18: Jake Andrews | B18: 2017 | C18: 0
A19: Wayne Andrews | B19: 2006 | C19: 7 | D19: 301 | E19: 2 | F19: 0
A20: Joe Anyinsah | B20: 2004 | C20: 7 | D20: 228 | E20: 0 | F20: 0
A21: Raphael Araoye | B21: 2023 | C21: 0
A22: Sinclair Armstrong | B22: 2024-2025 | C22: 82 | D22: 3380 | E22: 7 | F22: 0
A23: Chloe Arthur | B23: 2017 | C23: 23 | D23: 2003 | E23: 2 | F23: 1
A24: Brooke Aspin | B24: 2023 | C24: 17 | D24: 1368 | E24: 2 | F24: 0
A25: Robert Atkinson | B25: 2021-2026 | C25: 95 | D25: 7412 | E25: 10 | F25: 3
A26: Rosella Ayane | B26: 2018 | C26: 15 | D26: 795 | E26: 1 | F26: 0
A27: Luke Ayling | B27: 2014-2016 | C27: 89 | D27: 7555 | E27: 4 | F27: 5
A28: Tommy Backwell | B28: 2023 | C28: 0
A29: Sophie Baggaley | B29: 2017-2020 | C29: 72 | D29: 6480 | E29: 0 | F29: 0
A30: Stefan Bajic | B30: 2022-2024 | C30: 2 | D30: 180 | E30: 0 | F30: 0
A31: Nathan Baker | B31: 2015-2021 | C31: 148 | D31: 11045 | E31: 4 | F31: 3
A32: Bristol City FC
A33: Player | B33: Years | C33: Apps | D33: Min | E33: Goals | F33: Ast
A34: Tyreeq Bakinson | B34: 2017-2021 | C34: 54 | D34: 3246 | E34: 5 | F34: 1
A35: Sam Baldock | B35: 2012-2014 | C35: 84 | D35: 6528 | E35: 34 | F35: 6
A36: Tyrone Barnett | B36: 2013 | C36: 17 | D36: 717 | E36: 1 | F36: 1
A37: Adriano Basso | B37: 2005-2009 | C37: 166 | D37: 14587 | E37: 0 | F37: 0
A38: Matthew Bates | B38: 2012 | C38: 13 | D38: 1062 | E38: 0 | F38: 0
A39: Peter Beadle | B39: 2002 | C39: 24 | D39: 1063 | E39: 4 | F39: 2
A40: Micky Bell | B40: 2002-2004 | C40: 96 | D40: 7237 | E40: 3 | F40: 5
A41: Sam Bell | B41: 2020-2026 | C41: 118 | D41: 4988 | E41: 15 | F41: 5
A42: Ayman Benarous | B42: 2021 | C42: 12 | D42: 681 | E42: 0 | F42: 0
A43: Filip Benković | B43: 2019 | C43: 10 | D43: 644 | E43: 2 | F43: 0
A44: Elliott Bennett | B44: 2015 | C44: 15 | D44: 1259 | E44: 0 | F44: 1
A45: Daniel Bentley | B45: 2019-2022 | C45: 143 | D45: 12811 | E45: 0 | F45: 0
A46: Francesca Bentley | B46: 2023 | C46: 5 | D46: 450 | E46: 0 | F46: 0
A47: Kevin Betsy | B47: 2006-2007 | C47: 18 | D47: 1485 | E47: 1 | F47: 3
A48: Julie Biesmans | B48: 2017-2018 | C48: 36 | D48: 3198 | E48: 1 | F48: 2
A49: André Bikey | B49: 2011 | C49: 7 | D49: 630 | E49: 0 | F49: 0
A50: Max Bird | B50: 2024-2026 | C50: 66 | D50: 4298 | E50: 3 | F50: 9
A51: Emma Bissell | B51: 2020 | C51: 18 | D51: 794 | E51: 1 | F51: 0
A52: Yannick Bolasie | B52: 2011 | C52: 23 | D52: 727 | E52: 1 | F52: 0
A53: Jodie Brett | B53: 2017 | C53: 8 | D53: 720 | E53: 0 | F53: 0
A54: Michael Bridges | B54: 2005 | C54: 11 | D54: 510 | E54: 0 | F54: 0
A55: Matthew Briggs | B55: 2012 | C55: 4 | D55: 360 | E55: 0 | F55: 0
A56: Louis Britton | B56: 2020 | C56: 1 | D56: 19 | E56: 1 | F56: 0
A57: Steve Brooker | B57: 2004-2008 | C57: 101 | D57: 7398 | E57: 37 | F57: 13
A58: Aaron Brown | B58: 2002-2003 | C58: 59 | D58: 4132 | E58: 7 | F58: 5
A59: Frankie Brown | B59: 2017-2019 | C59: 49 | D59: 4171 | E59: 0 | F59: 1
A60: Marvin Brown | B60: 2002-2003 | C60: 5 | D60: 247 | E60: 1 | F60: 0
A61: Scott Brown | B61: 2004-2006 | C61: 63 | D61: 4079 | E61: 5 | F61: 5
A62: Josh Brownhill | B62: 2016-2019 | C62: 161 | D62: 13057 | E62: 17 | F62: 14
A63: Chris Brunt | B63: 2020 | C63: 14 | D63: 608 | E63: 0 | F63: 0
A64: Bristol City FC
A65: Player | B65: Years | C65: Apps | D65: Min | E65: Goals | F65: Ast
A66: Joe Bryan | B66: 2011-2018 | C66: 219 | D66: 16751 | E66: 20 | F66: 26
A67: Faye Bryson | B67: 2019-2020 | C67: 18 | D67: 923 | E67: 1 | F67: 0
A68: Jasmine Bull | B68: 2023 | C68: 9 | D68: 334 | E68: 0 | F68: 0
A69: Joe Burnell | B69: 2002-2003 | C69: 61 | D69: 4958 | E69: 1 | F69: 0
A70: Wes Burns | B70: 2012-2015 | C70: 49 | D70: 1149 | E70: 3 | F70: 0
A71: Tony Butler | B71: 2002-2004 | C71: 98 | D71: 8577 | E71: 4 | F71: 1
A72: Darren Byfield | B72: 2007 | C72: 33 | D72: 1784 | E72: 8 | F72: 0
A73: Jamal Campbell-Ryce | B73: 2009-2011 | C73: 62 | D73: 4026 | E73: 2 | F73: 8
A74: Louis Carey | B74: 2002-2013 | C74: 312 | D74: 26503 | E74: 9 | F74: 6
A75: Nick Carle | B75: 2007 | C75: 17 | D75: 1119 | E75: 0 | F75: 0
A76: Steven Caulker | B76: 2010 | C76: 29 | D76: 2476 | E76: 2 | F76: 1
A77: Olivia Chance | B77: 2019 | C77: 14 | D77: 1021 | E77: 0 | F77: 0
A78: Kalifa Cissé | B78: 2010-2011 | C78: 61 | D78: 3872 | E78: 2 | F78: 1
A79: Olivia Clark | B79: 2023 | C79: 7 | D79: 584 | E79: 0 | F79: 0
A80: David Clarkson | B80: 2009-2011 | C80: 64 | D80: 2537 | E80: 11 | F80: 7
A81: Simon Clist | B81: 2002-2003 | C81: 4 | D81: 163 | E81: 1 | F81: 0
A82: Danny Coles | B82: 2002-2004 | C82: 122 | D82: 10578 | E82: 5 | F82: 4
A83: Maisy Collis | B83: 2019-2020 | C83: 1 | D83: 34 | E83: 0 | F83: 0
A84: Megan Connolly | B84: 2023 | C84: 22 | D84: 1930 | E84: 1 | F84: 1
A85: Tommy Conway | B85: 2020-2023 | C85: 92 | D85: 5019 | E85: 25 | F85: 6
A86: Izzy Cook | B86: 2020 | C86: 0
A87: Harry Cornick | B87: 2022-2025 | C87: 67 | D87: 2176 | E87: 5 | F87: 2
A88: Barry Corr | B88: 2006 | C88: 3 | D88: 109 | E88: 0 | F88: 0
A89: David Cotterill | B89: 2004-2016 | C89: 75 | D89: 5229 | E89: 10 | F89: 6
A90: Simon Cox | B90: 2015 | C90: 4 | D90: 63 | E90: 0 | F90: 0
A91: Eartha Cumings Budd | B91: 2018-2019 | C91: 0
A92: Robbie Cundy | B92: 2021 | C92: 14 | D92: 896 | E92: 0 | F92: 0
A93: Greg Cunningham | B93: 2012-2014 | C93: 94 | D93: 6734 | E93: 5 | F93: 6
A94: Yana Daniels | B94: 2017-2020 | C94: 53 | D94: 4208 | E94: 4 | F94: 4
A95: Neil Danns | B95: 2012 | C95: 9 | D95: 794 | E95: 2 | F95: 0
A96: Bristol City FC
A97: Player | B97: Years | C97: Apps | D97: Min | E97: Goals | F97: Ast
A98: Jay Dasilva | B98: 2018-2022 | C98: 144 | D98: 10813 | E98: 2 | F98: 11
A99: Steve Davies | B99: 2012 | C99: 37 | D99: 2006 | E99: 13 | F99: 2
A100: Yas Davies | B100: 2023 | C100: 0
...

Sheet Bristol Rovers
A1: Player | B1: Years | C1: Apps | D1: Min | E1: Goals | F1: Ast
A2: Timmy Abraham | B2: 2019 | C2: 4 | D2: 79 | E2: 0 | F2: 0
A3: Victor Adeboyejo | B3: 2019 | C3: 25 | D3: 925 | E3: 1 | F3: 0
A4: Junior Agogo | B4: 2003-2006 | C4: 126 | D4: 9612 | E4: 42 | F4: 10
A5: Brandon Aguilera | B5: 2023 | C5: 12 | D5: 753 | E5: 2 | F5: 0
A6: John Akinde | B6: 2010 | C6: 14 | D6: 758 | E6: 0 | F6: 2
A7: Bradley Allen | B7: 2002 | C7: 8 | D7: 421 | E7: 1 | F7: 0
A8: Mikkel Andersen | B8: 2009-2010 | C8: 58 | D8: 5220 | E8: 0 | F8: 0
A9: Elliot Anderson | B9: 2021 | C9: 21 | D9: 1758 | E9: 7 | F9: 6
A10: Harry Anderson | B10: 2021-2022 | C10: 77 | D10: 5135 | E10: 6 | F10: 5
A11: Ijah Anderson | B11: 2002-2003 | C11: 53 | D11: 4463 | E11: 0 | F11: 0
A12: John Anderson | B12: 2003-2005 | C12: 54 | D12: 4078 | E12: 2 | F12: 0
A13: Nick Anderton | B13: 2021 | C13: 38 | D13: 2785 | E13: 2 | F13: 2
A14: Wayne Andrews | B14: 2007 | C14: 1 | D14: 20 | E14: 0 | F14: 0
A15: Alexis André | B15: 2017-2020 | C15: 0
A16: Alexis André Jr. | B16: 2017 | C16: 1 | D16: 30 | E16: 0 | F16: 0
A17: Byron Anthony | B17: 2006-2011 | C17: 163 | D17: 13815 | E17: 7 | F17: 1
A18: Micah Anthony | B18: 2024 | C18: 0
A19: Joe Anyinsah | B19: 2011-2012 | C19: 62 | D19: 3859 | E19: 8 | F19: 3
A20: Liam Armstrong | B20: 2020 | C20: 0
A21: Neil Arndale | B21: 2002-2003 | C21: 4 | D21: 175 | E21: 0 | F21: 0
A22: Vitālijs Astafjevs | B22: 2002 | C22: 33 | D22: 2337 | E22: 8 | F22: 3
A23: Kevin Austin | B23: 2002-2003 | C23: 56 | D23: 4566 | E23: 0 | F23: 1
A24: Jonah Ayunga | B24: 2020 | C24: 32 | D24: 1590 | E24: 2 | F24: 1
A25: Elkan Baggott | B25: 2023 | C25: 14 | D25: 1036 | E25: 1 | F25: 1
A26: Mohammad Baghdadi | B26: 2017 | C26: 2 | D26: 35 | E26: 0 | F26: 0
A27: Ángelo Balanta | B27: 2014 | C27: 16 | D27: 529 | E27: 1 | F27: 1
A28: Ellery Balcombe | B28: 2022 | C28: 8 | D28: 640 | E28: 0 | F28: 0
A29: Jack Baldwin | B29: 2020-2021 | C29: 46 | D29: 3526 | E29: 2 | F29: 0
A30: Pat Baldwin | B30: 2009 | C30: 6 | D30: 540 | E30: 0 | F30: 0
A31: Adam Barrett | B31: 2002-2003 | C31: 90 | D31: 8048 | E31: 5 | F31: 4
A32: Bristol Rovers FC
A33: Player | B33: Years | C33: Apps | D33: Min | E33: Goals | F33: Ast
A34: Josh Barrett | B34: 2019-2020 | C34: 17 | D34: 440 | E34: 0 | F34: 0
A35: Jon Bass | B35: 2004-2005 | C35: 12 | D35: 898 | E35: 0 | F35: 1
A36: Chris Beardsley | B36: 2013 | C36: 24 | D36: 1455 | E36: 1 | F36: 1
A37: James Belshaw | B37: 2021-2023 | C37: 88 | D37: 7940 | E37: 0 | F37: 2
A38: Kyle Bennett | B38: 2017-2019 | C38: 55 | D38: 3307 | E38: 4 | F38: 2
A39: Scott Bevan | B39: 2011 | C39: 37 | D39: 3285 | E39: 0 | F39: 0
A40: Bryant Bilongo | B40: 2024-2025 | C40: 28 | D40: 1418 | E40: 1 | F40: 2
A41: Jamal Blackman | B41: 2019 | C41: 10 | D41: 900 | E41: 0 | F41: 0
A42: Nathan Blissett | B42: 2014-2015 | C42: 24 | D42: 1468 | E42: 5 | F42: 2
A43: Dominic Blizzard | B43: 2009-2010 | C43: 39 | D43: 2133 | E43: 1 | F43: 1
A44: Hiram Boateng | B44: 2016 | C44: 10 | D44: 690 | E44: 0 | F44: 3
A45: Billy Bodin | B45: 2015-2017 | C45: 103 | D45: 7330 | E45: 37 | F45: 12
A46: Lamare Bogarde | B46: 2022-2023 | C46: 33 | D46: 2106 | E46: 0 | F46: 2
A47: Marc Bola | B47: 2017 | C47: 20 | D47: 1605 | E47: 0 | F47: 1
A48: Cian Bolger | B48: 2010-2012 | C48: 48 | D48: 4132 | E48: 2 | F48: 1
A49: Andrew Bond | B49: 2013 | C49: 5 | D49: 431 | E49: 0 | F49: 1
A50: Jack Bonham | B50: 2018 | C50: 40 | D50: 3558 | E50: 0 | F50: 0
A51: Steve Book | B51: 2005 | C51: 1 | D51: 90 | E51: 0 | F51: 0
A52: Danny Boxall | B52: 2002-2003 | C52: 63 | D52: 5173 | E52: 0 | F52: 1
A53: Owen Brain | B53: 2021 | C53: 0
A54: Guy Branston | B54: 2012 | C54: 4 | D54: 358 | E54: 1 | F54: 0
A55: Tom Broadbent | B55: 2017-2018 | C55: 32 | D55: 2508 | E55: 0 | F55: 0
A56: Fabian Broghammer | B56: 2012-2013 | C56: 40 | D56: 2408 | E56: 3 | F56: 1
A57: Ryan Broom | B57: 2015-2017 | C57: 11 | D57: 168 | E57: 0 | F57: 0
A58: Jevani Brown | B58: 2023-2024 | C58: 37 | D58: 1999 | E58: 2 | F58: 5
A59: Junior Brown | B59: 2021 | C59: 6 | D59: 294 | E59: 0 | F59: 0
A60: Lee Brown | B60: 2011-2017 | C60: 297 | D60: 25374 | E60: 22 | F60: 36
A61: Wayne Brown | B61: 2009-2012 | C61: 57 | D61: 2961 | E61: 3 | F61: 5
A62: Ryan Brunt | B62: 2012-2014 | C62: 36 | D62: 2462 | E62: 5 | F62: 2
A63: Simon Bryant | B63: 2002-2003 | C63: 34 | D63: 2092 | E63: 1 | F63: 3
A64: Bristol Rovers FC
A65: Player | B65: Years | C65: Apps | D65: Min | E65: Goals | F65: Ast
A66: Joseph Budd | B66: 2021 | C66: 0
A67: Lini Burden | B67: 2022 | C67: 0
A68: Jonny Burn | B68: 2016-2017 | C68: 3 | D68: 198 | E68: 0 | F68: 0
A69: Liam Burns | B69: 2004 | C69: 3 | D69: 243 | E69: 0 | F69: 0
A70: Matt Butcher | B70: 2024 | C70: 18 | D70: 1466 | E70: 0 | F70: 3
A71: Stuart Campbell | B71: 2004-2011 | C71: 288 | D71: 23792 | E71: 2 | F71: 46
A72: Mustapha Carayol | B72: 2011 | C72: 30 | D72: 2019 | E72: 4 | F72: 5
A73: Wayne Carlisle | B73: 2002-2003 | C73: 66 | D73: 4935 | E73: 14 | F73: 13
A74: Chris Carruthers | B74: 2004-2007 | C74: 100 | D74: 7800 | E74: 1 | F74: 7
A75: Brian Cash | B75: 2004 | C75: 1 | D75: 11 | E75: 0 | F75: 0
A76: Trevor Challis | B76: 2002 | C76: 16 | D76: 1273 | E76: 0 | F76: 0
A77: Aaron Chapman | B77: 2015 | C77: 5 | D77: 450 | E77: 0 | F77: 0
A78: James Clarke | B78: 2015-2018 | C78: 120 | D78: 9265 | E78: 2 | F78: 5
A79: Leon Clarke | B79: 2021 | C79: 11 | D79: 274 | E79: 2 | F79: 0
A80: Ollie Clarke | B80: 2010-2019 | C80: 251 | D80: 18571 | E80: 20 | F80: 7
A81: Ryan Clarke | B81: 2002-2004 | C81: 22 | D81: 1980 | E81: 0 | F81: 0
A82: Trevor Clarke | B82: 2021-2022 | C82: 19 | D82: 852 | E82: 0 | F82: 1
A83: Jonson Clarke-Harris | B83: 2018-2019 | C83: 49 | D83: 3886 | E83: 27 | F83: 1
A84: Jake Clarke-Salter | B84: 2016 | C84: 13 | D84: 897 | E84: 1 | F84: 0
A85: David Clarkson | B85: 2012-2013 | C85: 60 | D85: 4122 | E85: 12 | F85: 2
A86: Charlie Clough | B86: 2007-2010 | C86: 3 | D86: 131 | E86: 0 | F86: 0
A87: Seanan Clucas | B87: 2012-2013 | C87: 36 | D87: 2253 | E87: 0 | F87: 1
A88: Josh Coburn | B88: 2022 | C88: 36 | D88: 2391 | E88: 10 | F88: 0
A89: Danny Coles | B89: 2007-2010 | C89: 102 | D89: 8894 | E89: 3 | F89: 3
A90: Charlie Colkett | B90: 2016 | C90: 15 | D90: 687 | E90: 3 | F90: 1
A91: Aaron Collins | B91: 2021-2023 | C91: 129 | D91: 9840 | E91: 38 | F91: 21
A92: James Connolly | B92: 2021-2023 | C92: 70 | D92: 5262 | E92: 2 | F92: 1
A93: Kamil Conteh | B93: 2023-2025 | C93: 68 | D93: 5226 | E93: 1 | F93: 1
A94: Adrian Coote | B94: 2002 | C94: 5 | D94: 371 | E94: 1 | F94: 0
A95: Paul Coutts | B95: 2021-2022 | C95: 65 | D95: 4875 | E95: 1 | F95: 5
A96: Bristol Rovers FC
A97: Player | B97: Years | C97: Apps | D97: Min | E97: Goals | F97: Ast
A98: Paris Cowan-Hall | B98: 2015 | C98: 3 | D98: 131 | E98: 0 | F98: 0
A99: Matthew Cox | B99: 2023 | C99: 33 | D99: 2970 | E99: 0 | F99: 0
A100: Tony Craig | B100: 2017-2019 | C100: 108 | D100: 9664 | E100: 6 | F100: 1
...

Sheet Brighton & Hove Albion
A1: Player | B1: Years | C1: Apps | D1: Min | E1: Goals | F1: Ast
A2: Adam El-Abd | B2: 2003-2013 | C2: 300 | D2: 23651 | E2: 5 | F2: 4
A3: David Adekola | B3: 1996 | C3: 1 | E3: 0
A4: Sam Adekugbe | B4: 2016 | C4: 5 | D4: 450 | E4: 1 | F4: 0
A5: Simon Adingra | B5: 2023-2024 | C5: 73 | D5: 4261 | E5: 12 | F5: 5
A6: Torbjørn Agdestein | B6: 2011-2012 | C6: 6 | D6: 74 | E6: 0 | F6: 1
A7: Kemy Agustien | B7: 2013-2014 | C7: 14 | D7: 655 | E7: 0 | F7: 1
A8: Michelle Agyemang | B8: 2024-2025 | C8: 22 | D8: 1024 | E8: 4 | F8: 1
A9: Soufyan Ahannach | B9: 2017-2019 | C9: 16 | D9: 1137 | E9: 1 | F9: 4
A10: Ade Akinbiyi | B10: 1994 | C10: 7 | E10: 4
A11: Chuba Akpom | B11: 2016 | C11: 10 | D11: 186 | E11: 0 | F11: 0
A12: Derek Allan | B12: 1995-1998 | C12: 80 | E12: 2
A13: Steven Alzate | B13: 2017-2023 | C13: 72 | D13: 4792 | E13: 5 | F13: 3
A14: Mikkel Andersen | B14: 2008 | C14: 5 | D14: 450 | E14: 0 | F14: 0
A15: Florin Andone | B15: 2018-2021 | C15: 32 | D15: 1329 | E15: 6 | F15: 0
A16: Calvin Andrew | B16: 2008 | C16: 9 | D16: 518 | E16: 3 | F16: 0
A17: Ben Andrews | B17: 1997-2000 | C17: 4 | E17: 0
A18: Keith Andrews | B18: 2013 | C18: 31 | D18: 2567 | E18: 1 | F18: 2
A19: Phil Andrews | B19: 1993-1996 | C19: 25 | E19: 1
A20: Casper Ankergren | B20: 2010-2016 | C20: 70 | D20: 6139 | E20: 0 | F20: 0
A21: Andy Ansah | B21: 1997-1998 | C21: 25 | E21: 3
A22: Joe Anyinsah | B22: 2008 | C22: 11 | D22: 828 | E22: 0 | F22: 0
A23: Diego Arismendi | B23: 2009 | C23: 6 | D23: 197 | E23: 0 | F23: 0
A24: Paul Armstrong | B24: 1997-1999 | C24: 53 | E24: 2
A25: Andy Arnott | B25: 1998-1999 | C25: 28 | E25: 2
A26: Warren Aspinall | B26: 1999-2000 | C26: 32 | E26: 3
A27: Gai Assulin | B27: 2011 | C27: 7 | D27: 185 | E27: 0 | F27: 0
A28: Graeme Atkinson | B28: 1997-1998 | C28: 16 | E28: 0
A29: Brighton & Hove Albion FC
A30: Player | B30: Years | C30: Apps | D30: Min | E30: Goals | F30: Ast
A31: Bigo Atom | B31: 2023-2025 | C31: 25 | D31: 1792 | E31: 1 | F31: 1
A32: Marit Auée | B32: 2024-2025 | C32: 14 | D32: 551 | E32: 0 | F32: 1
A33: Yasin Ayari | B33: 2022-2026 | C33: 78 | D33: 4609 | E33: 7 | F33: 4
A34: Rinsola Babajide | B34: 2021 | C34: 3 | D34: 93 | E34: 0 | F34: 0
A35: Sophie Baggaley | B35: 2023-2025 | C35: 36 | D35: 3240 | E35: 0 | F35: 0
A36: Ian Baird | B36: 1996-1997 | C36: 44 | E36: 14
A37: Sam Baldock | B37: 2014-2017 | C37: 96 | D37: 6604 | E37: 21 | F37: 16
A38: Carlos Baleba | B38: 2023-2025 | C38: 112 | D38: 6539 | E38: 4 | F38: 2
A39: Leon Balogun | B39: 2018-2019 | C39: 12 | D39: 939 | E39: 1 | F39: 0
A40: Libby Bance | B40: 2019-2022 | C40: 30 | D40: 1039 | E40: 0 | F40: 0
A41: Al Bangura | B41: 2008 | C41: 6 | D41: 515 | E41: 0 | F41: 0
A42: Ben Barclay | B42: 2017-2026 | C42: 33 | D42: 2636 | E42: 3 | F42: 0
A43: Valentín Barco | B43: 2023-2024 | C43: 7 | D43: 318 | E43: 0 | F43: 0
A44: George Barker | B44: 2012-2013 | C44: 4 | D44: 34 | E44: 0 | F44: 0
A45: Richie Barker | B45: 1997-1998 | C45: 60 | E45: 12
A46: Ashley Barnes | B46: 2009-2013 | C46: 149 | D46: 10288 | E46: 46 | F46: 14
